Workbook

Sheet Inputs
A1: Securitization waterfall: inputs (synthetic data, not a real transaction)
A3: Selected scenario number | B3: 1 | C3: 1 to 6 standard; 7 to 10 custom slots
A4: Selected cpr | B4: =INDEX(Inputs!$B$45:$B$54,Inputs!$B$3) -> 0.1
A5: Selected cdr | B5: =INDEX(Inputs!$C$45:$C$54,Inputs!$B$3) -> 0.03
A6: Selected sev | B6: =INDEX(Inputs!$D$45:$D$54,Inputs!$B$3) -> 0.4
A7: Selected lag | B7: =INDEX(Inputs!$E$45:$E$54,Inputs!$B$3) -> 6
A8: Selected shift | B8: =INDEX(Inputs!$F$45:$F$54,Inputs!$B$3) -> 0
A9: Monthly default rate | B9: =1-(1-Inputs!$B$5)^(1/12) -> 0.0025350486
A10: Single monthly mortality | B10: =1-(1-Inputs!$B$4)^(1/12) -> 0.008741611
A11: Index start | B11: 0.043
A12: Index long run | B12: 0.0325
A13: Index decay (months) | B13: 24
A14: Senior fees, annual (servicing + trustee) | B14: 0.0063
A15: Initial and target reserve | B15: 3000000
A16: Pro rata start (1) or sequential (0) | B16: 0
A17: Swap hedge on floating notes (1/0) | B17: 0
A18: Swap fixed rate | B18: 0.036
A19: Retirement tolerance (USD) | B19: 1e-06
A20: Shortfall tolerance (USD) | B20: 1
A21: Class A original balance | B21: 300000000
A22: Class A floating (1) or fixed (0) | B22: 1
... A35: Class C IC trigger | B35: 1.15
A36: Pool balance | B36: =SUM(Inputs!$B$58:$B$67) -> 400000000
A37: Residual par (pool + reserve - notes) | B37: =Inputs!$B$36+Inputs!$B$15-Inputs!$B$21-Inputs!$B$26-Inputs!$B$31 -> 33000000
A44: Scenario | B44: CPR | C44: CDR | D44: Severity | E44: Lag (months) | F44: Index shift
A45: Base | B45: 0.1 | C45: 0.03 | D45: 0.4 | E45: 6 | F45: 0
A46: Mild stress | B46: 0.1 | C46: 0.06 | D46: 0.5 | E46: 6 | F46: 0
A47: Stress | B47: 0.06 | C47: 0.12 | D47: 0.6 | E47: 9 | F47: 0
A48: Severe stress | B48: 0.04 | C48: 0.2 | D48: 0.7 | E48: 12 | F48: 0
A49: Fast prepay | B49: 0.3 | C49: 0.03 | D49: 0.4 | E49: 6 | F49: 0
A50: Rate shock | B50: 0.1 | C50: 0.06 | D50: 0.5 | E50: 6 | F50: 0.03
A51: Custom 1 | B51: 0.1 | C51: 0.03 | D51: 0.4 | E51: 6 | F51: 0
A52: Custom 2 | B52: 0.1 | C52: 0.03 | D52: 0.4 | E52: 6 | F52: 0
A53: Custom 3 | B53: 0.1 | C53: 0.03 | D53: 0.4 | E53: 6 | F53: 0
A54: Custom 4 | B54: 0.1 | C54: 0.03 | D54: 0.4 | E54: 6 | F54: 0
A57: Pool rep line | B57: Balance | C57: WAC | D57: Term (months)
A58: L01 | B58: 39000000 | C58: 0.073 | D58: 36
A59: L02 | B59: 75500000 | C59: 0.078 | D59: 48
A60: L03 | B60: 21600000 | C60: 0.083 | D60: 48
A61: L04 | B61: 67200000 | C61: 0.088 | D61: 60
A62: L05 | B62: 19000000 | C62: 0.093 | D62: 60
A63: L06 | B63: 22700000 | C63: 0.0955 | D63: 60
A64: L07 | B64: 35200000 | C64: 0.098 | D64: 72
A65: L08 | B65: 36400000 | C65: 0.103 | D65: 72
A66: L09 | B66: 36100000 | C66: 0.1055 | D66: 84
A67: L10 | B67: 47300000 | C67: 0.1105 | D67: 84

Sheet Pool
A4: Period | B4: L1_rem | C4: L1_beg | D4: L1_def | E4: L1_int | F4: L1_sch | G4: L1_pre | H4: L1_end | I4: L2_rem | J4: L2_beg | K4: L2_def | L4: L2_int | M4: L2_sch | N4: L2_pre | O4: L2_end | P4: L3_rem | Q4: L3_beg | R4: L3_def | S4: L3_int | T4: L3_sch | U4: L3_pre | V4: L3_end | W4: L4_rem | X4: L4_beg | Y4: L4_def | Z4: L4_int | AA4: L4_sch | AB4: L4_pre | AC4: L4_end | AD4: L5_rem | AE4: L5_beg | AF4: L5_def | AG4: L5_int | AH4: L5_sch | AI4: L5_pre | AJ4: L5_end | AK4: L6_rem | AL4: L6_beg | AM4: L6_def | AN4: L6_int | AO4: L6_sch | AP4: L6_pre | AQ4: L6_end | AR4: L7_rem | AS4: L7_beg | AT4: L7_def | AU4: L7_int | AV4: L7_sch | AW4: L7_pre | AX4: L7_end | AY4: L8_rem | AZ4: L8_beg | BA4: L8_def | BB4: L8_int | BC4: L8_sch | BD4: L8_pre | BE4: L8_end | BF4: L9_rem | BG4: L9_beg | BH4: L9_def | BI4: L9_int | BJ4: L9_sch | BK4: L9_pre | BL4: L9_end | BM4: L10_rem | BN4: L10_beg | BO4: L10_def | BP4: L10_int | BQ4: L10_sch | BR4: L10_pre | BS4: L10_end | BT4: tot_beg | BU4: tot_defaults | BV4: tot_interest | BW4: tot_sched | BX4: tot_prepay | BY4: tot_end | BZ4: recov | CA4: pending | CB4: value | CC4: cash | CD4: cum_loss
H5: 0 | O5: 0 | V5: 0 | AC5: 0 | AJ5: 0 | AQ5: 0 | AX5: 0 | BE5: 0 | BL5: 0 | BS5: 0 | BY5: 0 | CA5: 0 | CD5: 0
A6: =ROW()-5 -> 1 | B6: =Inputs!$D$58-(A6-1) -> 36 | C6: =IF(B6<=0,0,IF(A6=1,Inputs!$B$58,H5)) -> 39000000 | D6: =C6*Inputs!$B$9 -> 98866.896 | E6: =(C6-D6)*Inputs!$C$58/12 -> 236648.56 | F6: =IF(B6<=0,0,IF(B6=1,C6-D6,MIN((C6-D6)*(Inputs!$C$58/12)/(1-(1+Inputs!$C$58/12)^(-B6))-E6,C6-D6))) -> 969848.55 | G6: =(C6-D6-F6)*Inputs!$B$10 -> 331580.53 | H6: =C6-D6-F6-G6 -> 37599704 | I6: =Inputs!$D$59-(A6-1) -> 48 | J6: =IF(I6<=0,0,IF(A6=1,Inputs!$B$59,O5)) -> 75500000 | K6: =J6*Inputs!$B$9 -> 191396.17 | L6: =(J6-K6)*Inputs!$C$59/12 -> 489505.92 | M6: =IF(I6<=0,0,IF(I6=1,J6-K6,MIN((J6-K6)*(Inputs!$C$59/12)/(1-(1+Inputs!$C$59/12)^(-I6))-L6,J6-K6))) -> 1341935.4 | N6: =(J6-K6-M6)*Inputs!$B$10 -> 646587.84 | O6: =J6-K6-M6-N6 -> 73320081 | P6: =Inputs!$D$60-(A6-1) -> 48 | Q6: =IF(P6<=0,0,IF(A6=1,Inputs!$B$60,V5)) -> 21600000 | R6: =Q6*Inputs!$B$9 -> 54757.05 | S6: =(Q6-R6)*Inputs!$C$60/12 -> 149021.26 | T6: =IF(P6<=0,0,IF(P6=1,Q6-R6,MIN((Q6-R6)*(Inputs!$C$60/12)/(1-(1+Inputs!$C$60/12)^(-P6))-S6,Q6-R6))) -> 380000.37 | U6: =(Q6-R6-T6)*Inputs!$B$10 -> 185018.32 | V6: =Q6-R6-T6-U6 -> 20980224 | W6: =Inputs!$D$61-(A6-1) -> 60 | X6: =IF(W6<=0,0,IF(A6=1,Inputs!$B$61,AC5)) -> 67200000 | Y6: =X6*Inputs!$B$9 -> 170355.27 | Z6: =(X6-Y6)*Inputs!$C$61/12 -> 491550.73 | AA6: =IF(W6<=0,0,IF(W6=1,X6-Y6,MIN((X6-Y6)*(Inputs!$C$61/12)/(1-(1+Inputs!$C$61/12)^(-W6))-Z6,X6-Y6))) -> 893377.15 | AB6: =(X6-Y6-AA6)*Inputs!$B$10 -> 578137.52 | AC6: =X6-Y6-AA6-AB6 -> 65558130 | AD6: =Inputs!$D$62-(A6-1) -> 60 | AE6: =IF(AD6<=0,0,IF(A6=1,Inputs!$B$62,AJ5)) -> 19000000 | AF6: =AE6*Inputs!$B$9 -> 48165.924 | AG6: =(AE6-AF6)*Inputs!$C$62/12 -> 146876.71 | AH6: =IF(AD6<=0,0,IF(AD6=1,AE6-AF6,MIN((AE6-AF6)*(Inputs!$C$62/12)/(1-(1+Inputs!$C$62/12)^(-AD6))-AG6,AE6-AF6))) -> 249297.3 | AI6: =(AE6-AF6-AH6)*Inputs!$B$10 -> 163490.3 | AJ6: =AE6-AF6-AH6-AI6 -> 18539046 | AK6: =Inputs!$D$63-(A6-1) -> 60 | AL6: =IF(AK6<=0,0,IF(A6=1,Inputs!$B$63,AQ5)) -> 22700000 | AM6: =AL6*Inputs!$B$9 -> 57545.604 | AN6: =(AL6-AM6)*Inputs!$C$63/12 -> 180196.2 | AO6: =IF(AK6<=0,0,IF(AK6=1,AL6-AM6,MIN((AL6-AM6)*(Inputs!$C$63/12)/(1-(1+Inputs!$C$63/12)^(-AK6))-AN6,AL6-AM6))) -> 295890.94 | AP6: =(AL6-AM6-AO6)*Inputs!$B$10 -> 195344.96 | AQ6: =AL6-AM6-AO6-AP6 -> 22151218 | AR6: =Inputs!$D$64-(A6-1) -> 72 | AS6: =IF(AR6<=0,0,IF(A6=1,Inputs!$B$64,AX5)) -> 35200000 | AT6: =AS6*Inputs!$B$9 -> 89233.711 | AU6: =(AS6-AT6)*Inputs!$C$64/12 -> 286737.92 | AV6: =IF(AR6<=0,0,IF(AR6=1,AS6-AT6,MIN((AS6-AT6)*(Inputs!$C$64/12)/(1-(1+Inputs!$C$64/12)^(-AR6))-AU6,AS6-AT6))) -> 360182.87 | AW6: =(AS6-AT6-AV6)*Inputs!$B$10 -> 303776.08 | AX6: =AS6-AT6-AV6-AW6 -> 34446807 | AY6: =Inputs!$D$65-(A6-1) -> 72 | AZ6: =IF(AY6<=0,0,IF(A6=1,Inputs!$B$65,BE5)) -> 36400000 | BA6: =AZ6*Inputs!$B$9 -> 92275.77 | BB6: =(AZ6-BA6)*Inputs!$C$65/12 -> 311641.3 | BC6: =IF(AY6<=0,0,IF(AY6=1,AZ6-BA6,MIN((AZ6-BA6)*(Inputs!$C$65/12)/(1-(1+Inputs!$C$65/12)^(-AY6))-BB6,AZ6-BA6))) -> 366495.47 | BD6: =(AZ6-BA6-BC6)*Inputs!$B$10 -> 314184.24 | BE6: =AZ6-BA6-BC6-BD6 -> 35627045 | BF6: =Inputs!$D$66-(A6-1) -> 84 | BG6: =IF(BF6<=0,0,IF(A6=1,Inputs!$B$66,BL5)) -> 36100000 | BH6: =BG6*Inputs!$B$9 -> 91515.255 | BI6: =(BG6-BH6)*Inputs!$C$66/12 -> 316574.6 | BJ6: =IF(BF6<=0,0,IF(BF6=1,BG6-BH6,MIN((BG6-BH6)*(Inputs!$C$66/12)/(1-(1+Inputs!$C$66/12)^(-BF6))-BI6,BG6-BH6))) -> 291491.59 | BK6: =(BG6-BH6-BJ6)*Inputs!$B$10 -> 312224.06 | BL6: =BG6-BH6-BJ6-BK6 -> 35404769 | BM6: =Inputs!$D$67-(A6-1) -> 84 | BN6: =IF(BM6<=0,0,IF(A6=1,Inputs!$B$67,BS5)) -> 47300000 | BO6: =BN6*Inputs!$B$9 -> 119907.8 | BP6: =(BN6-BO6)*Inputs!$C$67/12 -> 434450.02 | BQ6: =IF(BM6<=0,0,IF(BM6=1,BN6-BO6,MIN((BN6-BO6)*(Inputs!$C$67/12)/(1-(1+Inputs!$C$67/12)^(-BM6))-BP6,BN6-BO6))) -> 374628.99 | BR6: =(BN6-BO6-BQ6)*Inputs!$B$10 -> 409155.15 | BS6: =BN6-BO6-BQ6-BR6 -> 46396308 | BT6: =C6+J6+Q6+X6+AE6+AL6+AS6+AZ6+BG6+BN6 -> 400000000 | BU6: =D6+K6+R6+Y6+AF6+AM6+AT6+BA6+BH6+BO6 -> 1014019.4 | BV6: =E6+L6+S6+Z6+AG6+AN6+AU6+BB6+BI6+BP6 -> 3043203.2 | BW6: =F6+M6+T6+AA6+AH6+AO6+AV6+BC6+BJ6+BQ6 -> 5523148.6 | BX6: =G6+N6+U6+AB6+AI6+AP6+AW6+BD6+BK6+BR6 -> 3439499 | BY6: =H6+O6+V6+AC6+AJ6+AQ6+AX6+BE6+BL6+BS6 -> 3.9002333e+08 | BZ6: =IF(A6>Inputs!$B$7,(1-Inputs!$B$6)*INDEX($BU$6:$BU$125,A6-Inputs!$B$7),0) -> 0 | CA6: =CA5+(1-Inputs!$B$6)*BU6-BZ6 -> 608411.67 | CB6: =BY6+CA6 -> 3.9063174e+08 | CC6: =BV6+BW6+BX6+BZ6 -> 12005851 | CD6: =CD5+BU6-BZ6 -> 1014019.4
A7: =ROW()-5 -> 2 | B7: =Inputs!$D$58-(A7-1) -> 35 | C7: =IF(B7<=0,0,IF(A7=1,Inputs!$B$58,H6)) -> 37599704 | D7: =C7*Inputs!$B$9 -> 95317.078 | E7: =(C7-D7)*Inputs!$C$58/12 -> 228151.69 | F7: =IF(B7<=0,0,IF(B7=1,C7-D7,MIN((C7-D7)*(Inputs!$C$58/12)/(1-(1+Inputs!$C$58/12)^(-B7))-E7,C7-D7))) -> 964766.9 | G7: =(C7-D7-F7)*Inputs!$B$10 -> 319415.14 | H7: =C7-D7-F7-G7 -> 36220205 | I7: =Inputs!$D$59-(A7-1) -> 47 | J7: =IF(I7<=0,0,IF(A7=1,Inputs!$B$59,O6)) -> 73320081 | K7: =J7*Inputs!$B$9 -> 185869.97 | L7: =(J7-K7)*Inputs!$C$59/12 -> 475372.37 | M7: =IF(I7<=0,0,IF(I7=1,J7-K7,MIN((J7-K7)*(Inputs!$C$59/12)/(1-(1+Inputs!$C$59/12)^(-I7))-L7,J7-K7))) -> 1335457 | N7: =(J7-K7-M7)*Inputs!$B$10 -> 627636.77 | O7: =J7-K7-M7-N7 -> 71171117 | P7: =Inputs!$D$60-(A7-1) -> 47 | Q7: =IF(P7<=0,0,IF(A7=1,Inputs!$B$60,V6)) -> 20980224 | R7: =Q7*Inputs!$B$9 -> 53185.888 | S7: =(Q7-R7)*Inputs!$C$60/12 -> 144745.35 | T7: =IF(P7<=0,0,IF(P7=1,Q7-R7,MIN((Q7-R7)*(Inputs!$C$60/12)/(1-(1+Inputs!$C$60/12)^(-P7))-S7,Q7-R7))) -> 378322.41 | U7: =(Q7-R7-T7)*Inputs!$B$10 -> 179628.88 | V7: =Q7-R7-T7-U7 -> 20369087 | W7: =Inputs!$D$61-(A7-1) -> 59 | X7: =IF(W7<=0,0,IF(A7=1,Inputs!$B$61,AC6)) -> 65558130 | Y7: =X7*Inputs!$B$9 -> 166193.05 | Z7: =(X7-Y7)*Inputs!$C$61/12 -> 479540.87 | AA7: =IF(W7<=0,0,IF(W7=1,X7-Y7,MIN((X7-Y7)*(Inputs!$C$61/12)/(1-(1+Inputs!$C$61/12)^(-W7))-Z7,X7-Y7))) -> 889800.34 | AB7: =(X7-Y7-AA7)*Inputs!$B$10 -> 563852.58 | AC7: =X7-Y7-AA7-AB7 -> 63938284 | AD7: =Inputs!$D$62-(A7-1) -> 59 | AE7: =IF(AD7<=0,0,IF(A7=1,Inputs!$B$62,AJ6)) -> 18539046 | AF7: =AE7*Inputs!$B$9 -> 46997.384 | AG7: =(AE7-AF7)*Inputs!$C$62/12 -> 143313.38 | AH7: =IF(AD7<=0,0,IF(AD7=1,AE7-AF7,MIN((AE7-AF7)*(Inputs!$C$62/12)/(1-(1+Inputs!$C$62/12)^(-AD7))-AG7,AE7-AF7))) -> 248401.9 | AI7: =(AE7-AF7-AH7)*Inputs!$B$10 -> 159478.87 | AJ7: =AE7-AF7-AH7-AI7 -> 18084168 | AK7: =Inputs!$D$63-(A7-1) -> 59 | AL7: =IF(AK7<=0,0,IF(A7=1,Inputs!$B$63,AQ6)) -> 22151218 | AM7: =AL7*Inputs!$B$9 -> 56154.416 | AN7: =(AL7-AM7)*Inputs!$C$63/12 -> 175839.88 | AO7: =IF(AK7<=0,0,IF(AK7=1,AL7-AM7,MIN((AL7-AM7)*(Inputs!$C$63/12)/(1-(1+Inputs!$C$63/12)^(-AK7))-AN7,AL7-AM7))) -> 294889.13 | AP7: =(AL7-AM7-AO7)*Inputs!$B$10 -> 190568.65 | AQ7: =AL7-AM7-AO7-AP7 -> 21609606 | AR7: =Inputs!$D$64-(A7-1) -> 71 | AS7: =IF(AR7<=0,0,IF(A7=1,Inputs!$B$64,AX6)) -> 34446807 | AT7: =AS7*Inputs!$B$9 -> 87324.331 | AU7: =(AS7-AT7)*Inputs!$C$64/12 -> 280602.44 | AV7: =IF(AR7<=0,0,IF(AR7=1,AS7-AT7,MIN((AS7-AT7)*(Inputs!$C$64/12)/(1-(1+Inputs!$C$64/12)^(-AR7))-AU7,AS7-AT7))) -> 359037.58 | AW7: =(AS7-AT7-AV7)*Inputs!$B$10 -> 297218.67 | AX7: =AS7-AT7-AV7-AW7 -> 33703227 | AY7: =Inputs!$D$65-(A7-1) -> 71 | AZ7: =IF(AY7<=0,0,IF(A7=1,Inputs!$B$65,BE6)) -> 35627045 | BA7: =AZ7*Inputs!$B$9 -> 90316.29 | BB7: =(AZ7-BA7)*Inputs!$C$65/12 -> 305023.58 | BC7: =IF(AY7<=0,0,IF(AY7=1,AZ7-BA7,MIN((AZ7-BA7)*(Inputs!$C$65/12)/(1-(1+Inputs!$C$65/12)^(-AY7))-BB7,AZ7-BA7))) -> 365481.1 | BD7: =(AZ7-BA7-BC7)*Inputs!$B$10 -> 307453.36 | BE7: =AZ7-BA7-BC7-BD7 -> 34863794 | BF7: =Inputs!$D$66-(A7-1) -> 83 | BG7: =IF(BF7<=0,0,IF(A7=1,Inputs!$B$66,BL6)) -> 35404769 | BH7: =BG7*Inputs!$B$9 -> 89752.811 | BI7: =(BG7-BH7)*Inputs!$C$66/12 -> 310477.85 | BJ7: =IF(BF7<=0,0,IF(BF7=1,BG7-BH7,MIN((BG7-BH7)*(Inputs!$C$66/12)/(1-(1+Inputs!$C$66/12)^(-BF7))-BI7,BG7-BH7))) -> 290744.85 | BK7: =(BG7-BH7-BJ7)*Inputs!$B$10 -> 306168.55 | BL7: =BG7-BH7-BJ7-BK7 -> 34718103 | BM7: =Inputs!$D$67-(A7-1) -> 83 | BN7: =IF(BM7<=0,0,IF(A7=1,Inputs!$B$67,BS6)) -> 46396308 | BO7: =BN7*Inputs!$B$9 -> 117616.9 | BP7: =(BN7-BO7)*Inputs!$C$67/12 -> 426149.61 | BQ7: =IF(BM7<=0,0,IF(BM7=1,BN7-BO7,MIN((BN7-BO7)*(Inputs!$C$67/12)/(1-(1+Inputs!$C$67/12)^(-BM7))-BP7,BN7-BO7))) -> 373823.62 | BR7: =(BN7-BO7-BQ7)*Inputs!$B$10 -> 401282.49 | BS7: =BN7-BO7-BQ7-BR7 -> 45503585 | BT7: =C7+J7+Q7+X7+AE7+AL7+AS7+AZ7+BG7+BN7 -> 3.9002333e+08 | BU7: =D7+K7+R7+Y7+AF7+AM7+AT7+BA7+BH7+BO7 -> 988728.11 | BV7: =E7+L7+S7+Z7+AG7+AN7+AU7+BB7+BI7+BP7 -> 2969217 | BW7: =F7+M7+T7+AA7+AH7+AO7+AV7+BC7+BJ7+BQ7 -> 5500724.8 | BX7: =G7+N7+U7+AB7+AI7+AP7+AW7+BD7+BK7+BR7 -> 3352704 | BY7: =H7+O7+V7+AC7+AJ7+AQ7+AX7+BE7+BL7+BS7 -> 3.8018118e+08 | BZ7: =IF(A7>Inputs!$B$7,(1-Inputs!$B$6)*INDEX($BU$6:$BU$125,A7-Inputs!$B$7),0) -> 0 | CA7: =CA6+(1-Inputs!$B$6)*BU7-BZ7 -> 1201648.5 | CB7: =BY7+CA7 -> 3.8138282e+08 | CC7: =BV7+BW7+BX7+BZ7 -> 11822646 | CD7: =CD6+BU7-BZ7 -> 2002747.6
A8: =ROW()-5 -> 3 | B8: =Inputs!$D$58-(A8-1) -> 34 | C8: =IF(B8<=0,0,IF(A8=1,Inputs!$B$58,H7)) -> 36220205 | D8: =C8*Inputs!$B$9 -> 91819.98 | E8: =(C8-D8)*Inputs!$C$58/12 -> 219781.01 | F8: =IF(B8<=0,0,IF(B8=1,C8-D8,MIN((C8-D8)*(Inputs!$C$58/12)/(1-(1+Inputs!$C$58/12)^(-B8))-E8,C8-D8))) -> 959711.88 | G8: =(C8-D8-F8)*Inputs!$B$10 -> 307430.86 | H8: =C8-D8-F8-G8 -> 34861242 | I8: =Inputs!$D$59-(A8-1) -> 46 | J8: =IF(I8<=0,0,IF(A8=1,Inputs!$B$59,O7)) -> 71171117 | K8: =J8*Inputs!$B$9 -> 180422.24 | L8: =(J8-K8)*Inputs!$C$59/12 -> 461439.52 | M8: =IF(I8<=0,0,IF(I8=1,J8-K8,MIN((J8-K8)*(Inputs!$C$59/12)/(1-(1+Inputs!$C$59/12)^(-I8))-L8,J8-K8))) -> 1329009.8 | N8: =(J8-K8-M8)*Inputs!$B$10 -> 608955.35 | O8: =J8-K8-M8-N8 -> 69052729 | P8: =Inputs!$D$60-(A8-1) -> 46 | Q8: =IF(P8<=0,0,IF(A8=1,Inputs!$B$60,V7)) -> 20369087 | R8: =Q8*Inputs!$B$9 -> 51636.626 | S8: =(Q8-R8)*Inputs!$C$60/12 -> 140529.03 | T8: =IF(P8<=0,0,IF(P8=1,Q8-R8,MIN((Q8-R8)*(Inputs!$C$60/12)/(1-(1+Inputs!$C$60/12)^(-P8))-S8,Q8-R8))) -> 376651.86 | U8: =(Q8-R8-T8)*Inputs!$B$10 -> 174314.7 | V8: =Q8-R8-T8-U8 -> 19766484 | W8: =Inputs!$D$61-(A8-1) -> 58 | X8: =IF(W8<=0,0,IF(A8=1,Inputs!$B$61,AC7)) -> 63938284 | Y8: =X8*Inputs!$B$9 -> 162086.66 | Z8: =(X8-Y8)*Inputs!$C$61/12 -> 467692.11 | AA8: =IF(W8<=0,0,IF(W8=1,X8-Y8,MIN((X8-Y8)*(Inputs!$C$61/12)/(1-(1+Inputs!$C$61/12)^(-W8))-Z8,X8-Y8))) -> 886237.85 | AB8: =(X8-Y8-AA8)*Inputs!$B$10 -> 549759.56 | AC8: =X8-Y8-AA8-AB8 -> 62340200 | AD8: =Inputs!$D$62-(A8-1) -> 58 | AE8: =IF(AD8<=0,0,IF(A8=1,Inputs!$B$62,AJ7)) -> 18084168 | AF8: =AE8*Inputs!$B$9 -> 45844.246 | AG8: =(AE8-AF8)*Inputs!$C$62/12 -> 139797.01 | AH8: =IF(AD8<=0,0,IF(AD8=1,AE8-AF8,MIN((AE8-AF8)*(Inputs!$C$62/12)/(1-(1+Inputs!$C$62/12)^(-AD8))-AG8,AE8-AF8))) -> 247509.71 | AI8: =(AE8-AF8-AH8)*Inputs!$B$10 -> 155520.38 | AJ8: =AE8-AF8-AH8-AI8 -> 17635294 | AK8: =Inputs!$D$63-(A8-1) -> 58 | AL8: =IF(AK8<=0,0,IF(A8=1,Inputs!$B$63,AQ7)) -> 21609606 | AM8: =AL8*Inputs!$B$9 -> 54781.403 | AN8: =(AL8-AM8)*Inputs!$C$63/12 -> 171540.48 | AO8: =IF(AK8<=0,0,IF(AK8=1,AL8-AM8,MIN((AL8-AM8)*(Inputs!$C$63/12)/(1-(1+Inputs!$C$63/12)^(-AK8))-AN8,AL8-AM8))) -> 293890.71 | AP8: =(AL8-AM8-AO8)*Inputs!$B$10 -> 185854.82 | AQ8: =AL8-AM8-AO8-AP8 -> 21075079 | AR8: =Inputs!$D$64-(A8-1) -> 70 | AS8: =IF(AR8<=0,0,IF(A8=1,Inputs!$B$64,AX7)) -> 33703227 | AT8: =AS8*Inputs!$B$9 -> 85439.318 | AU8: =(AS8-AT8)*Inputs!$C$64/12 -> 274545.26 | AV8: =IF(AR8<=0,0,IF(AR8=1,AS8-AT8,MIN((AS8-AT8)*(Inputs!$C$64/12)/(1-(1+Inputs!$C$64/12)^(-AR8))-AU8,AS8-AT8))) -> 357895.93 | AW8: =(AS8-AT8-AV8)*Inputs!$B$10 -> 290745.03 | AX8: =AS8-AT8-AV8-AW8 -> 32969146 | AY8: =Inputs!$D$65-(A8-1) -> 70 | AZ8: =IF(AY8<=0,0,IF(A8=1,Inputs!$B$65,BE7)) -> 34863794 | BA8: =AZ8*Inputs!$B$9 -> 88381.412 | BB8: =(AZ8-BA8)*Inputs!$C$65/12 -> 298488.96 | BC8: =IF(AY8<=0,0,IF(AY8=1,AZ8-BA8,MIN((AZ8-BA8)*(Inputs!$C$65/12)/(1-(1+Inputs!$C$65/12)^(-AY8))-BB8,AZ8-BA8))) -> 364469.53 | BD8: =(AZ8-BA8-BC8)*Inputs!$B$10 -> 300807.07 | BE8: =AZ8-BA8-BC8-BD8 -> 34110136 | BF8: =Inputs!$D$66-(A8-1) -> 82 | BG8: =IF(BF8<=0,0,IF(A8=1,Inputs!$B$66,BL7)) -> 34718103 | BH8: =BG8*Inputs!$B$9 -> 88012.079 | BI8: =(BG8-BH8)*Inputs!$C$66/12 -> 304456.21 | BJ8: =IF(BF8<=0,0,IF(BF8=1,BG8-BH8,MIN((BG8-BH8)*(Inputs!$C$66/12)/(1-(1+Inputs!$C$66/12)^(-BF8))-BI8,BG8-BH8))) -> 290000.03 | BK8: =(BG8-BH8-BJ8)*Inputs!$B$10 -> 300187.71 | BL8: =BG8-BH8-BJ8-BK8 -> 34039903 | BM8: =Inputs!$D$67-(A8-1) -> 82 | BN8: =IF(BM8<=0,0,IF(A8=1,Inputs!$B$67,BS7)) -> 45503585 | BO8: =BN8*Inputs!$B$9 -> 115353.8 | BP8: =(BN8-BO8)*Inputs!$C$67/12 -> 417949.96 | BQ8: =IF(BM8<=0,0,IF(BM8=1,BN8-BO8,MIN((BN8-BO8)*(Inputs!$C$67/12)/(1-(1+Inputs!$C$67/12)^(-BM8))-BP8,BN8-BO8))) -> 373019.97 | BR8: =(BN8-BO8-BQ8)*Inputs!$B$10 -> 393505.46 | BS8: =BN8-BO8-BQ8-BR8 -> 44621706 | BT8: =C8+J8+Q8+X8+AE8+AL8+AS8+AZ8+BG8+BN8 -> 3.8018118e+08 | BU8: =D8+K8+R8+Y8+AF8+AM8+AT8+BA8+BH8+BO8 -> 963777.76 | BV8: =E8+L8+S8+Z8+AG8+AN8+AU8+BB8+BI8+BP8 -> 2896219.6 | BW8: =F8+M8+T8+AA8+AH8+AO8+AV8+BC8+BJ8+BQ8 -> 5478397.3 | BX8: =G8+N8+U8+AB8+AI8+AP8+AW8+BD8+BK8+BR8 -> 3267080.9 | BY8: =H8+O8+V8+AC8+AJ8+AQ8+AX8+BE8+BL8+BS8 -> 3.7047192e+08 | BZ8: =IF(A8>Inputs!$B$7,(1-Inputs!$B$6)*INDEX($BU$6:$BU$125,A8-Inputs!$B$7),0) -> 0 | CA8: =CA7+(1-Inputs!$B$6)*BU8-BZ8 -> 1779915.2 | CB8: =BY8+CA8 -> 3.7225184e+08 | CC8: =BV8+BW8+BX8+BZ8 -> 11641698 | CD8: =CD7+BU8-BZ8 -> 2966525.3
A9: =ROW()-5 -> 4 | B9: =Inputs!$D$58-(A9-1) -> 33 | C9: =IF(B9<=0,0,IF(A9=1,Inputs!$B$58,H8)) -> 34861242 | D9: =C9*Inputs!$B$9 -> 88374.944 | E9: =(C9-D9)*Inputs!$C$58/12 -> 211534.94 | F9: =IF(B9<=0,0,IF(B9=1,C9-D9,MIN((C9-D9)*(Inputs!$C$58/12)/(1-(1+Inputs!$C$58/12)^(-B9))-E9,C9-D9))) -> 954683.34 | G9: =(C9-D9-F9)*Inputs!$B$10 -> 295625.41 | H9: =C9-D9-F9-G9 -> 33522558 | I9: =Inputs!$D$59-(A9-1) -> 45 | J9: =IF(I9<=0,0,IF(A9=1,Inputs!$B$59,O8)) -> 69052729 | K9: =J9*Inputs!$B$9 -> 175052.03 | L9: =(J9-K9)*Inputs!$C$59/12 -> 447704.9 | M9: =IF(I9<=0,0,IF(I9=1,J9-K9,MIN((J9-K9)*(Inputs!$C$59/12)/(1-(1+Inputs!$C$59/12)^(-I9))-L9,J9-K9))) -> 1322593.8 | N9: =(J9-K9-M9)*Inputs!$B$10 -> 590540.26 | O9: =J9-K9-M9-N9 -> 66964543 | P9: =Inputs!$D$60-(A9-1) -> 45 | Q9: =IF(P9<=0,0,IF(A9=1,Inputs!$B$60,V8)) -> 19766484 | R9: =Q9*Inputs!$B$9 -> 50108.998 | S9: =(Q9-R9)*Inputs!$C$60/12 -> 136371.59 | T9: =IF(P9<=0,0,IF(P9=1,Q9-R9,MIN((Q9-R9)*(Inputs!$C$60/12)/(1-(1+Inputs!$C$60/12)^(-P9))-S9,Q9-R9))) -> 374988.69 | U9: =(Q9-R9-T9)*Inputs!$B$10 -> 169074.87 | V9: =Q9-R9-T9-U9 -> 19172311 | W9: =Inputs!$D$61-(A9-1) -> 57 | X9: =IF(W9<=0,0,IF(A9=1,Inputs!$B$61,AC8)) -> 62340200 | Y9: =X9*Inputs!$B$9 -> 158035.44 | Z9: =(X9-Y9)*Inputs!$C$61/12 -> 456002.54 | AA9: =IF(W9<=0,0,IF(W9=1,X9-Y9,MIN((X9-Y9)*(Inputs!$C$61/12)/(1-(1+Inputs!$C$61/12)^(-W9))-Z9,X9-Y9))) -> 882689.62 | AB9: =(X9-Y9-AA9)*Inputs!$B$10 -> 535856.16 | AC9: =X9-Y9-AA9-AB9 -> 60763619 | AD9: =Inputs!$D$62-(A9-1) -> 57 | AE9: =IF(AD9<=0,0,IF(A9=1,Inputs!$B$62,AJ8)) -> 17635294 | AF9: =AE9*Inputs!$B$9 -> 44706.328 | AG9: =(AE9-AF9)*Inputs!$C$62/12 -> 136327.05 | AH9: =IF(AD9<=0,0,IF(AD9=1,AE9-AF9,MIN((AE9-AF9)*(Inputs!$C$62/12)/(1-(1+Inputs!$C$62/12)^(-AD9))-AG9,AE9-AF9))) -> 246620.72 | AI9: =(AE9-AF9-AH9)*Inputs!$B$10 -> 151614.21 | AJ9: =AE9-AF9-AH9-AI9 -> 17192353 | AK9: =Inputs!$D$63-(A9-1) -> 57 | AL9: =IF(AK9<=0,0,IF(A9=1,Inputs!$B$63,AQ8)) -> 21075079 | AM9: =AL9*Inputs!$B$9 -> 53426.351 | AN9: =(AL9-AM9)*Inputs!$C$63/12 -> 167297.32 | AO9: =IF(AK9<=0,0,IF(AK9=1,AL9-AM9,MIN((AL9-AM9)*(Inputs!$C$63/12)/(1-(1+Inputs!$C$63/12)^(-AK9))-AN9,AL9-AM9))) -> 292895.68 | AP9: =(AL9-AM9-AO9)*Inputs!$B$10 -> 181202.73 | AQ9: =AL9-AM9-AO9-AP9 -> 20547555 | AR9: =Inputs!$D$64-(A9-1) -> 69 | AS9: =IF(AR9<=0,0,IF(A9=1,Inputs!$B$64,AX8)) -> 32969146 | AT9: =AS9*Inputs!$B$9 -> 83578.389 | AU9: =(AS9-AT9)*Inputs!$C$64/12 -> 268565.47 | AV9: =IF(AR9<=0,0,IF(AR9=1,AS9-AT9,MIN((AS9-AT9)*(Inputs!$C$64/12)/(1-(1+Inputs!$C$64/12)^(-AR9))-AU9,AS9-AT9))) -> 356757.92 | AW9: =(AS9-AT9-AV9)*Inputs!$B$10 -> 284354.2 | AX9: =AS9-AT9-AV9-AW9 -> 32244456 | AY9: =Inputs!$D$65-(A9-1) -> 69 | AZ9: =IF(AY9<=0,0,IF(A9=1,Inputs!$B$65,BE8)) -> 34110136 | BA9: =AZ9*Inputs!$B$9 -> 86470.852 | BB9: =(AZ9-BA9)*Inputs!$C$65/12 -> 292036.46 | BC9: =IF(AY9<=0,0,IF(AY9=1,AZ9-BA9,MIN((AZ9-BA9)*(Inputs!$C$65/12)/(1-(1+Inputs!$C$65/12)^(-AY9))-BB9,AZ9-BA9))) -> 363460.76 | BD9: =(AZ9-BA9-BC9)*Inputs!$B$10 -> 294244.41 | BE9: =AZ9-BA9-BC9-BD9 -> 33365960 | BF9: =Inputs!$D$66-(A9-1) -> 81 | BG9: =IF(BF9<=0,0,IF(A9=1,Inputs!$B$66,BL8)) -> 34039903 | BH9: =BG9*Inputs!$B$9 -> 86292.809 | BI9: =(BG9-BH9)*Inputs!$C$66/12 -> 298508.82 | BJ9: =IF(BF9<=0,0,IF(BF9=1,BG9-BH9,MIN((BG9-BH9)*(Inputs!$C$66/12)/(1-(1+Inputs!$C$66/12)^(-BF9))-BI9,BG9-BH9))) -> 289257.11 | BK9: =(BG9-BH9-BJ9)*Inputs!$B$10 -> 294280.68 | BL9: =BG9-BH9-BJ9-BK9 -> 33370072 | BM9: =Inputs!$D$67-(A9-1) -> 81 | BN9: =IF(BM9<=0,0,IF(A9=1,Inputs!$B$67,BS8)) -> 44621706 | BO9: =BN9*Inputs!$B$9 -> 113118.19 | BP9: =(BN9-BO9)*Inputs!$C$67/12 -> 409849.91 | BQ9: =IF(BM9<=0,0,IF(BM9=1,BN9-BO9,MIN((BN9-BO9)*(Inputs!$C$67/12)/(1-(1+Inputs!$C$67/12)^(-BM9))-BP9,BN9-BO9))) -> 372218.05 | BR9: =(BN9-BO9-BQ9)*Inputs!$B$10 -> 385822.97 | BS9: =BN9-BO9-BQ9-BR9 -> 43750547 | BT9: =C9+J9+Q9+X9+AE9+AL9+AS9+AZ9+BG9+BN9 -> 3.7047192e+08 | BU9: =D9+K9+R9+Y9+AF9+AM9+AT9+BA9+BH9+BO9 -> 939164.33 | BV9: =E9+L9+S9+Z9+AG9+AN9+AU9+BB9+BI9+BP9 -> 2824199 | BW9: =F9+M9+T9+AA9+AH9+AO9+AV9+BC9+BJ9+BQ9 -> 5456165.7 | BX9: =G9+N9+U9+AB9+AI9+AP9+AW9+BD9+BK9+BR9 -> 3182615.9 | BY9: =H9+O9+V9+AC9+AJ9+AQ9+AX9+BE9+BL9+BS9 -> 3.6089397e+08 | BZ9: =IF(A9>Inputs!$B$7,(1-Inputs!$B$6)*INDEX($BU$6:$BU$125,A9-Inputs!$B$7),0) -> 0 | CA9: =CA8+(1-Inputs!$B$6)*BU9-BZ9 -> 2343413.8 | CB9: =BY9+CA9 -> 3.6323739e+08 | CC9: =BV9+BW9+BX9+BZ9 -> 11462981 | CD9: =CD8+BU9-BZ9 -> 3905689.6
A10: =ROW()-5 -> 5 | B10: =Inputs!$D$58-(A10-1) -> 32 | C10: =IF(B10<=0,0,IF(A10=1,Inputs!$B$58,H9)) -> 33522558 | D10: =C10*Inputs!$B$9 -> 84981.315 | E10: =(C10-D10)*Inputs!$C$58/12 -> 203411.93 | F10: =IF(B10<=0,0,IF(B10=1,C10-D10,MIN((C10-D10)*(Inputs!$C$58/12)/(1-(1+Inputs!$C$58/12)^(-B10))-E10,C10-D10))) -> 949681.16 | G10: =(C10-D10-F10)*Inputs!$B$10 -> 283996.55 | H10: =C10-D10-F10-G10 -> 32203899 | I10: =Inputs!$D$59-(A10-1) -> 44 | J10: =IF(I10<=0,0,IF(A10=1,Inputs!$B$59,O9)) -> 66964543 | K10: =J10*Inputs!$B$9 -> 169758.37 | L10: =(J10-K10)*Inputs!$C$59/12 -> 434166.1 | M10: =IF(I10<=0,0,IF(I10=1,J10-K10,MIN((J10-K10)*(Inputs!$C$59/12)/(1-(1+Inputs!$C$59/12)^(-I10))-L10,J10-K10))) -> 1316208.8 | N10: =(J10-K10-M10)*Inputs!$B$10 -> 572388.24 | O10: =J10-K10-M10-N10 -> 64906188 | P10: =Inputs!$D$60-(A10-1) -> 44 | Q10: =IF(P10<=0,0,IF(A10=1,Inputs!$B$60,V9)) -> 19172311 | R10: =Q10*Inputs!$B$9 -> 48602.741 | S10: =(Q10-R10)*Inputs!$C$60/12 -> 132272.32 | T10: =IF(P10<=0,0,IF(P10=1,Q10-R10,MIN((Q10-R10)*(Inputs!$C$60/12)/(1-(1+Inputs!$C$60/12)^(-P10))-S10,Q10-R10))) -> 373332.86 | U10: =(Q10-R10-T10)*Inputs!$B$10 -> 163908.49 | V10: =Q10-R10-T10-U10 -> 18586467 | W10: =Inputs!$D$61-(A10-1) -> 56 | X10: =IF(W10<=0,0,IF(A10=1,Inputs!$B$61,AC9)) -> 60763619 | Y10: =X10*Inputs!$B$9 -> 154038.73 | Z10: =(X10-Y10)*Inputs!$C$61/12 -> 444470.25 | AA10: =IF(W10<=0,0,IF(W10=1,X10-Y10,MIN((X10-Y10)*(Inputs!$C$61/12)/(1-(1+Inputs!$C$61/12)^(-W10))-Z10,X10-Y10))) -> 879155.59 | AB10: =(X10-Y10-AA10)*Inputs!$B$10 -> 522140.13 | AC10: =X10-Y10-AA10-AB10 -> 59208284 | AD10: =Inputs!$D$62-(A10-1) -> 56 | AE10: =IF(AD10<=0,0,IF(A10=1,Inputs!$B$62,AJ9)) -> 17192353 | AF10: =AE10*Inputs!$B$9 -> 43583.45 | AG10: =(AE10-AF10)*Inputs!$C$62/12 -> 132902.96 | AH10: =IF(AD10<=0,0,IF(AD10=1,AE10-AF10,MIN((AE10-AF10)*(Inputs!$C$62/12)/(1-(1+Inputs!$C$62/12)^(-AD10))-AG10,AE10-AF10))) -> 245734.93 | AI10: =(AE10-AF10-AH10)*Inputs!$B$10 -> 147759.75 | AJ10: =AE10-AF10-AH10-AI10 -> 16755275 | AK10: =Inputs!$D$63-(A10-1) -> 56 | AL10: =IF(AK10<=0,0,IF(A10=1,Inputs!$B$63,AQ9)) -> 20547555 | AM10: =AL10*Inputs!$B$9 -> 52089.05 | AN10: =(AL10-AM10)*Inputs!$C$63/12 -> 163109.75 | AO10: =IF(AK10<=0,0,IF(AK10=1,AL10-AM10,MIN((AL10-AM10)*(Inputs!$C$63/12)/(1-(1+Inputs!$C$63/12)^(-AK10))-AN10,AL10-AM10))) -> 291904.01 | AP10: =(AL10-AM10-AO10)*Inputs!$B$10 -> 176611.68 | AQ10: =AL10-AM10-AO10-AP10 -> 20026950 | AR10: =Inputs!$D$64-(A10-1) -> 68 | AS10: =IF(AR10<=0,0,IF(A10=1,Inputs!$B$64,AX9)) -> 32244456 | AT10: =AS10*Inputs!$B$9 -> 81741.263 | AU10: =(AS10-AT10)*Inputs!$C$64/12 -> 262662.17 | AV10: =IF(AR10<=0,0,IF(AR10=1,AS10-AT10,MIN((AS10-AT10)*(Inputs!$C$64/12)/(1-(1+Inputs!$C$64/12)^(-AR10))-AU10,AS10-AT10))) -> 355623.52 | AW10: =(AS10-AT10-AV10)*Inputs!$B$10 -> 278045.22 | AX10: =AS10-AT10-AV10-AW10 -> 31529046 | AY10: =Inputs!$D$65-(A10-1) -> 68 | AZ10: =IF(AY10<=0,0,IF(A10=1,Inputs!$B$65,BE9)) -> 33365960 | BA10: =AZ10*Inputs!$B$9 -> 84584.33 | BB10: =(AZ10-BA10)*Inputs!$C$65/12 -> 285665.14 | BC10: =IF(AY10<=0,0,IF(AY10=1,AZ10-BA10,MIN((AZ10-BA10)*(Inputs!$C$65/12)/(1-(1+Inputs!$C$65/12)^(-AY10))-BB10,AZ10-BA10))) -> 362454.79 | BD10: =(AZ10-BA10-BC10)*Inputs!$B$10 -> 287764.4 | BE10: =AZ10-BA10-BC10-BD10 -> 32631156 | BF10: =Inputs!$D$66-(A10-1) -> 80 | BG10: =IF(BF10<=0,0,IF(A10=1,Inputs!$B$66,BL9)) -> 33370072 | BH10: =BG10*Inputs!$B$9 -> 84594.756 | BI10: =(BG10-BH10)*Inputs!$C$66/12 -> 292634.82 | BJ10: =IF(BF10<=0,0,IF(BF10=1,BG10-BH10,MIN((BG10-BH10)*(Inputs!$C$66/12)/(1-(1+Inputs!$C$66/12)^(-BF10))-BI10,BG10-BH10))) -> 288516.1 | BK10: =(BG10-BH10-BJ10)*Inputs!$B$10 -> 288446.6 | BL10: =BG10-BH10-BJ10-BK10 -> 32708515 | BM10: =Inputs!$D$67-(A10-1) -> 80 | BN10: =IF(BM10<=0,0,IF(A10=1,Inputs!$B$67,BS9)) -> 43750547 | BO10: =BN10*Inputs!$B$9 -> 110909.76 | BP10: =(BN10-BO10)*Inputs!$C$67/12 -> 401848.32 | BQ10: =IF(BM10<=0,0,IF(BM10=1,BN10-BO10,MIN((BN10-BO10)*(Inputs!$C$67/12)/(1-(1+Inputs!$C$67/12)^(-BM10))-BP10,BN10-BO10))) -> 371417.86 | BR10: =(BN10-BO10-BQ10)*Inputs!$B$10 -> 378233.94 | BS10: =BN10-BO10-BQ10-BR10 -> 42889985 | BT10: =C10+J10+Q10+X10+AE10+AL10+AS10+AZ10+BG10+BN10 -> 3.6089397e+08 | BU10: =D10+K10+R10+Y10+AF10+AM10+AT10+BA10+BH10+BO10 -> 914883.77 | BV10: =E10+L10+S10+Z10+AG10+AN10+AU10+BB10+BI10+BP10 -> 2753143.8 | BW10: =F10+M10+T10+AA10+AH10+AO10+AV10+BC10+BJ10+BQ10 -> 5434029.6 | BX10: =G10+N10+U10+AB10+AI10+AP10+AW10+BD10+BK10+BR10 -> 3099295 | BY10: =H10+O10+V10+AC10+AJ10+AQ10+AX10+BE10+BL10+BS10 -> 3.5144577e+08 | BZ10: =IF(A10>Inputs!$B$7,(1-Inputs!$B$6)*INDEX($BU$6:$BU$125,A10-Inputs!$B$7),0) -> 0 | CA10: =CA9+(1-Inputs!$B$6)*BU10-BZ10 -> 2892344 | CB10: =BY10+CA10 -> 3.5433811e+08 | CC10: =BV10+BW10+BX10+BZ10 -> 11286468 | CD10: =CD9+BU10-BZ10 -> 4820573.4
A11: =ROW()-5 -> 6 | B11: =Inputs!$D$58-(A11-1) -> 31 | C11: =IF(B11<=0,0,IF(A11=1,Inputs!$B$58,H10)) -> 32203899 | D11: =C11*Inputs!$B$9 -> 81638.451 | E11: =(C11-D11)*Inputs!$C$58/12 -> 195410.42 | F11: =IF(B11<=0,0,IF(B11=1,C11-D11,MIN((C11-D11)*(Inputs!$C$58/12)/(1-(1+Inputs!$C$58/12)^(-B11))-E11,C11-D11))) -> 944705.18 | G11: =(C11-D11-F11)*Inputs!$B$10 -> 272542.06 | H11: =C11-D11-F11-G11 -> 30905014 | I11: =Inputs!$D$59-(A11-1) -> 43 | J11: =IF(I11<=0,0,IF(A11=1,Inputs!$B$59,O10)) -> 64906188 | K11: =J11*Inputs!$B$9 -> 164540.34 | L11: =(J11-K11)*Inputs!$C$59/12 -> 420820.71 | M11: =IF(I11<=0,0,IF(I11=1,J11-K11,MIN((J11-K11)*(Inputs!$C$59/12)/(1-(1+Inputs!$C$59/12)^(-I11))-L11,J11-K11))) -> 1309854.6 | N11: =(J11-K11-M11)*Inputs!$B$10 -> 554496.06 | O11: =J11-K11-M11-N11 -> 62877297 | P11: =Inputs!$D$60-(A11-1) -> 43 | Q11: =IF(P11<=0,0,IF(A11=1,Inputs!$B$60,V10)) -> 18586467 | R11: =Q11*Inputs!$B$9 -> 47117.598 | S11: =(Q11-R11)*Inputs!$C$60/12 -> 128230.5 | T11: =IF(P11<=0,0,IF(P11=1,Q11-R11,MIN((Q11-R11)*(Inputs!$C$60/12)/(1-(1+Inputs!$C$60/12)^(-P11))-S11,Q11-R11))) -> 371684.34 | U11: =(Q11-R11-T11)*Inputs!$B$10 -> 158814.66 | V11: =Q11-R11-T11-U11 -> 18008851 | W11: =Inputs!$D$61-(A11-1) -> 55 | X11: =IF(W11<=0,0,IF(A11=1,Inputs!$B$61,AC10)) -> 59208284 | Y11: =X11*Inputs!$B$9 -> 150095.88 | Z11: =(X11-Y11)*Inputs!$C$61/12 -> 433093.38 | AA11: =IF(W11<=0,0,IF(W11=1,X11-Y11,MIN((X11-Y11)*(Inputs!$C$61/12)/(1-(1+Inputs!$C$61/12)^(-W11))-Z11,X11-Y11))) -> 875635.72 | AB11: =(X11-Y11-AA11)*Inputs!$B$10 -> 508609.24 | AC11: =X11-Y11-AA11-AB11 -> 57673944 | AD11: =Inputs!$D$62-(A11-1) -> 55 | AE11: =IF(AD11<=0,0,IF(A11=1,Inputs!$B$62,AJ10)) -> 16755275 | AF11: =AE11*Inputs!$B$9 -> 42475.436 | AG11: =(AE11-AF11)*Inputs!$C$62/12 -> 129524.19 | AH11: =IF(AD11<=0,0,IF(AD11=1,AE11-AF11,MIN((AE11-AF11)*(Inputs!$C$62/12)/(1-(1+Inputs!$C$62/12)^(-AD11))-AG11,AE11-AF11))) -> 244852.31 | AI11: =(AE11-AF11-AH11)*Inputs!$B$10 -> 143956.38 | AJ11: =AE11-AF11-AH11-AI11 -> 16323990 | AK11: =Inputs!$D$63-(A11-1) -> 55 | AL11: =IF(AK11<=0,0,IF(A11=1,Inputs!$B$63,AQ10)) -> 20026950 | AM11: =AL11*Inputs!$B$9 -> 50769.292 | AN11: =(AL11-AM11)*Inputs!$C$63/12 -> 158977.1 | AO11: =IF(AK11<=0,0,IF(AK11=1,AL11-AM11,MIN((AL11-AM11)*(Inputs!$C$63/12)/(1-(1+Inputs!$C$63/12)^(-AK11))-AN11,AL11-AM11))) -> 290915.7 | AP11: =(AL11-AM11-AO11)*Inputs!$B$10 -> 172080.93 | AQ11: =AL11-AM11-AO11-AP11 -> 19513184 | AR11: =Inputs!$D$64-(A11-1) -> 67 | AS11: =IF(AR11<=0,0,IF(A11=1,Inputs!$B$64,AX10)) -> 31529046 | AT11: =AS11*Inputs!$B$9 -> 79927.664 | AU11: =(AS11-AT11)*Inputs!$C$64/12 -> 256834.47 | AV11: =IF(AR11<=0,0,IF(AR11=1,AS11-AT11,MIN((AS11-AT11)*(Inputs!$C$64/12)/(1-(1+Inputs!$C$64/12)^(-AR11))-AU11,AS11-AT11))) -> 354492.72 | AW11: =(AS11-AT11-AV11)*Inputs!$B$10 -> 271817.12 | AX11: =AS11-AT11-AV11-AW11 -> 30822808 | AY11: =Inputs!$D$65-(A11-1) -> 67 | AZ11: =IF(AY11<=0,0,IF(A11=1,Inputs!$B$65,BE10)) -> 32631156 | BA11: =AZ11*Inputs!$B$9 -> 82721.567 | BB11: =(AZ11-BA11)*Inputs!$C$65/12 -> 279374.06 | BC11: =IF(AY11<=0,0,IF(AY11=1,AZ11-BA11,MIN((AZ11-BA11)*(Inputs!$C$65/12)/(1-(1+Inputs!$C$65/12)^(-AY11))-BB11,AZ11-BA11))) -> 361451.6 | BD11: =(AZ11-BA11-BC11)*Inputs!$B$10 -> 281366.08 | BE11: =AZ11-BA11-BC11-BD11 -> 31905617 | BF11: =Inputs!$D$66-(A11-1) -> 79 | BG11: =IF(BF11<=0,0,IF(A11=1,Inputs!$B$66,BL10)) -> 32708515 | BH11: =BG11*Inputs!$B$9 -> 82917.676 | BI11: =(BG11-BH11)*Inputs!$C$66/12 -> 286833.38 | BJ11: =IF(BF11<=0,0,IF(BF11=1,BG11-BH11,MIN((BG11-BH11)*(Inputs!$C$66/12)/(1-(1+Inputs!$C$66/12)^(-BF11))-BI11,BG11-BH11))) -> 287776.99 | BK11: =(BG11-BH11-BJ11)*Inputs!$B$10 -> 282684.64 | BL11: =BG11-BH11-BJ11-BK11 -> 32055136 | BM11: =Inputs!$D$67-(A11-1) -> 79 | BN11: =IF(BM11<=0,0,IF(A11=1,Inputs!$B$67,BS10)) -> 42889985 | BO11: =BN11*Inputs!$B$9 -> 108728.2 | BP11: =(BN11-BO11)*Inputs!$C$67/12 -> 393944.07 | BQ11: =IF(BM11<=0,0,IF(BM11=1,BN11-BO11,MIN((BN11-BO11)*(Inputs!$C$67/12)/(1-(1+Inputs!$C$67/12)^(-BM11))-BP11,BN11-BO11))) -> 370619.38 | BR11: =(BN11-BO11-BQ11)*Inputs!$B$10 -> 370737.29 | BS11: =BN11-BO11-BQ11-BR11 -> 42039900 | BT11: =C11+J11+Q11+X11+AE11+AL11+AS11+AZ11+BG11+BN11 -> 3.5144577e+08 | BU11: =D11+K11+R11+Y11+AF11+AM11+AT11+BA11+BH11+BO11 -> 890932.1 | BV11: =E11+L11+S11+Z11+AG11+AN11+AU11+BB11+BI11+BP11 -> 2683042.3 | BW11: =F11+M11+T11+AA11+AH11+AO11+AV11+BC11+BJ11+BQ11 -> 5411988.6 | BX11: =G11+N11+U11+AB11+AI11+AP11+AW11+BD11+BK11+BR11 -> 3017104.5 | BY11: =H11+O11+V11+AC11+AJ11+AQ11+AX11+BE11+BL11+BS11 -> 3.4212574e+08 | BZ11: =IF(A11>Inputs!$B$7,(1-Inputs!$B$6)*INDEX($BU$6:$BU$125,A11-Inputs!$B$7),0) -> 0 | CA11: =CA10+(1-Inputs!$B$6)*BU11-BZ11 -> 3426903.3 | CB11: =BY11+CA11 -> 3.4555264e+08 | CC11: =BV11+BW11+BX11+BZ11 -> 11112135 | CD11: =CD10+BU11-BZ11 -> 5711505.5
A12: =ROW()-5 -> 7 | B12: =Inputs!$D$58-(A12-1) -> 30 | C12: =IF(B12<=0,0,IF(A12=1,Inputs!$B$58,H11)) -> 30905014 | D12: =C12*Inputs!$B$9 -> 78345.712 | E12: =(C12-D12)*Inputs!$C$58/12 -> 187528.9 | F12: =IF(B12<=0,0,IF(B12=1,C12-D12,MIN((C12-D12)*(Inputs!$C$58/12)/(1-(1+Inputs!$C$58/12)^(-B12))-E12,C12-D12))) -> 939755.27 | G12: =(C12-D12-F12)*Inputs!$B$10 -> 261259.76 | H12: =C12-D12-F12-G12 -> 29625653 | I12: =Inputs!$D$59-(A12-1) -> 42 | J12: =IF(I12<=0,0,IF(A12=1,Inputs!$B$59,O11)) -> 62877297 | K12: =J12*Inputs!$B$9 -> 159397 | L12: =(J12-K12)*Inputs!$C$59/12 -> 407666.35 | M12: =IF(I12<=0,0,IF(I12=1,J12-K12,MIN((J12-K12)*(Inputs!$C$59/12)/(1-(1+Inputs!$C$59/12)^(-I12))-L12,J12-K12))) -> 1303531.1 | N12: =(J12-K12-M12)*Inputs!$B$10 -> 536860.52 | O12: =J12-K12-M12-N12 -> 60877508 | P12: =Inputs!$D$60-(A12-1) -> 42 | Q12: =IF(P12<=0,0,IF(A12=1,Inputs!$B$60,V11)) -> 18008851 | R12: =Q12*Inputs!$B$9 -> 45653.312 | S12: =(Q12-R12)*Inputs!$C$60/12 -> 124245.45 | T12: =IF(P12<=0,0,IF(P12=1,Q12-R12,MIN((Q12-R12)*(Inputs!$C$60/12)/(1-(1+Inputs!$C$60/12)^(-P12))-S12,Q12-R12))) -> 370043.11 | U12: =(Q12-R12-T12)*Inputs!$B$10 -> 153792.51 | V12: =Q12-R12-T12-U12 -> 17439362 | W12: =Inputs!$D$61-(A12-1) -> 54 | X12: =IF(W12<=0,0,IF(A12=1,Inputs!$B$61,AC11)) -> 57673944 | Y12: =X12*Inputs!$B$9 -> 146206.25 | Z12: =(X12-Y12)*Inputs!$C$61/12 -> 421870.07 | AA12: =IF(W12<=0,0,IF(W12=1,X12-Y12,MIN((X12-Y12)*(Inputs!$C$61/12)/(1-(1+Inputs!$C$61/12)^(-W12))-Z12,X12-Y12))) -> 872129.94 | AB12: =(X12-Y12-AA12)*Inputs!$B$10 -> 495261.28 | AC12: =X12-Y12-AA12-AB12 -> 56160346 | AD12: =Inputs!$D$62-(A12-1) -> 54 | AE12: =IF(AD12<=0,0,IF(A12=1,Inputs!$B$62,AJ11)) -> 16323990 | AF12: =AE12*Inputs!$B$9 -> 41382.109 | AG12: =(AE12-AF12)*Inputs!$C$62/12 -> 126190.21 | AH12: =IF(AD12<=0,0,IF(AD12=1,AE12-AF12,MIN((AE12-AF12)*(Inputs!$C$62/12)/(1-(1+Inputs!$C$62/12)^(-AD12))-AG12,AE12-AF12))) -> 243972.87 | AI12: =(AE12-AF12-AH12)*Inputs!$B$10 -> 140203.51 | AJ12: =AE12-AF12-AH12-AI12 -> 15898432 | AK12: =Inputs!$D$63-(A12-1) -> 54 | AL12: =IF(AK12<=0,0,IF(A12=1,Inputs!$B$63,AQ11)) -> 19513184 | AM12: =AL12*Inputs!$B$9 -> 49466.87 | AN12: =(AL12-AM12)*Inputs!$C$63/12 -> 154898.75 | AO12: =IF(AK12<=0,0,IF(AK12=1,AL12-AM12,MIN((AL12-AM12)*(Inputs!$C$63/12)/(1-(1+Inputs!$C$63/12)^(-AK12))-AN12,AL12-AM12))) -> 289930.74 | AP12: =(AL12-AM12-AO12)*Inputs!$B$10 -> 167609.78 | AQ12: =AL12-AM12-AO12-AP12 -> 19006177 | AR12: =Inputs!$D$64-(A12-1) -> 66 | AS12: =IF(AR12<=0,0,IF(A12=1,Inputs!$B$64,AX11)) -> 30822808 | AT12: =AS12*Inputs!$B$9 -> 78137.318 | AU12: =(AS12-AT12)*Inputs!$C$64/12 -> 251081.48 | AV12: =IF(AR12<=0,0,IF(AR12=1,AS12-AT12,MIN((AS12-AT12)*(Inputs!$C$64/12)/(1-(1+Inputs!$C$64/12)^(-AR12))-AU12,AS12-AT12))) -> 353365.53 | AW12: =(AS12-AT12-AV12)*Inputs!$B$10 -> 265668.97 | AX12: =AS12-AT12-AV12-AW12 -> 30125637 | AY12: =Inputs!$D$65-(A12-1) -> 66 | AZ12: =IF(AY12<=0,0,IF(A12=1,Inputs!$B$65,BE11)) -> 31905617 | BA12: =AZ12*Inputs!$B$9 -> 80882.29 | BB12: =(AZ12-BA12)*Inputs!$C$65/12 -> 273162.31 | BC12: =IF(AY12<=0,0,IF(AY12=1,AZ12-BA12,MIN((AZ12-BA12)*(Inputs!$C$65/12)/(1-(1+Inputs!$C$65/12)^(-AY12))-BB12,AZ12-BA12))) -> 360451.19 | BD12: =(AZ12-BA12-BC12)*Inputs!$B$10 -> 275048.53 | BE12: =AZ12-BA12-BC12-BD12 -> 31189235 | BF12: =Inputs!$D$66-(A12-1) -> 78 | BG12: =IF(BF12<=0,0,IF(A12=1,Inputs!$B$66,BL11)) -> 32055136 | BH12: =BG12*Inputs!$B$9 -> 81261.327 | BI12: =(BG12-BH12)*Inputs!$C$66/12 -> 281103.65 | BJ12: =IF(BF12<=0,0,IF(BF12=1,BG12-BH12,MIN((BG12-BH12)*(Inputs!$C$66/12)/(1-(1+Inputs!$C$66/12)^(-BF12))-BI12,BG12-BH12))) -> 287039.77 | BK12: =(BG12-BH12-BJ12)*Inputs!$B$10 -> 276993.98 | BL12: =BG12-BH12-BJ12-BK12 -> 31409841 | BM12: =Inputs!$D$67-(A12-1) -> 78 | BN12: =IF(BM12<=0,0,IF(A12=1,Inputs!$B$67,BS11)) -> 42039900 | BO12: =BN12*Inputs!$B$9 -> 106573.19 | BP12: =(BN12-BO12)*Inputs!$C$67/12 -> 386136.05 | BQ12: =IF(BM12<=0,0,IF(BM12=1,BN12-BO12,MIN((BN12-BO12)*(Inputs!$C$67/12)/(1-(1+Inputs!$C$67/12)^(-BM12))-BP12,BN12-BO12))) -> 369822.62 | BR12: =(BN12-BO12-BQ12)*Inputs!$B$10 -> 363331.99 | BS12: =BN12-BO12-BQ12-BR12 -> 41200172 | BT12: =C12+J12+Q12+X12+AE12+AL12+AS12+AZ12+BG12+BN12 -> 3.4212574e+08 | BU12: =D12+K12+R12+Y12+AF12+AM12+AT12+BA12+BH12+BO12 -> 867305.38 | BV12: =E12+L12+S12+Z12+AG12+AN12+AU12+BB12+BI12+BP12 -> 2613883.2 | BW12: =F12+M12+T12+AA12+AH12+AO12+AV12+BC12+BJ12+BQ12 -> 5390042.1 | BX12: =G12+N12+U12+AB12+AI12+AP12+AW12+BD12+BK12+BR12 -> 2936030.8 | BY12: =H12+O12+V12+AC12+AJ12+AQ12+AX12+BE12+BL12+BS12 -> 3.3293236e+08 | BZ12: =IF(A12>Inputs!$B$7,(1-Inputs!$B$6)*INDEX($BU$6:$BU$125,A12-Inputs!$B$7),0) -> 608411.67 | CA12: =CA11+(1-Inputs!$B$6)*BU12-BZ12 -> 3338874.9 | CB12: =BY12+CA12 -> 3.3627124e+08 | CC12: =BV12+BW12+BX12+BZ12 -> 11548368 | CD12: =CD11+BU12-BZ12 -> 5970399.2
A13: =ROW()-5 -> 8 | B13: =Inputs!$D$58-(A13-1) -> 29 | C13: =IF(B13<=0,0,IF(A13=1,Inputs!$B$58,H12)) -> 29625653 | D13: =C13*Inputs!$B$9 -> 75102.471 | E13: =(C13-D13)*Inputs!$C$58/12 -> 179765.85 | F13: =IF(B13<=0,0,IF(B13=1,C13-D13,MIN((C13-D13)*(Inputs!$C$58/12)/(1-(1+Inputs!$C$58/12)^(-B13))-E13,C13-D13))) -> 934831.3 | G13: =(C13-D13-F13)*Inputs!$B$10 -> 250147.48 | H13: =C13-D13-F13-G13 -> 28365572 | I13: =Inputs!$D$59-(A13-1) -> 41 | J13: =IF(I13<=0,0,IF(A13=1,Inputs!$B$59,O12)) -> 60877508 | K13: =J13*Inputs!$B$9 -> 154327.44 | L13: =(J13-K13)*Inputs!$C$59/12 -> 394700.68 | M13: =IF(I13<=0,0,IF(I13=1,J13-K13,MIN((J13-K13)*(Inputs!$C$59/12)/(1-(1+Inputs!$C$59/12)^(-I13))-L13,J13-K13))) -> 1297238.1 | N13: =(J13-K13-M13)*Inputs!$B$10 -> 519478.47 | O13: =J13-K13-M13-N13 -> 58906464 | P13: =Inputs!$D$60-(A13-1) -> 41 | Q13: =IF(P13<=0,0,IF(A13=1,Inputs!$B$60,V12)) -> 17439362 | R13: =Q13*Inputs!$B$9 -> 44209.63 | S13: =(Q13-R13)*Inputs!$C$60/12 -> 120316.47 | T13: =IF(P13<=0,0,IF(P13=1,Q13-R13,MIN((Q13-R13)*(Inputs!$C$60/12)/(1-(1+Inputs!$C$60/12)^(-P13))-S13,Q13-R13))) -> 368409.12 | U13: =(Q13-R13-T13)*Inputs!$B$10 -> 148841.16 | V13: =Q13-R13-T13-U13 -> 16877902 | W13: =Inputs!$D$61-(A13-1) -> 53 | X13: =IF(W13<=0,0,IF(A13=1,Inputs!$B$61,AC12)) -> 56160346 | Y13: =X13*Inputs!$B$9 -> 142369.21 | Z13: =(X13-Y13)*Inputs!$C$61/12 -> 410798.5 | AA13: =IF(W13<=0,0,IF(W13=1,X13-Y13,MIN((X13-Y13)*(Inputs!$C$61/12)/(1-(1+Inputs!$C$61/12)^(-W13))-Z13,X13-Y13))) -> 868638.19 | AB13: =(X13-Y13-AA13)*Inputs!$B$10 -> 482094.06 | AC13: =X13-Y13-AA13-AB13 -> 54667245 | AD13: =Inputs!$D$62-(A13-1) -> 53 | AE13: =IF(AD13<=0,0,IF(A13=1,Inputs!$B$62,AJ12)) -> 15898432 | AF13: =AE13*Inputs!$B$9 -> 40303.298 | AG13: =(AE13-AF13)*Inputs!$C$62/12 -> 122900.5 | AH13: =IF(AD13<=0,0,IF(AD13=1,AE13-AF13,MIN((AE13-AF13)*(Inputs!$C$62/12)/(1-(1+Inputs!$C$62/12)^(-AD13))-AG13,AE13-AF13))) -> 243096.59 | AI13: =(AE13-AF13-AH13)*Inputs!$B$10 -> 136500.54 | AJ13: =AE13-AF13-AH13-AI13 -> 15478532 | AK13: =Inputs!$D$63-(A13-1) -> 53 | AL13: =IF(AK13<=0,0,IF(A13=1,Inputs!$B$63,AQ12)) -> 19006177 | AM13: =AL13*Inputs!$B$9 -> 48181.582 | AN13: =(AL13-AM13)*Inputs!$C$63/12 -> 150874.04 | AO13: =IF(AK13<=0,0,IF(AK13=1,AL13-AM13,MIN((AL13-AM13)*(Inputs!$C$63/12)/(1-(1+Inputs!$C$63/12)^(-AK13))-AN13,AL13-AM13))) -> 288949.11 | AP13: =(AL13-AM13-AO13)*Inputs!$B$10 -> 163197.54 | AQ13: =AL13-AM13-AO13-AP13 -> 18505848 | AR13: =Inputs!$D$64-(A13-1) -> 65 | AS13: =IF(AR13<=0,0,IF(A13=1,Inputs!$B$64,AX12)) -> 30125637 | AT13: =AS13*Inputs!$B$9 -> 76369.953 | AU13: =(AS13-AT13)*Inputs!$C$64/12 -> 245402.34 | AV13: =IF(AR13<=0,0,IF(AR13=1,AS13-AT13,MIN((AS13-AT13)*(Inputs!$C$64/12)/(1-(1+Inputs!$C$64/12)^(-AR13))-AU13,AS13-AT13))) -> 352241.92 | AW13: =(AS13-AT13-AV13)*Inputs!$B$10 -> 259599.84 | AX13: =AS13-AT13-AV13-AW13 -> 29437425 | AY13: =Inputs!$D$65-(A13-1) -> 65 | AZ13: =IF(AY13<=0,0,IF(A13=1,Inputs!$B$65,BE12)) -> 31189235 | BA13: =AZ13*Inputs!$B$9 -> 79066.227 | BB13: =(AZ13-BA13)*Inputs!$C$65/12 -> 267028.95 | BC13: =IF(AY13<=0,0,IF(AY13=1,AZ13-BA13,MIN((AZ13-BA13)*(Inputs!$C$65/12)/(1-(1+Inputs!$C$65/12)^(-AY13))-BB13,AZ13-BA13))) -> 359453.54 | BD13: =(AZ13-BA13-BC13)*Inputs!$B$10 -> 268810.79 | BE13: =AZ13-BA13-BC13-BD13 -> 30481904 | BF13: =Inputs!$D$66-(A13-1) -> 77 | BG13: =IF(BF13<=0,0,IF(A13=1,Inputs!$B$66,BL12)) -> 31409841 | BH13: =BG13*Inputs!$B$9 -> 79625.473 | BI13: =(BG13-BH13)*Inputs!$C$66/12 -> 275444.81 | BJ13: =IF(BF13<=0,0,IF(BF13=1,BG13-BH13,MIN((BG13-BH13)*(Inputs!$C$66/12)/(1-(1+Inputs!$C$66/12)^(-BF13))-BI13,BG13-BH13))) -> 286304.43 | BK13: =(BG13-BH13-BJ13)*Inputs!$B$10 -> 271373.79 | BL13: =BG13-BH13-BJ13-BK13 -> 30772537 | BM13: =Inputs!$D$67-(A13-1) -> 77 | BN13: =IF(BM13<=0,0,IF(A13=1,Inputs!$B$67,BS12)) -> 41200172 | BO13: =BN13*Inputs!$B$9 -> 104444.44 | BP13: =(BN13-BO13)*Inputs!$C$67/12 -> 378423.16 | BQ13: =IF(BM13<=0,0,IF(BM13=1,BN13-BO13,MIN((BN13-BO13)*(Inputs!$C$67/12)/(1-(1+Inputs!$C$67/12)^(-BM13))-BP13,BN13-BO13))) -> 369027.58 | BR13: =(BN13-BO13-BQ13)*Inputs!$B$10 -> 356016.97 | BS13: =BN13-BO13-BQ13-BR13 -> 40370683 | BT13: =C13+J13+Q13+X13+AE13+AL13+AS13+AZ13+BG13+BN13 -> 3.3293236e+08 | BU13: =D13+K13+R13+Y13+AF13+AM13+AT13+BA13+BH13+BO13 -> 843999.72 | BV13: =E13+L13+S13+Z13+AG13+AN13+AU13+BB13+BI13+BP13 -> 2545655.3 | BW13: =F13+M13+T13+AA13+AH13+AO13+AV13+BC13+BJ13+BQ13 -> 5368189.9 | BX13: =G13+N13+U13+AB13+AI13+AP13+AW13+BD13+BK13+BR13 -> 2856060.6 | BY13: =H13+O13+V13+AC13+AJ13+AQ13+AX13+BE13+BL13+BS13 -> 3.2386411e+08 | BZ13: =IF(A13>Inputs!$B$7,(1-Inputs!$B$6)*INDEX($BU$6:$BU$125,A13-Inputs!$B$7),0) -> 593236.87 | CA13: =CA12+(1-Inputs!$B$6)*BU13-BZ13 -> 3252037.8 | CB13: =BY13+CA13 -> 3.2711615e+08 | CC13: =BV13+BW13+BX13+BZ13 -> 11363143 | CD13: =CD12+BU13-BZ13 -> 6221162.1
A14: =ROW()-5 -> 9 | B14: =Inputs!$D$58-(A14-1) -> 28 | C14: =IF(B14<=0,0,IF(A14=1,Inputs!$B$58,H13)) -> 28365572 | D14: =C14*Inputs!$B$9 -> 71908.103 | E14: =(C14-D14)*Inputs!$C$58/12 -> 172119.79 | F14: =IF(B14<=0,0,IF(B14=1,C14-D14,MIN((C14-D14)*(Inputs!$C$58/12)/(1-(1+Inputs!$C$58/12)^(-B14))-E14,C14-D14))) -> 929933.13 | G14: =(C14-D14-F14)*Inputs!$B$10 -> 239203.09 | H14: =C14-D14-F14-G14 -> 27124527 | I14: =Inputs!$D$59-(A14-1) -> 40 | J14: =IF(I14<=0,0,IF(A14=1,Inputs!$B$59,O13)) -> 58906464 | K14: =J14*Inputs!$B$9 -> 149330.75 | L14: =(J14-K14)*Inputs!$C$59/12 -> 381921.37 | M14: =IF(I14<=0,0,IF(I14=1,J14-K14,MIN((J14-K14)*(Inputs!$C$59/12)/(1-(1+Inputs!$C$59/12)^(-I14))-L14,J14-K14))) -> 1290975.5 | N14: =(J14-K14-M14)*Inputs!$B$10 -> 502346.8 | O14: =J14-K14-M14-N14 -> 56963811 | P14: =Inputs!$D$60-(A14-1) -> 40 | Q14: =IF(P14<=0,0,IF(A14=1,Inputs!$B$60,V13)) -> 16877902 | R14: =Q14*Inputs!$B$9 -> 42786.302 | S14: =(Q14-R14)*Inputs!$C$60/12 -> 116442.88 | T14: =IF(P14<=0,0,IF(P14=1,Q14-R14,MIN((Q14-R14)*(Inputs!$C$60/12)/(1-(1+Inputs!$C$60/12)^(-P14))-S14,Q14-R14))) -> 366782.34 | U14: =(Q14-R14-T14)*Inputs!$B$10 -> 143959.76 | V14: =Q14-R14-T14-U14 -> 16324373 | W14: =Inputs!$D$61-(A14-1) -> 52 | X14: =IF(W14<=0,0,IF(A14=1,Inputs!$B$61,AC13)) -> 54667245 | Y14: =X14*Inputs!$B$9 -> 138584.12 | Z14: =(X14-Y14)*Inputs!$C$61/12 -> 399876.84 | AA14: =IF(W14<=0,0,IF(W14=1,X14-Y14,MIN((X14-Y14)*(Inputs!$C$61/12)/(1-(1+Inputs!$C$61/12)^(-W14))-Z14,X14-Y14))) -> 865160.43 | AB14: =(X14-Y14-AA14)*Inputs!$B$10 -> 469105.44 | AC14: =X14-Y14-AA14-AB14 -> 53194395 | AD14: =Inputs!$D$62-(A14-1) -> 52 | AE14: =IF(AD14<=0,0,IF(A14=1,Inputs!$B$62,AJ13)) -> 15478532 | AF14: =AE14*Inputs!$B$9 -> 39238.83 | AG14: =(AE14-AF14)*Inputs!$C$62/12 -> 119654.52 | AH14: =IF(AD14<=0,0,IF(AD14=1,AE14-AF14,MIN((AE14-AF14)*(Inputs!$C$62/12)/(1-(1+Inputs!$C$62/12)^(-AD14))-AG14,AE14-AF14))) -> 242223.46 | AI14: =(AE14-AF14-AH14)*Inputs!$B$10 -> 132846.87 | AJ14: =AE14-AF14-AH14-AI14 -> 15064222 | AK14: =Inputs!$D$63-(A14-1) -> 52 | AL14: =IF(AK14<=0,0,IF(A14=1,Inputs!$B$63,AQ13)) -> 18505848 | AM14: =AL14*Inputs!$B$9 -> 46913.225 | AN14: =(AL14-AM14)*Inputs!$C$63/12 -> 146902.36 | AO14: =IF(AK14<=0,0,IF(AK14=1,AL14-AM14,MIN((AL14-AM14)*(Inputs!$C$63/12)/(1-(1+Inputs!$C$63/12)^(-AK14))-AN14,AL14-AM14))) -> 287970.81 | AP14: =(AL14-AM14-AO14)*Inputs!$B$10 -> 158843.5 | AQ14: =AL14-AM14-AO14-AP14 -> 18012121 | AR14: =Inputs!$D$64-(A14-1) -> 64 | AS14: =IF(AR14<=0,0,IF(A14=1,Inputs!$B$64,AX13)) -> 29437425 | AT14: =AS14*Inputs!$B$9 -> 74625.303 | AU14: =(AS14-AT14)*Inputs!$C$64/12 -> 239796.2 | AV14: =IF(AR14<=0,0,IF(AR14=1,AS14-AT14,MIN((AS14-AT14)*(Inputs!$C$64/12)/(1-(1+Inputs!$C$64/12)^(-AR14))-AU14,AS14-AT14))) -> 351121.88 | AW14: =(AS14-AT14-AV14)*Inputs!$B$10 -> 253608.8 | AX14: =AS14-AT14-AV14-AW14 -> 28758069 | AY14: =Inputs!$D$65-(A14-1) -> 64 | AZ14: =IF(AY14<=0,0,IF(A14=1,Inputs!$B$65,BE13)) -> 30481904 | BA14: =AZ14*Inputs!$B$9 -> 77273.11 | BB14: =(AZ14-BA14)*Inputs!$C$65/12 -> 260973.09 | BC14: =IF(AY14<=0,0,IF(AY14=1,AZ14-BA14,MIN((AZ14-BA14)*(Inputs!$C$65/12)/(1-(1+Inputs!$C$65/12)^(-AY14))-BB14,AZ14-BA14))) -> 358458.66 | BD14: =(AZ14-BA14-BC14)*Inputs!$B$10 -> 262651.95 | BE14: =AZ14-BA14-BC14-BD14 -> 29783521 | BF14: =Inputs!$D$66-(A14-1) -> 76 | BG14: =IF(BF14<=0,0,IF(A14=1,Inputs!$B$66,BL13)) -> 30772537 | BH14: =BG14*Inputs!$B$9 -> 78009.877 | BI14: =(BG14-BH14)*Inputs!$C$66/12 -> 269856.05 | BJ14: =IF(BF14<=0,0,IF(BF14=1,BG14-BH14,MIN((BG14-BH14)*(Inputs!$C$66/12)/(1-(1+Inputs!$C$66/12)^(-BF14))-BI14,BG14-BH14))) -> 285570.98 | BK14: =(BG14-BH14-BJ14)*Inputs!$B$10 -> 265823.26 | BL14: =BG14-BH14-BJ14-BK14 -> 30143133 | BM14: =Inputs!$D$67-(A14-1) -> 76 | BN14: =IF(BM14<=0,0,IF(A14=1,Inputs!$B$67,BS13)) -> 40370683 | BO14: =BN14*Inputs!$B$9 -> 102341.64 | BP14: =(BN14-BO14)*Inputs!$C$67/12 -> 370804.31 | BQ14: =IF(BM14<=0,0,IF(BM14=1,BN14-BO14,MIN((BN14-BO14)*(Inputs!$C$67/12)/(1-(1+Inputs!$C$67/12)^(-BM14))-BP14,BN14-BO14))) -> 368234.24 | BR14: =(BN14-BO14-BQ14)*Inputs!$B$10 -> 348791.22 | BS14: =BN14-BO14-BQ14-BR14 -> 39551316 | BT14: =C14+J14+Q14+X14+AE14+AL14+AS14+AZ14+BG14+BN14 -> 3.2386411e+08 | BU14: =D14+K14+R14+Y14+AF14+AM14+AT14+BA14+BH14+BO14 -> 821011.27 | BV14: =E14+L14+S14+Z14+AG14+AN14+AU14+BB14+BI14+BP14 -> 2478347.4 | BW14: =F14+M14+T14+AA14+AH14+AO14+AV14+BC14+BJ14+BQ14 -> 5346431.4 | BX14: =G14+N14+U14+AB14+AI14+AP14+AW14+BD14+BK14+BR14 -> 2777180.7 | BY14: =H14+O14+V14+AC14+AJ14+AQ14+AX14+BE14+BL14+BS14 -> 3.1491949e+08 | BZ14: =IF(A14>Inputs!$B$7,(1-Inputs!$B$6)*INDEX($BU$6:$BU$125,A14-Inputs!$B$7),0) -> 578266.66 | CA14: =CA13+(1-Inputs!$B$6)*BU14-BZ14 -> 3166377.9 | CB14: =BY14+CA14 -> 3.1808587e+08 | CC14: =BV14+BW14+BX14+BZ14 -> 11180226 | CD14: =CD13+BU14-BZ14 -> 6463906.7
A15: =ROW()-5 -> 10 | B15: =Inputs!$D$58-(A15-1) -> 27 | C15: =IF(B15<=0,0,IF(A15=1,Inputs!$B$58,H14)) -> 27124527 | D15: =C15*Inputs!$B$9 -> 68761.996 | E15: =(C15-D15)*Inputs!$C$58/12 -> 164589.24 | F15: =IF(B15<=0,0,IF(B15=1,C15-D15,MIN((C15-D15)*(Inputs!$C$58/12)/(1-(1+Inputs!$C$58/12)^(-B15))-E15,C15-D15))) -> 925060.62 | G15: =(C15-D15-F15)*Inputs!$B$10 -> 228424.46 | H15: =C15-D15-F15-G15 -> 25902280 | I15: =Inputs!$D$59-(A15-1) -> 39 | J15: =IF(I15<=0,0,IF(A15=1,Inputs!$B$59,O14)) -> 56963811 | K15: =J15*Inputs!$B$9 -> 144406.03 | L15: =(J15-K15)*Inputs!$C$59/12 -> 369326.13 | M15: =IF(I15<=0,0,IF(I15=1,J15-K15,MIN((J15-K15)*(Inputs!$C$59/12)/(1-(1+Inputs!$C$59/12)^(-I15))-L15,J15-K15))) -> 1284743.1 | N15: =(J15-K15-M15)*Inputs!$B$10 -> 485462.41 | O15: =J15-K15-M15-N15 -> 55049200 | P15: =Inputs!$D$60-(A15-1) -> 39 | Q15: =IF(P15<=0,0,IF(A15=1,Inputs!$B$60,V14)) -> 16324373 | R15: =Q15*Inputs!$B$9 -> 41383.08 | S15: =(Q15-R15)*Inputs!$C$60/12 -> 112624.02 | T15: =IF(P15<=0,0,IF(P15=1,Q15-R15,MIN((Q15-R15)*(Inputs!$C$60/12)/(1-(1+Inputs!$C$60/12)^(-P15))-S15,Q15-R15))) -> 365162.75 | U15: =(Q15-R15-T15)*Inputs!$B$10 -> 139147.46 | V15: =Q15-R15-T15-U15 -> 15778680 | W15: =Inputs!$D$61-(A15-1) -> 51 | X15: =IF(W15<=0,0,IF(A15=1,Inputs!$B$61,AC14)) -> 53194395 | Y15: =X15*Inputs!$B$9 -> 134850.38 | Z15: =(X15-Y15)*Inputs!$C$61/12 -> 389103.32 | AA15: =IF(W15<=0,0,IF(W15=1,X15-Y15,MIN((X15-Y15)*(Inputs!$C$61/12)/(1-(1+Inputs!$C$61/12)^(-W15))-Z15,X15-Y15))) -> 861696.58 | AB15: =(X15-Y15-AA15)*Inputs!$B$10 -> 456293.28 | AC15: =X15-Y15-AA15-AB15 -> 51741554 | AD15: =Inputs!$D$62-(A15-1) -> 51 | AE15: =IF(AD15<=0,0,IF(A15=1,Inputs!$B$62,AJ14)) -> 15064222 | AF15: =AE15*Inputs!$B$9 -> 38188.536 | AG15: =(AE15-AF15)*Inputs!$C$62/12 -> 116451.76 | AH15: =IF(AD15<=0,0,IF(AD15=1,AE15-AF15,MIN((AE15-AF15)*(Inputs!$C$62/12)/(1-(1+Inputs!$C$62/12)^(-AD15))-AG15,AE15-AF15))) -> 241353.46 | AI15: =(AE15-AF15-AH15)*Inputs!$B$10 -> 129241.92 | AJ15: =AE15-AF15-AH15-AI15 -> 14655438 | AK15: =Inputs!$D$63-(A15-1) -> 51 | AL15: =IF(AK15<=0,0,IF(A15=1,Inputs!$B$63,AQ14)) -> 18012121 | AM15: =AL15*Inputs!$B$9 -> 45661.602 | AN15: =(AL15-AM15)*Inputs!$C$63/12 -> 142983.07 | AO15: =IF(AK15<=0,0,IF(AK15=1,AL15-AM15,MIN((AL15-AM15)*(Inputs!$C$63/12)/(1-(1+Inputs!$C$63/12)^(-AK15))-AN15,AL15-AM15))) -> 286995.81 | AP15: =(AL15-AM15-AO15)*Inputs!$B$10 -> 154546.99 | AQ15: =AL15-AM15-AO15-AP15 -> 17524916 | AR15: =Inputs!$D$64-(A15-1) -> 63 | AS15: =IF(AR15<=0,0,IF(A15=1,Inputs!$B$64,AX14)) -> 28758069 | AT15: =AS15*Inputs!$B$9 -> 72903.103 | AU15: =(AS15-AT15)*Inputs!$C$64/12 -> 234262.19 | AV15: =IF(AR15<=0,0,IF(AR15=1,AS15-AT15,MIN((AS15-AT15)*(Inputs!$C$64/12)/(1-(1+Inputs!$C$64/12)^(-AR15))-AU15,AS15-AT15))) -> 350005.4 | AW15: =(AS15-AT15-AV15)*Inputs!$B$10 -> 247694.95 | AX15: =AS15-AT15-AV15-AW15 -> 28087466 | AY15: =Inputs!$D$65-(A15-1) -> 63 | AZ15: =IF(AY15<=0,0,IF(A15=1,Inputs!$B$65,BE14)) -> 29783521 | BA15: =AZ15*Inputs!$B$9 -> 75502.673 | BB15: =(AZ15-BA15)*Inputs!$C$65/12 -> 254993.82 | BC15: =IF(AY15<=0,0,IF(AY15=1,AZ15-BA15,MIN((AZ15-BA15)*(Inputs!$C$65/12)/(1-(1+Inputs!$C$65/12)^(-AY15))-BB15,AZ15-BA15))) -> 357466.53 | BD15: =(AZ15-BA15-BC15)*Inputs!$B$10 -> 256571.1 | BE15: =AZ15-BA15-BC15-BD15 -> 29093980 | BF15: =Inputs!$D$66-(A15-1) -> 75 | BG15: =IF(BF15<=0,0,IF(A15=1,Inputs!$B$66,BL14)) -> 30143133 | BH15: =BG15*Inputs!$B$9 -> 76414.307 | BI15: =(BG15-BH15)*Inputs!$C$66/12 -> 264336.57 | BJ15: =IF(BF15<=0,0,IF(BF15=1,BG15-BH15,MIN((BG15-BH15)*(Inputs!$C$66/12)/(1-(1+Inputs!$C$66/12)^(-BF15))-BI15,BG15-BH15))) -> 284839.41 | BK15: =(BG15-BH15-BJ15)*Inputs!$B$10 -> 260341.6 | BL15: =BG15-BH15-BJ15-BK15 -> 29521537 | BM15: =Inputs!$D$67-(A15-1) -> 75 | BN15: =IF(BM15<=0,0,IF(A15=1,Inputs!$B$67,BS14)) -> 39551316 | BO15: =BN15*Inputs!$B$9 -> 100264.51 | BP15: =(BN15-BO15)*Inputs!$C$67/12 -> 363278.44 | BQ15: =IF(BM15<=0,0,IF(BM15=1,BN15-BO15,MIN((BN15-BO15)*(Inputs!$C$67/12)/(1-(1+Inputs!$C$67/12)^(-BM15))-BP15,BN15-BO15))) -> 367442.61 | BR15: =(BN15-BO15-BQ15)*Inputs!$B$10 -> 341653.71 | BS15: =BN15-BO15-BQ15-BR15 -> 38741955 | BT15: =C15+J15+Q15+X15+AE15+AL15+AS15+AZ15+BG15+BN15 -> 3.1491949e+08 | BU15: =D15+K15+R15+Y15+AF15+AM15+AT15+BA15+BH15+BO15 -> 798336.21 | BV15: =E15+L15+S15+Z15+AG15+AN15+AU15+BB15+BI15+BP15 -> 2411948.6 | BW15: =F15+M15+T15+AA15+AH15+AO15+AV15+BC15+BJ15+BQ15 -> 5324766.3 | BX15: =G15+N15+U15+AB15+AI15+AP15+AW15+BD15+BK15+BR15 -> 2699377.9 | BY15: =H15+O15+V15+AC15+AJ15+AQ15+AX15+BE15+BL15+BS15 -> 3.0609701e+08 | BZ15: =IF(A15>Inputs!$B$7,(1-Inputs!$B$6)*INDEX($BU$6:$BU$125,A15-Inputs!$B$7),0) -> 563498.6 | CA15: =CA14+(1-Inputs!$B$6)*BU15-BZ15 -> 3081881.1 | CB15: =BY15+CA15 -> 3.0917889e+08 | CC15: =BV15+BW15+BX15+BZ15 -> 10999591 | CD15: =CD14+BU15-BZ15 -> 6698744.3
A16: =ROW()-5 -> 11 | B16: =Inputs!$D$58-(A16-1) -> 26 | C16: =IF(B16<=0,0,IF(A16=1,Inputs!$B$58,H15)) -> 25902280 | D16: =C16*Inputs!$B$9 -> 65663.54 | E16: =(C16-D16)*Inputs!$C$58/12 -> 157172.75 | F16: =IF(B16<=0,0,IF(B16=1,C16-D16,MIN((C16-D16)*(Inputs!$C$58/12)/(1-(1+Inputs!$C$58/12)^(-B16))-E16,C16-D16))) -> 920213.65 | G16: =(C16-D16-F16)*Inputs!$B$10 -> 217809.5 | H16: =C16-D16-F16-G16 -> 24698594 | I16: =Inputs!$D$59-(A16-1) -> 38 | J16: =IF(I16<=0,0,IF(A16=1,Inputs!$B$59,O15)) -> 55049200 | K16: =J16*Inputs!$B$9 -> 139552.4 | L16: =(J16-K16)*Inputs!$C$59/12 -> 356912.71 | M16: =IF(I16<=0,0,IF(I16=1,J16-K16,MIN((J16-K16)*(Inputs!$C$59/12)/(1-(1+Inputs!$C$59/12)^(-I16))-L16,J16-K16))) -> 1278540.8 | N16: =(J16-K16-M16)*Inputs!$B$10 -> 468822.27 | O16: =J16-K16-M16-N16 -> 53162284 | P16: =Inputs!$D$60-(A16-1) -> 38 | Q16: =IF(P16<=0,0,IF(A16=1,Inputs!$B$60,V15)) -> 15778680 | R16: =Q16*Inputs!$B$9 -> 39999.721 | S16: =(Q16-R16)*Inputs!$C$60/12 -> 108859.21 | T16: =IF(P16<=0,0,IF(P16=1,Q16-R16,MIN((Q16-R16)*(Inputs!$C$60/12)/(1-(1+Inputs!$C$60/12)^(-P16))-S16,Q16-R16))) -> 363550.31 | U16: =(Q16-R16-T16)*Inputs!$B$10 -> 134403.41 | V16: =Q16-R16-T16-U16 -> 15240727 | W16: =Inputs!$D$61-(A16-1) -> 50 | X16: =IF(W16<=0,0,IF(A16=1,Inputs!$B$61,AC15)) -> 51741554 | Y16: =X16*Inputs!$B$9 -> 131167.36 | Z16: =(X16-Y16)*Inputs!$C$61/12 -> 378476.17 | AA16: =IF(W16<=0,0,IF(W16=1,X16-Y16,MIN((X16-Y16)*(Inputs!$C$61/12)/(1-(1+Inputs!$C$61/12)^(-W16))-Z16,X16-Y16))) -> 858246.61 | AB16: =(X16-Y16-AA16)*Inputs!$B$10 -> 443655.47 | AC16: =X16-Y16-AA16-AB16 -> 50308485 | AD16: =Inputs!$D$62-(A16-1) -> 50 | AE16: =IF(AD16<=0,0,IF(A16=1,Inputs!$B$62,AJ15)) -> 14655438 | AF16: =AE16*Inputs!$B$9 -> 37152.249 | AG16: =(AE16-AF16)*Inputs!$C$62/12 -> 113291.72 | AH16: =IF(AD16<=0,0,IF(AD16=1,AE16-AF16,MIN((AE16-AF16)*(Inputs!$C$62/12)/(1-(1+Inputs!$C$62/12)^(-AD16))-AG16,AE16-AF16))) -> 240486.58 | AI16: =(AE16-AF16-AH16)*Inputs!$B$10 -> 125685.13 | AJ16: =AE16-AF16-AH16-AI16 -> 14252115 | AK16: =Inputs!$D$63-(A16-1) -> 50 | AL16: =IF(AK16<=0,0,IF(A16=1,Inputs!$B$63,AQ15)) -> 17524916 | AM16: =AL16*Inputs!$B$9 -> 44426.515 | AN16: =(AL16-AM16)*Inputs!$C$63/12 -> 139115.57 | AO16: =IF(AK16<=0,0,IF(AK16=1,AL16-AM16,MIN((AL16-AM16)*(Inputs!$C$63/12)/(1-(1+Inputs!$C$63/12)^(-AK16))-AN16,AL16-AM16))) -> 286024.12 | AP16: =(AL16-AM16-AO16)*Inputs!$B$10 -> 150307.33 | AQ16: =AL16-AM16-AO16-AP16 -> 17044158 | AR16: =Inputs!$D$64-(A16-1) -> 62 | AS16: =IF(AR16<=0,0,IF(A16=1,Inputs!$B$64,AX15)) -> 28087466 | AT16: =AS16*Inputs!$B$9 -> 71203.09 | AU16: =(AS16-AT16)*Inputs!$C$64/12 -> 228799.48 | AV16: =IF(AR16<=0,0,IF(AR16=1,AS16-AT16,MIN((AS16-AT16)*(Inputs!$C$64/12)/(1-(1+Inputs!$C$64/12)^(-AR16))-AU16,AS16-AT16))) -> 348892.47 | AW16: =(AS16-AT16-AV16)*Inputs!$B$10 -> 241857.38 | AX16: =AS16-AT16-AV16-AW16 -> 27425513 | AY16: =Inputs!$D$65-(A16-1) -> 62 | AZ16: =IF(AY16<=0,0,IF(A16=1,Inputs!$B$65,BE15)) -> 29093980 | BA16: =AZ16*Inputs!$B$9 -> 73754.655 | BB16: =(AZ16-BA16)*Inputs!$C$65/12 -> 249090.27 | BC16: =IF(AY16<=0,0,IF(AY16=1,AZ16-BA16,MIN((AZ16-BA16)*(Inputs!$C$65/12)/(1-(1+Inputs!$C$65/12)^(-AY16))-BB16,AZ16-BA16))) -> 356477.14 | BD16: =(AZ16-BA16-BC16)*Inputs!$B$10 -> 250567.34 | BE16: =AZ16-BA16-BC16-BD16 -> 28413181 | BF16: =Inputs!$D$66-(A16-1) -> 74 | BG16: =IF(BF16<=0,0,IF(A16=1,Inputs!$B$66,BL15)) -> 29521537 | BH16: =BG16*Inputs!$B$9 -> 74838.533 | BI16: =(BG16-BH16)*Inputs!$C$66/12 -> 258885.56 | BJ16: =IF(BF16<=0,0,IF(BF16=1,BG16-BH16,MIN((BG16-BH16)*(Inputs!$C$66/12)/(1-(1+Inputs!$C$66/12)^(-BF16))-BI16,BG16-BH16))) -> 284109.72 | BK16: =(BG16-BH16-BJ16)*Inputs!$B$10 -> 254928.01 | BL16: =BG16-BH16-BJ16-BK16 -> 28907661 | BM16: =Inputs!$D$67-(A16-1) -> 74 | BN16: =IF(BM16<=0,0,IF(A16=1,Inputs!$B$67,BS15)) -> 38741955 | BO16: =BN16*Inputs!$B$9 -> 98212.74 | BP16: =(BN16-BO16)*Inputs!$C$67/12 -> 355844.46 | BQ16: =IF(BM16<=0,0,IF(BM16=1,BN16-BO16,MIN((BN16-BO16)*(Inputs!$C$67/12)/(1-(1+Inputs!$C$67/12)^(-BM16))-BP16,BN16-BO16))) -> 366652.68 | BR16: =(BN16-BO16-BQ16)*Inputs!$B$10 -> 334603.43 | BS16: =BN16-BO16-BQ16-BR16 -> 37942487 | BT16: =C16+J16+Q16+X16+AE16+AL16+AS16+AZ16+BG16+BN16 -> 3.0609701e+08 | BU16: =D16+K16+R16+Y16+AF16+AM16+AT16+BA16+BH16+BO16 -> 775970.8 | BV16: =E16+L16+S16+Z16+AG16+AN16+AU16+BB16+BI16+BP16 -> 2346447.9 | BW16: =F16+M16+T16+AA16+AH16+AO16+AV16+BC16+BJ16+BQ16 -> 5303194.1 | BX16: =G16+N16+U16+AB16+AI16+AP16+AW16+BD16+BK16+BR16 -> 2622639.3 | BY16: =H16+O16+V16+AC16+AJ16+AQ16+AX16+BE16+BL16+BS16 -> 2.973952e+08 | BZ16: =IF(A16>Inputs!$B$7,(1-Inputs!$B$6)*INDEX($BU$6:$BU$125,A16-Inputs!$B$7),0) -> 548930.26 | CA16: =CA15+(1-Inputs!$B$6)*BU16-BZ16 -> 2998533.3 | CB16: =BY16+CA16 -> 3.0039374e+08 | CC16: =BV16+BW16+BX16+BZ16 -> 10821212 | CD16: =CD15+BU16-BZ16 -> 6925784.9
A17: =ROW()-5 -> 12 | B17: =Inputs!$D$58-(A17-1) -> 25 | C17: =IF(B17<=0,0,IF(A17=1,Inputs!$B$58,H16)) -> 24698594 | D17: =C17*Inputs!$B$9 -> 62612.136 | E17: =(C17-D17)*Inputs!$C$58/12 -> 149868.89 | F17: =IF(B17<=0,0,IF(B17=1,C17-D17,MIN((C17-D17)*(Inputs!$C$58/12)/(1-(1+Inputs!$C$58/12)^(-B17))-E17,C17-D17))) -> 915392.07 | G17: =(C17-D17-F17)*Inputs!$B$10 -> 207356.16 | H17: =C17-D17-F17-G17 -> 23513233 | I17: =Inputs!$D$59-(A17-1) -> 37 | J17: =IF(I17<=0,0,IF(A17=1,Inputs!$B$59,O16)) -> 53162284 | K17: =J17*Inputs!$B$9 -> 134768.97 | L17: =(J17-K17)*Inputs!$C$59/12 -> 344678.85 | M17: =IF(I17<=0,0,IF(I17=1,J17-K17,MIN((J17-K17)*(Inputs!$C$59/12)/(1-(1+Inputs!$C$59/12)^(-I17))-L17,J17-K17))) -> 1272368.5 | N17: =(J17-K17-M17)*Inputs!$B$10 -> 452423.36 | O17: =J17-K17-M17-N17 -> 51302723 | P17: =Inputs!$D$60-(A17-1) -> 37 | Q17: =IF(P17<=0,0,IF(A17=1,Inputs!$B$60,V16)) -> 15240727 | R17: =Q17*Inputs!$B$9 -> 38635.983 | S17: =(Q17-R17)*Inputs!$C$60/12 -> 105147.79 | T17: =IF(P17<=0,0,IF(P17=1,Q17-R17,MIN((Q17-R17)*(Inputs!$C$60/12)/(1-(1+Inputs!$C$60/12)^(-P17))-S17,Q17-R17))) -> 361944.99 | U17: =(Q17-R17-T17)*Inputs!$B$10 -> 129726.78 | V17: =Q17-R17-T17-U17 -> 14710419 | W17: =Inputs!$D$61-(A17-1) -> 49 | X17: =IF(W17<=0,0,IF(A17=1,Inputs!$B$61,AC16)) -> 50308485 | Y17: =X17*Inputs!$B$9 -> 127534.45 | Z17: =(X17-Y17)*Inputs!$C$61/12 -> 367993.64 | AA17: =IF(W17<=0,0,IF(W17=1,X17-Y17,MIN((X17-Y17)*(Inputs!$C$61/12)/(1-(1+Inputs!$C$61/12)^(-W17))-Z17,X17-Y17))) -> 854810.45 | AB17: =(X17-Y17-AA17)*Inputs!$B$10 -> 431189.93 | AC17: =X17-Y17-AA17-AB17 -> 48894950 | AD17: =Inputs!$D$62-(A17-1) -> 49 | AE17: =IF(AD17<=0,0,IF(A17=1,Inputs!$B$62,AJ16)) -> 14252115 | AF17: =AE17*Inputs!$B$9 -> 36129.803 | AG17: =(AE17-AF17)*Inputs!$C$62/12 -> 110173.88 | AH17: =IF(AD17<=0,0,IF(AD17=1,AE17-AF17,MIN((AE17-AF17)*(Inputs!$C$62/12)/(1-(1+Inputs!$C$62/12)^(-AD17))-AG17,AE17-AF17))) -> 239622.82 | AI17: =(AE17-AF17-AH17)*Inputs!$B$10 -> 122175.92 | AJ17: =AE17-AF17-AH17-AI17 -> 13854186 | AK17: =Inputs!$D$63-(A17-1) -> 49 | AL17: =IF(AK17<=0,0,IF(A17=1,Inputs!$B$63,AQ16)) -> 17044158 | AM17: =AL17*Inputs!$B$9 -> 43207.77 | AN17: =(AL17-AM17)*Inputs!$C$63/12 -> 135299.23 | AO17: =IF(AK17<=0,0,IF(AK17=1,AL17-AM17,MIN((AL17-AM17)*(Inputs!$C$63/12)/(1-(1+Inputs!$C$63/12)^(-AK17))-AN17,AL17-AM17))) -> 285055.72 | AP17: =(AL17-AM17-AO17)*Inputs!$B$10 -> 146123.85 | AQ17: =AL17-AM17-AO17-AP17 -> 16569771 | AR17: =Inputs!$D$64-(A17-1) -> 61 | AS17: =IF(AR17<=0,0,IF(A17=1,Inputs!$B$64,AX16)) -> 27425513 | AT17: =AS17*Inputs!$B$9 -> 69525.008 | AU17: =(AS17-AT17)*Inputs!$C$64/12 -> 223407.23 | AV17: =IF(AR17<=0,0,IF(AR17=1,AS17-AT17,MIN((AS17-AT17)*(Inputs!$C$64/12)/(1-(1+Inputs!$C$64/12)^(-AR17))-AU17,AS17-AT17))) -> 347783.08 | AW17: =(AS17-AT17-AV17)*Inputs!$B$10 -> 236095.22 | AX17: =AS17-AT17-AV17-AW17 -> 26772109 | AY17: =Inputs!$D$65-(A17-1) -> 61 | AZ17: =IF(AY17<=0,0,IF(A17=1,Inputs!$B$65,BE16)) -> 28413181 | BA17: =AZ17*Inputs!$B$9 -> 72028.796 | BB17: =(AZ17-BA17)*Inputs!$C$65/12 -> 243261.56 | BC17: =IF(AY17<=0,0,IF(AY17=1,AZ17-BA17,MIN((AZ17-BA17)*(Inputs!$C$65/12)/(1-(1+Inputs!$C$65/12)^(-AY17))-BB17,AZ17-BA17))) -> 355490.5 | BD17: =(AZ17-BA17-BC17)*Inputs!$B$10 -> 244639.77 | BE17: =AZ17-BA17-BC17-BD17 -> 27741022 | BF17: =Inputs!$D$66-(A17-1) -> 73 | BG17: =IF(BF17<=0,0,IF(A17=1,Inputs!$B$66,BL16)) -> 28907661 | BH17: =BG17*Inputs!$B$9 -> 73282.326 | BI17: =(BG17-BH17)*Inputs!$C$66/12 -> 253502.25 | BJ17: =IF(BF17<=0,0,IF(BF17=1,BG17-BH17,MIN((BG17-BH17)*(Inputs!$C$66/12)/(1-(1+Inputs!$C$66/12)^(-BF17))-BI17,BG17-BH17))) -> 283381.89 | BK17: =(BG17-BH17-BJ17)*Inputs!$B$10 -> 249581.71 | BL17: =BG17-BH17-BJ17-BK17 -> 28301415 | BM17: =Inputs!$D$67-(A17-1) -> 73 | BN17: =IF(BM17<=0,0,IF(A17=1,Inputs!$B$67,BS16)) -> 37942487 | BO17: =BN17*Inputs!$B$9 -> 96186.048 | BP17: =(BN17-BO17)*Inputs!$C$67/12 -> 348501.35 | BQ17: =IF(BM17<=0,0,IF(BM17=1,BN17-BO17,MIN((BN17-BO17)*(Inputs!$C$67/12)/(1-(1+Inputs!$C$67/12)^(-BM17))-BP17,BN17-BO17))) -> 365864.45 | BR17: =(BN17-BO17-BQ17)*Inputs!$B$10 -> 327639.39 | BS17: =BN17-BO17-BQ17-BR17 -> 37152797 | BT17: =C17+J17+Q17+X17+AE17+AL17+AS17+AZ17+BG17+BN17 -> 2.973952e+08 | BU17: =D17+K17+R17+Y17+AF17+AM17+AT17+BA17+BH17+BO17 -> 753911.3 | BV17: =E17+L17+S17+Z17+AG17+AN17+AU17+BB17+BI17+BP17 -> 2281834.7 | BW17: =F17+M17+T17+AA17+AH17+AO17+AV17+BC17+BJ17+BQ17 -> 5281714.4 | BX17: =G17+N17+U17+AB17+AI17+AP17+AW17+BD17+BK17+BR17 -> 2546952.1 | BY17: =H17+O17+V17+AC17+AJ17+AQ17+AX17+BE17+BL17+BS17 -> 2.8881263e+08 | BZ17: =IF(A17>Inputs!$B$7,(1-Inputs!$B$6)*INDEX($BU$6:$BU$125,A17-Inputs!$B$7),0) -> 534559.26 | CA17: =CA16+(1-Inputs!$B$6)*BU17-BZ17 -> 2916320.8 | CB17: =BY17+CA17 -> 2.9172895e+08 | CC17: =BV17+BW17+BX17+BZ17 -> 10645060 | CD17: =CD16+BU17-BZ17 -> 7145136.9
... A125: =ROW()-5 -> 120 | B125: =Inputs!$D$58-(A125-1) -> -83 | C125: =IF(B125<=0,0,IF(A125=1,Inputs!$B$58,H124)) -> 0 | D125: =C125*Inputs!$B$9 -> 0 | E125: =(C125-D125)*Inputs!$C$58/12 -> 0 | F125: =IF(B125<=0,0,IF(B125=1,C125-D125,MIN((C125-D125)*(Inputs!$C$58/12)/(1-(1+Inputs!$C$58/12)^(-B125))-E125,C125-D125))) -> 0 | G125: =(C125-D125-F125)*Inputs!$B$10 -> 0 | H125: =C125-D125-F125-G125 -> 0 | I125: =Inputs!$D$59-(A125-1) -> -71 | J125: =IF(I125<=0,0,IF(A125=1,Inputs!$B$59,O124)) -> 0 | K125: =J125*Inputs!$B$9 -> 0 | L125: =(J125-K125)*Inputs!$C$59/12 -> 0 | M125: =IF(I125<=0,0,IF(I125=1,J125-K125,MIN((J125-K125)*(Inputs!$C$59/12)/(1-(1+Inputs!$C$59/12)^(-I125))-L125,J125-K125))) -> 0 | N125: =(J125-K125-M125)*Inputs!$B$10 -> 0 | O125: =J125-K125-M125-N125 -> 0 | P125: =Inputs!$D$60-(A125-1) -> -71 | Q125: =IF(P125<=0,0,IF(A125=1,Inputs!$B$60,V124)) -> 0 | R125: =Q125*Inputs!$B$9 -> 0 | S125: =(Q125-R125)*Inputs!$C$60/12 -> 0 | T125: =IF(P125<=0,0,IF(P125=1,Q125-R125,MIN((Q125-R125)*(Inputs!$C$60/12)/(1-(1+Inputs!$C$60/12)^(-P125))-S125,Q125-R125))) -> 0 | U125: =(Q125-R125-T125)*Inputs!$B$10 -> 0 | V125: =Q125-R125-T125-U125 -> 0 | W125: =Inputs!$D$61-(A125-1) -> -59 | X125: =IF(W125<=0,0,IF(A125=1,Inputs!$B$61,AC124)) -> 0 | Y125: =X125*Inputs!$B$9 -> 0 | Z125: =(X125-Y125)*Inputs!$C$61/12 -> 0 | AA125: =IF(W125<=0,0,IF(W125=1,X125-Y125,MIN((X125-Y125)*(Inputs!$C$61/12)/(1-(1+Inputs!$C$61/12)^(-W125))-Z125,X125-Y125))) -> 0 | AB125: =(X125-Y125-AA125)*Inputs!$B$10 -> 0 | AC125: =X125-Y125-AA125-AB125 -> 0 | AD125: =Inputs!$D$62-(A125-1) -> -59 | AE125: =IF(AD125<=0,0,IF(A125=1,Inputs!$B$62,AJ124)) -> 0 | AF125: =AE125*Inputs!$B$9 -> 0 | AG125: =(AE125-AF125)*Inputs!$C$62/12 -> 0 | AH125: =IF(AD125<=0,0,IF(AD125=1,AE125-AF125,MIN((AE125-AF125)*(Inputs!$C$62/12)/(1-(1+Inputs!$C$62/12)^(-AD125))-AG125,AE125-AF125))) -> 0 | AI125: =(AE125-AF125-AH125)*Inputs!$B$10 -> 0 | AJ125: =AE125-AF125-AH125-AI125 -> 0 | AK125: =Inputs!$D$63-(A125-1) -> -59 | AL125: =IF(AK125<=0,0,IF(A125=1,Inputs!$B$63,AQ124)) -> 0 | AM125: =AL125*Inputs!$B$9 -> 0 | AN125: =(AL125-AM125)*Inputs!$C$63/12 -> 0 | AO125: =IF(AK125<=0,0,IF(AK125=1,AL125-AM125,MIN((AL125-AM125)*(Inputs!$C$63/12)/(1-(1+Inputs!$C$63/12)^(-AK125))-AN125,AL125-AM125))) -> 0 | AP125: =(AL125-AM125-AO125)*Inputs!$B$10 -> 0 | AQ125: =AL125-AM125-AO125-AP125 -> 0 | AR125: =Inputs!$D$64-(A125-1) -> -47 | AS125: =IF(AR125<=0,0,IF(A125=1,Inputs!$B$64,AX124)) -> 0 | AT125: =AS125*Inputs!$B$9 -> 0 | AU125: =(AS125-AT125)*Inputs!$C$64/12 -> 0 | AV125: =IF(AR125<=0,0,IF(AR125=1,AS125-AT125,MIN((AS125-AT125)*(Inputs!$C$64/12)/(1-(1+Inputs!$C$64/12)^(-AR125))-AU125,AS125-AT125))) -> 0 | AW125: =(AS125-AT125-AV125)*Inputs!$B$10 -> 0 | AX125: =AS125-AT125-AV125-AW125 -> 0 | AY125: =Inputs!$D$65-(A125-1) -> -47 | AZ125: =IF(AY125<=0,0,IF(A125=1,Inputs!$B$65,BE124)) -> 0 | BA125: =AZ125*Inputs!$B$9 -> 0 | BB125: =(AZ125-BA125)*Inputs!$C$65/12 -> 0 | BC125: =IF(AY125<=0,0,IF(AY125=1,AZ125-BA125,MIN((AZ125-BA125)*(Inputs!$C$65/12)/(1-(1+Inputs!$C$65/12)^(-AY125))-BB125,AZ125-BA125))) -> 0 | BD125: =(AZ125-BA125-BC125)*Inputs!$B$10 -> 0 | BE125: =AZ125-BA125-BC125-BD125 -> 0 | BF125: =Inputs!$D$66-(A125-1) -> -35 | BG125: =IF(BF125<=0,0,IF(A125=1,Inputs!$B$66,BL124)) -> 0 | BH125: =BG125*Inputs!$B$9 -> 0 | BI125: =(BG125-BH125)*Inputs!$C$66/12 -> 0 | BJ125: =IF(BF125<=0,0,IF(BF125=1,BG125-BH125,MIN((BG125-BH125)*(Inputs!$C$66/12)/(1-(1+Inputs!$C$66/12)^(-BF125))-BI125,BG125-BH125))) -> 0 | BK125: =(BG125-BH125-BJ125)*Inputs!$B$10 -> 0 | BL125: =BG125-BH125-BJ125-BK125 -> 0 | BM125: =Inputs!$D$67-(A125-1) -> -35 | BN125: =IF(BM125<=0,0,IF(A125=1,Inputs!$B$67,BS124)) -> 0 | BO125: =BN125*Inputs!$B$9 -> 0 | BP125: =(BN125-BO125)*Inputs!$C$67/12 -> 0 | BQ125: =IF(BM125<=0,0,IF(BM125=1,BN125-BO125,MIN((BN125-BO125)*(Inputs!$C$67/12)/(1-(1+Inputs!$C$67/12)^(-BM125))-BP125,BN125-BO125))) -> 0 | BR125: =(BN125-BO125-BQ125)*Inputs!$B$10 -> 0 | BS125: =BN125-BO125-BQ125-BR125 -> 0 | BT125: =C125+J125+Q125+X125+AE125+AL125+AS125+AZ125+BG125+BN125 -> 0 | BU125: =D125+K125+R125+Y125+AF125+AM125+AT125+BA125+BH125+BO125 -> 0 | BV125: =E125+L125+S125+Z125+AG125+AN125+AU125+BB125+BI125+BP125 -> 0 | BW125: =F125+M125+T125+AA125+AH125+AO125+AV125+BC125+BJ125+BQ125 -> 0 | BX125: =G125+N125+U125+AB125+AI125+AP125+AW125+BD125+BK125+BR125 -> 0 | BY125: =H125+O125+V125+AC125+AJ125+AQ125+AX125+BE125+BL125+BS125 -> 0 | BZ125: =IF(A125>Inputs!$B$7,(1-Inputs!$B$6)*INDEX($BU$6:$BU$125,A125-Inputs!$B$7),0) -> 0 | CA125: =CA124+(1-Inputs!$B$6)*BU125-BZ125 -> -1.0697931e-10 | CB125: =BY125+CA125 -> -1.0697931e-10 | CC125: =BV125+BW125+BX125+BZ125 -> 0 | CD125: =CD124+BU125-BZ125 -> 10913893

Sheet Waterfall
A4: Period | B4: fwd | C4: beg_A | D4: beg_B | E4: beg_C | F4: cpn_A | G4: cpn_B | H4: cpn_C | I4: fees_accr | J4: accr_A | K4: accr_B | L4: accr_C | M4: swap | N4: fees_due | O4: due_A | P4: due_B | Q4: due_C | R4: ic | S4: pc | T4: seq | U4: sq_A | V4: sq_B | W4: sq_C | X4: lv1_A | Y4: lv1_B | Z4: lv1_C | AA4: pr1_A | AB4: pr1_B | AC4: pr1_C | AD4: lv2_A | AE4: lv2_B | AF4: lv2_C | AG4: pr2_A | AH4: pr2_B | AI4: pr2_C | AJ4: lv3_A | AK4: lv3_B | AL4: lv3_C | AM4: pr3_A | AN4: pr3_B | AO4: pr3_C | AP4: reg_A | AQ4: reg_B | AR4: reg_C | AS4: resid_prin_raw | AT4: pf_A | AU4: pf_B | AV4: pf_C | AW4: cv | AX4: oc_A | AY4: icr_A | AZ4: br_A | BA4: oc_B | BB4: icr_B | BC4: br_B | BD4: oc_C | BE4: icr_C | BF4: br_C | BG4: any_breach | BH4: fee1 | BI4: av1 | BJ4: intA1 | BK4: av2 | BL4: t1_A | BM4: t1_B | BN4: t1_C | BO4: av3 | BP4: intB1 | BQ4: av4 | BR4: t2_A | BS4: t2_B | BT4: t2_C | BU4: av5 | BV4: intC1 | BW4: av6 | BX4: t3_A | BY4: t3_B | BZ4: t3_C | CA4: av7 | CB4: defic0 | CC4: t4_A | CD4: t4_B | CE4: t4_C | CF4: av8 | CG4: topup | CH4: resid_int | CI4: res1 | CJ4: dr_fee | CK4: dr_A | CL4: dr_B | CM4: draw | CN4: res2 | CO4: fee2 | CP4: ipA2 | CQ4: ipB2 | CR4: ipC2 | CS4: aft_A | CT4: aft_B | CU4: aft_C | CV4: defic | CW4: wd_C | CX4: wd_B | CY4: wd_A | CZ4: bal_A | DA4: bal_B | DB4: bal_C | DC4: cf1 | DD4: ci1_A | DE4: ci1_B | DF4: ci1_C | DG4: retired | DH4: release | DI4: cash | DJ4: sw_fee | DK4: sw_A | DL4: sw_B | DM4: sw_C | DN4: swept | DO4: reserve_end | DP4: carry_fee | DQ4: carry_A | DR4: carry_B | DS4: carry_C | DT4: fees_paid | DU4: int_A | DV4: prin_A | DW4: int_B | DX4: prin_B | DY4: int_C | DZ4: prin_C | EA4: resid_prin | EB4: resid_cash | EC4: excess_spread | ED4: conservation_gap | EE4: bad_residual
T5: =1-Inputs!$B$16 -> 1 | BG5: 0 | CZ5: =Inputs!$B$21 -> 300000000 | DA5: =Inputs!$B$26 -> 40000000 | DB5: =Inputs!$B$31 -> 30000000 | DO5: =Inputs!$B$15 -> 3000000 | DP5: 0 | DQ5: 0 | DR5: 0 | DS5: 0
A6: =ROW()-5 -> 1 | B6: =Inputs!$B$11+(Inputs!$B$12-Inputs!$B$11)*(1-EXP(-A6/Inputs!$B$13))+Inputs!$B$8 -> 0.042571489 | C6: =CZ5 -> 300000000 | D6: =DA5 -> 40000000 | E6: =DB5 -> 30000000 | F6: =IF(Inputs!$B$22=1,B6+Inputs!$B$23,Inputs!$B$23)/12 -> 0.0044642908 | G6: =IF(Inputs!$B$27=1,B6+Inputs!$B$28,Inputs!$B$28)/12 -> 0.0054226241 | H6: =IF(Inputs!$B$32=1,B6+Inputs!$B$33,Inputs!$B$33)/12 -> 0.00625 | I6: =Pool!BT6*Inputs!$B$14/12 -> 210000 | J6: =C6*F6 -> 1339287.2 | K6: =D6*G6 -> 216904.96 | L6: =E6*H6 -> 187500 | M6: =Inputs!$B$17*(C6*Inputs!$B$22+D6*Inputs!$B$27+E6*Inputs!$B$32)*(B6-Inputs!$B$18)/12 -> 0 | N6: =DP5+I6+MAX(-M6,0) -> 210000 | O6: =DQ5+J6 -> 1339287.2 | P6: =DR5+K6 -> 216904.96 | Q6: =DS5+L6 -> 187500 | R6: =Pool!BV6+MAX(M6,0) -> 3043203.2 | S6: =Pool!BW6+Pool!BX6+Pool!BZ6 -> 8962647.6 | T6: =MAX(T5,BG5) -> 1 | U6: =MIN(C6,S6) -> 8962647.6 | V6: =MIN(D6,S6-U6) -> 0 | W6: =MIN(E6,S6-U6-V6) -> 0 | X6: =IF(C6-(0)>Inputs!$B$19,1,0) -> 1 | Y6: =IF(D6-(0)>Inputs!$B$19,1,0) -> 1 | Z6: =IF(E6-(0)>Inputs!$B$19,1,0) -> 1 | AA6: =IF((X6*C6+Y6*D6+Z6*E6)>0,MIN(C6-(0),S6*X6*C6/(X6*C6+Y6*D6+Z6*E6)),0) -> 7267011.6 | AB6: =IF((X6*C6+Y6*D6+Z6*E6)>0,MIN(D6-(0),S6*Y6*D6/(X6*C6+Y6*D6+Z6*E6)),0) -> 968934.88 | AC6: =IF((X6*C6+Y6*D6+Z6*E6)>0,MIN(E6-(0),S6*Z6*E6/(X6*C6+Y6*D6+Z6*E6)),0) -> 726701.16 | AD6: =IF(C6-(AA6)>Inputs!$B$19,1,0) -> 1 | AE6: =IF(D6-(AB6)>Inputs!$B$19,1,0) -> 1 | AF6: =IF(E6-(AC6)>Inputs!$B$19,1,0) -> 1 | AG6: =IF((AD6*C6+AE6*D6+AF6*E6)>0,MIN(C6-(AA6),(S6-(AA6+AB6+AC6))*AD6*C6/(AD6*C6+AE6*D6+AF6*E6)),0) -> 0 | AH6: =IF((AD6*C6+AE6*D6+AF6*E6)>0,MIN(D6-(AB6),(S6-(AA6+AB6+AC6))*AE6*D6/(AD6*C6+AE6*D6+AF6*E6)),0) -> 0 | AI6: =IF((AD6*C6+AE6*D6+AF6*E6)>0,MIN(E6-(AC6),(S6-(AA6+AB6+AC6))*AF6*E6/(AD6*C6+AE6*D6+AF6*E6)),0) -> 0 | AJ6: =IF(C6-(AA6+AG6)>Inputs!$B$19,1,0) -> 1 | AK6: =IF(D6-(AB6+AH6)>Inputs!$B$19,1,0) -> 1 | AL6: =IF(E6-(AC6+AI6)>Inputs!$B$19,1,0) -> 1 | AM6: =IF((AJ6*C6+AK6*D6+AL6*E6)>0,MIN(C6-(AA6+AG6),(S6-(AA6+AB6+AC6+AG6+AH6+AI6))*AJ6*C6/(AJ6*C6+AK6*D6+AL6*E6)),0) -> 0 | AN6: =IF((AJ6*C6+AK6*D6+AL6*E6)>0,MIN(D6-(AB6+AH6),(S6-(AA6+AB6+AC6+AG6+AH6+AI6))*AK6*D6/(AJ6*C6+AK6*D6+AL6*E6)),0) -> 0 | AO6: =IF((AJ6*C6+AK6*D6+AL6*E6)>0,MIN(E6-(AC6+AI6),(S6-(AA6+AB6+AC6+AG6+AH6+AI6))*AL6*E6/(AJ6*C6+AK6*D6+AL6*E6)),0) -> 0 | AP6: =IF(T6=1,U6,AA6+AG6+AM6) -> 8962647.6 | AQ6: =IF(T6=1,V6,AB6+AH6+AN6) -> 0 | AR6: =IF(T6=1,W6,AC6+AI6+AO6) -> 0 | AS6: =S6-AP6-AQ6-AR6 -> 0 | AT6: =C6-AP6 -> 2.9103735e+08 | AU6: =D6-AQ6 -> 40000000 | AV6: =E6-AR6 -> 30000000 | AW6: =Pool!CB6 -> 3.9063174e+08 | AX6: =IF((AT6)>Inputs!$B$19,AW6/(AT6),1000000000) -> 1.3422048 | AY6: =IF((J6)>0.000000001,(R6-I6-MAX(-M6,0))/(J6),1000000000) -> 2.115456 | AZ6: =IF(OR(AX6<Inputs!$B$24,AY6<Inputs!$B$25),1,0) -> 0 | BA6: =IF((AT6+AU6)>Inputs!$B$19,AW6/(AT6+AU6),1000000000) -> 1.1800232 | BB6: =IF((J6+K6)>0.000000001,(R6-I6-MAX(-M6,0))/(J6+K6),1000000000) -> 1.8205998 | BC6: =IF(OR(BA6<Inputs!$B$29,BB6<Inputs!$B$30),1,0) -> 0 | BD6: =IF((AT6+AU6+AV6)>Inputs!$B$19,AW6/(AT6+AU6+AV6),1000000000) -> 1.0819704 | BE6: =IF((J6+K6+L6)>0.000000001,(R6-I6-MAX(-M6,0))/(J6+K6+L6),1000000000) -> 1.6248299 | BF6: =IF(OR(BD6<Inputs!$B$34,BE6<Inputs!$B$35),1,0) -> 0 | BG6: =MAX(AZ6,BC6,BF6) -> 0 | BH6: =MIN(R6,N6) -> 210000 | BI6: =R6-BH6 -> 2833203.2 | BJ6: =MIN(BI6,O6) -> 1339287.2 | BK6: =BI6-BJ6 -> 1493916 | BL6: =AZ6*MIN(AT6,BK6) -> 0 | BM6: =AZ6*MIN(AU6,BK6-BL6) -> 0 | BN6: =AZ6*MIN(AV6,BK6-BL6-BM6) -> 0 | BO6: =BK6-BL6-BM6-BN6 -> 1493916 | BP6: =MIN(BO6,P6) -> 216904.96 | BQ6: =BO6-BP6 -> 1277011 | BR6: =BC6*MIN((AT6-BL6),BQ6) -> 0 | BS6: =BC6*MIN((AU6-BM6),BQ6-BR6) -> 0 | BT6: =BC6*MIN((AV6-BN6),BQ6-BR6-BS6) -> 0 | BU6: =BQ6-BR6-BS6-BT6 -> 1277011 | BV6: =MIN(BU6,Q6) -> 187500 | BW6: =BU6-BV6 -> 1089511 | BX6: =BF6*MIN((AT6-BL6-BR6),BW6) -> 0 | BY6: =BF6*MIN((AU6-BM6-BS6),BW6-BX6) -> 0 | BZ6: =BF6*MIN((AV6-BN6-BT6),BW6-BX6-BY6) -> 0 | CA6: =BW6-BX6-BY6-BZ6 -> 1089511 | CB6: =MAX(0,AT6+AU6+AV6-BL6-BM6-BN6-BR6-BS6-BT6-BX6-BY6-BZ6-AW6) -> 0 | CC6: =1*MIN((AT6-BL6-BR6-BX6),MIN(CA6,CB6)) -> 0 | CD6: =1*MIN((AU6-BM6-BS6-BY6),MIN(CA6,CB6)-CC6) -> 0 | CE6: =1*MIN((AV6-BN6-BT6-BZ6),MIN(CA6,CB6)-CC6-CD6) -> 0 | CF6: =CA6-CC6-CD6-CE6 -> 1089511 | CG6: =IF(C6+D6+E6>Inputs!$B$19,MIN(CF6,MAX(0,Inputs!$B$15-DO5)),0) -> 0 | CH6: =CF6-CG6 -> 1089511 | CI6: =DO5+CG6 -> 3000000 | CJ6: =MIN(MAX(N6-BH6,0),CI6) -> 0 | CK6: =MIN(MAX(O6-BJ6,0),CI6-CJ6) -> 0 | CL6: =MIN(MAX(P6-BP6,0),CI6-CJ6-CK6) -> 0 | CM6: =CJ6+CK6+CL6 -> 0 | CN6: =CI6-CM6 -> 3000000 | CO6: =BH6+CJ6 -> 210000 | CP6: =BJ6+CK6 -> 1339287.2 | CQ6: =BP6+CL6 -> 216904.96 | CR6: =BV6 -> 187500 | CS6: =AT6-BL6-BR6-BX6-CC6 -> 2.9103735e+08 | CT6: =AU6-BM6-BS6-BY6-CD6 -> 40000000 | CU6: =AV6-BN6-BT6-BZ6-CE6 -> 30000000 | CV6: =MAX(0,CS6+CT6+CU6-AW6) -> 0 | CW6: =MIN(CU6,CV6) -> 0 | CX6: =MIN(CT6,CV6-CW6) -> 0 | CY6: =MIN(CS6,CV6-CW6-CX6) -> 0 | CZ6: =IF(CS6-CY6<Inputs!$B$19,0,CS6-CY6) -> 2.9103735e+08 | DA6: =IF(CT6-CX6<Inputs!$B$19,0,CT6-CX6) -> 40000000 | DB6: =IF(CU6-CW6<Inputs!$B$19,0,CU6-CW6) -> 30000000 | DC6: =N6-CO6 -> 0 | DD6: =O6-CP6 -> 0 | DE6: =P6-CQ6 -> 0 | DF6: =Q6-CR6 -> 0 | DG6: =IF(CZ6+DA6+DB6<=Inputs!$B$19,1,0) -> 0 | DH6: =DG6*CN6 -> 0 | DI6: =DG6*(AS6+DH6) -> 0 | DJ6: =DG6*MIN(DC6,DI6) -> 0 | DK6: =DG6*MIN(DD6,DI6-DJ6) -> 0 | DL6: =DG6*MIN(DE6,DI6-DJ6-DK6) -> 0 | DM6: =DG6*MIN(DF6,DI6-DJ6-DK6-DL6) -> 0 | DN6: =DJ6+DK6+DL6+DM6 -> 0 | DO6: =CN6-DH6 -> 3000000 | DP6: =DC6-DJ6 -> 0 | DQ6: =DD6-DK6 -> 0 | DR6: =DE6-DL6 -> 0 | DS6: =DF6-DM6 -> 0 | DT6: =CO6+DJ6 -> 210000 | DU6: =CP6+DK6 -> 1339287.2 | DV6: =AP6+BL6+BR6+BX6+CC6 -> 8962647.6 | DW6: =CQ6+DL6 -> 216904.96 | DX6: =AQ6+BM6+BS6+BY6+CD6 -> 0 | DY6: =CR6+DM6 -> 187500 | DZ6: =AR6+BN6+BT6+BZ6+CE6 -> 0 | EA6: =DI6-DN6 -> 0 | EB6: =CH6+EA6 -> 1089511 | EC6: =R6-I6-MAX(-M6,0)-J6-K6-L6 -> 1089511 | ED6: =R6+S6+CM6+DH6-CG6-DT6-DU6-DW6-DY6-DV6-DX6-DZ6-EB6 -> 0 | EE6: =IF(AND(EB6>0.000001,DP6+DQ6+DR6+DS6>0.000001),1,0) -> 0
A7: =ROW()-5 -> 2 | B7: =Inputs!$B$11+(Inputs!$B$12-Inputs!$B$11)*(1-EXP(-A7/Inputs!$B$13))+Inputs!$B$8 -> 0.042160466 | C7: =CZ6 -> 2.9103735e+08 | D7: =DA6 -> 40000000 | E7: =DB6 -> 30000000 | F7: =IF(Inputs!$B$22=1,B7+Inputs!$B$23,Inputs!$B$23)/12 -> 0.0044300389 | G7: =IF(Inputs!$B$27=1,B7+Inputs!$B$28,Inputs!$B$28)/12 -> 0.0053883722 | H7: =IF(Inputs!$B$32=1,B7+Inputs!$B$33,Inputs!$B$33)/12 -> 0.00625 | I7: =Pool!BT7*Inputs!$B$14/12 -> 204762.25 | J7: =C7*F7 -> 1289306.8 | K7: =D7*G7 -> 215534.89 | L7: =E7*H7 -> 187500 | M7: =Inputs!$B$17*(C7*Inputs!$B$22+D7*Inputs!$B$27+E7*Inputs!$B$32)*(B7-Inputs!$B$18)/12 -> 0 | N7: =DP6+I7+MAX(-M7,0) -> 204762.25 | O7: =DQ6+J7 -> 1289306.8 | P7: =DR6+K7 -> 215534.89 | Q7: =DS6+L7 -> 187500 | R7: =Pool!BV7+MAX(M7,0) -> 2969217 | S7: =Pool!BW7+Pool!BX7+Pool!BZ7 -> 8853428.8 | T7: =MAX(T6,BG6) -> 1 | U7: =MIN(C7,S7) -> 8853428.8 | V7: =MIN(D7,S7-U7) -> 0 | W7: =MIN(E7,S7-U7-V7) -> 0 | X7: =IF(C7-(0)>Inputs!$B$19,1,0) -> 1 | Y7: =IF(D7-(0)>Inputs!$B$19,1,0) -> 1 | Z7: =IF(E7-(0)>Inputs!$B$19,1,0) -> 1 | AA7: =IF((X7*C7+Y7*D7+Z7*E7)>0,MIN(C7-(0),S7*X7*C7/(X7*C7+Y7*D7+Z7*E7)),0) -> 7136875 | AB7: =IF((X7*C7+Y7*D7+Z7*E7)>0,MIN(D7-(0),S7*Y7*D7/(X7*C7+Y7*D7+Z7*E7)),0) -> 980887.84 | AC7: =IF((X7*C7+Y7*D7+Z7*E7)>0,MIN(E7-(0),S7*Z7*E7/(X7*C7+Y7*D7+Z7*E7)),0) -> 735665.88 | AD7: =IF(C7-(AA7)>Inputs!$B$19,1,0) -> 1 | AE7: =IF(D7-(AB7)>Inputs!$B$19,1,0) -> 1 | AF7: =IF(E7-(AC7)>Inputs!$B$19,1,0) -> 1 | AG7: =IF((AD7*C7+AE7*D7+AF7*E7)>0,MIN(C7-(AA7),(S7-(AA7+AB7+AC7))*AD7*C7/(AD7*C7+AE7*D7+AF7*E7)),0) -> 0 | AH7: =IF((AD7*C7+AE7*D7+AF7*E7)>0,MIN(D7-(AB7),(S7-(AA7+AB7+AC7))*AE7*D7/(AD7*C7+AE7*D7+AF7*E7)),0) -> 0 | AI7: =IF((AD7*C7+AE7*D7+AF7*E7)>0,MIN(E7-(AC7),(S7-(AA7+AB7+AC7))*AF7*E7/(AD7*C7+AE7*D7+AF7*E7)),0) -> 0 | AJ7: =IF(C7-(AA7+AG7)>Inputs!$B$19,1,0) -> 1 | AK7: =IF(D7-(AB7+AH7)>Inputs!$B$19,1,0) -> 1 | AL7: =IF(E7-(AC7+AI7)>Inputs!$B$19,1,0) -> 1 | AM7: =IF((AJ7*C7+AK7*D7+AL7*E7)>0,MIN(C7-(AA7+AG7),(S7-(AA7+AB7+AC7+AG7+AH7+AI7))*AJ7*C7/(AJ7*C7+AK7*D7+AL7*E7)),0) -> 0 | AN7: =IF((AJ7*C7+AK7*D7+AL7*E7)>0,MIN(D7-(AB7+AH7),(S7-(AA7+AB7+AC7+AG7+AH7+AI7))*AK7*D7/(AJ7*C7+AK7*D7+AL7*E7)),0) -> 0 | AO7: =IF((AJ7*C7+AK7*D7+AL7*E7)>0,MIN(E7-(AC7+AI7),(S7-(AA7+AB7+AC7+AG7+AH7+AI7))*AL7*E7/(AJ7*C7+AK7*D7+AL7*E7)),0) -> 0 | AP7: =IF(T7=1,U7,AA7+AG7+AM7) -> 8853428.8 | AQ7: =IF(T7=1,V7,AB7+AH7+AN7) -> 0 | AR7: =IF(T7=1,W7,AC7+AI7+AO7) -> 0 | AS7: =S7-AP7-AQ7-AR7 -> 0 | AT7: =C7-AP7 -> 2.8218392e+08 | AU7: =D7-AQ7 -> 40000000 | AV7: =E7-AR7 -> 30000000 | AW7: =Pool!CB7 -> 3.8138282e+08 | AX7: =IF((AT7)>Inputs!$B$19,AW7/(AT7),1000000000) -> 1.3515399 | AY7: =IF((J7)>0.000000001,(R7-I7-MAX(-M7,0))/(J7),1000000000) -> 2.1441404 | AZ7: =IF(OR(AX7<Inputs!$B$24,AY7<Inputs!$B$25),1,0) -> 0 | BA7: =IF((AT7+AU7)>Inputs!$B$19,AW7/(AT7+AU7),1000000000) -> 1.1837426 | BB7: =IF((J7+K7)>0.000000001,(R7-I7-MAX(-M7,0))/(J7+K7),1000000000) -> 1.8370403 | BC7: =IF(OR(BA7<Inputs!$B$29,BB7<Inputs!$B$30),1,0) -> 0 | BD7: =IF((AT7+AU7+AV7)>Inputs!$B$19,AW7/(AT7+AU7+AV7),1000000000) -> 1.0829081 | BE7: =IF((J7+K7+L7)>0.000000001,(R7-I7-MAX(-M7,0))/(J7+K7+L7),1000000000) -> 1.6335087 | BF7: =IF(OR(BD7<Inputs!$B$34,BE7<Inputs!$B$35),1,0) -> 0 | BG7: =MAX(AZ7,BC7,BF7) -> 0 | BH7: =MIN(R7,N7) -> 204762.25 | BI7: =R7-BH7 -> 2764454.8 | BJ7: =MIN(BI7,O7) -> 1289306.8 | BK7: =BI7-BJ7 -> 1475148 | BL7: =AZ7*MIN(AT7,BK7) -> 0 | BM7: =AZ7*MIN(AU7,BK7-BL7) -> 0 | BN7: =AZ7*MIN(AV7,BK7-BL7-BM7) -> 0 | BO7: =BK7-BL7-BM7-BN7 -> 1475148 | BP7: =MIN(BO7,P7) -> 215534.89 | BQ7: =BO7-BP7 -> 1259613.1 | BR7: =BC7*MIN((AT7-BL7),BQ7) -> 0 | BS7: =BC7*MIN((AU7-BM7),BQ7-BR7) -> 0 | BT7: =BC7*MIN((AV7-BN7),BQ7-BR7-BS7) -> 0 | BU7: =BQ7-BR7-BS7-BT7 -> 1259613.1 | BV7: =MIN(BU7,Q7) -> 187500 | BW7: =BU7-BV7 -> 1072113.1 | BX7: =BF7*MIN((AT7-BL7-BR7),BW7) -> 0 | BY7: =BF7*MIN((AU7-BM7-BS7),BW7-BX7) -> 0 | BZ7: =BF7*MIN((AV7-BN7-BT7),BW7-BX7-BY7) -> 0 | CA7: =BW7-BX7-BY7-BZ7 -> 1072113.1 | CB7: =MAX(0,AT7+AU7+AV7-BL7-BM7-BN7-BR7-BS7-BT7-BX7-BY7-BZ7-AW7) -> 0 | CC7: =1*MIN((AT7-BL7-BR7-BX7),MIN(CA7,CB7)) -> 0 | CD7: =1*MIN((AU7-BM7-BS7-BY7),MIN(CA7,CB7)-CC7) -> 0 | CE7: =1*MIN((AV7-BN7-BT7-BZ7),MIN(CA7,CB7)-CC7-CD7) -> 0 | CF7: =CA7-CC7-CD7-CE7 -> 1072113.1 | CG7: =IF(C7+D7+E7>Inputs!$B$19,MIN(CF7,MAX(0,Inputs!$B$15-DO6)),0) -> 0 | CH7: =CF7-CG7 -> 1072113.1 | CI7: =DO6+CG7 -> 3000000 | CJ7: =MIN(MAX(N7-BH7,0),CI7) -> 0 | CK7: =MIN(MAX(O7-BJ7,0),CI7-CJ7) -> 0 | CL7: =MIN(MAX(P7-BP7,0),CI7-CJ7-CK7) -> 0 | CM7: =CJ7+CK7+CL7 -> 0 | CN7: =CI7-CM7 -> 3000000 | CO7: =BH7+CJ7 -> 204762.25 | CP7: =BJ7+CK7 -> 1289306.8 | CQ7: =BP7+CL7 -> 215534.89 | CR7: =BV7 -> 187500 | CS7: =AT7-BL7-BR7-BX7-CC7 -> 2.8218392e+08 | CT7: =AU7-BM7-BS7-BY7-CD7 -> 40000000 | CU7: =AV7-BN7-BT7-BZ7-CE7 -> 30000000 | CV7: =MAX(0,CS7+CT7+CU7-AW7) -> 0 | CW7: =MIN(CU7,CV7) -> 0 | CX7: =MIN(CT7,CV7-CW7) -> 0 | CY7: =MIN(CS7,CV7-CW7-CX7) -> 0 | CZ7: =IF(CS7-CY7<Inputs!$B$19,0,CS7-CY7) -> 2.8218392e+08 | DA7: =IF(CT7-CX7<Inputs!$B$19,0,CT7-CX7) -> 40000000 | DB7: =IF(CU7-CW7<Inputs!$B$19,0,CU7-CW7) -> 30000000 | DC7: =N7-CO7 -> 0 | DD7: =O7-CP7 -> 0 | DE7: =P7-CQ7 -> 0 | DF7: =Q7-CR7 -> 0 | DG7: =IF(CZ7+DA7+DB7<=Inputs!$B$19,1,0) -> 0 | DH7: =DG7*CN7 -> 0 | DI7: =DG7*(AS7+DH7) -> 0 | DJ7: =DG7*MIN(DC7,DI7) -> 0 | DK7: =DG7*MIN(DD7,DI7-DJ7) -> 0 | DL7: =DG7*MIN(DE7,DI7-DJ7-DK7) -> 0 | DM7: =DG7*MIN(DF7,DI7-DJ7-DK7-DL7) -> 0 | DN7: =DJ7+DK7+DL7+DM7 -> 0 | DO7: =CN7-DH7 -> 3000000 | DP7: =DC7-DJ7 -> 0 | DQ7: =DD7-DK7 -> 0 | DR7: =DE7-DL7 -> 0 | DS7: =DF7-DM7 -> 0 | DT7: =CO7+DJ7 -> 204762.25 | DU7: =CP7+DK7 -> 1289306.8 | DV7: =AP7+BL7+BR7+BX7+CC7 -> 8853428.8 | DW7: =CQ7+DL7 -> 215534.89 | DX7: =AQ7+BM7+BS7+BY7+CD7 -> 0 | DY7: =CR7+DM7 -> 187500 | DZ7: =AR7+BN7+BT7+BZ7+CE7 -> 0 | EA7: =DI7-DN7 -> 0 | EB7: =CH7+EA7 -> 1072113.1 | EC7: =R7-I7-MAX(-M7,0)-J7-K7-L7 -> 1072113.1 | ED7: =R7+S7+CM7+DH7-CG7-DT7-DU7-DW7-DY7-DV7-DX7-DZ7-EB7 -> 0 | EE7: =IF(AND(EB7>0.000001,DP7+DQ7+DR7+DS7>0.000001),1,0) -> 0
A8: =ROW()-5 -> 3 | B8: =Inputs!$B$11+(Inputs!$B$12-Inputs!$B$11)*(1-EXP(-A8/Inputs!$B$13))+Inputs!$B$8 -> 0.041766217 | C8: =CZ7 -> 2.8218392e+08 | D8: =DA7 -> 40000000 | E8: =DB7 -> 30000000 | F8: =IF(Inputs!$B$22=1,B8+Inputs!$B$23,Inputs!$B$23)/12 -> 0.0043971848 | G8: =IF(Inputs!$B$27=1,B8+Inputs!$B$28,Inputs!$B$28)/12 -> 0.0053555181 | H8: =IF(Inputs!$B$32=1,B8+Inputs!$B$33,Inputs!$B$33)/12 -> 0.00625 | I8: =Pool!BT8*Inputs!$B$14/12 -> 199595.12 | J8: =C8*F8 -> 1240814.9 | K8: =D8*G8 -> 214220.72 | L8: =E8*H8 -> 187500 | M8: =Inputs!$B$17*(C8*Inputs!$B$22+D8*Inputs!$B$27+E8*Inputs!$B$32)*(B8-Inputs!$B$18)/12 -> 0 | N8: =DP7+I8+MAX(-M8,0) -> 199595.12 | O8: =DQ7+J8 -> 1240814.9 | P8: =DR7+K8 -> 214220.72 | Q8: =DS7+L8 -> 187500 | R8: =Pool!BV8+MAX(M8,0) -> 2896219.6 | S8: =Pool!BW8+Pool!BX8+Pool!BZ8 -> 8745478.3 | T8: =MAX(T7,BG7) -> 1 | U8: =MIN(C8,S8) -> 8745478.3 | V8: =MIN(D8,S8-U8) -> 0 | W8: =MIN(E8,S8-U8-V8) -> 0 | X8: =IF(C8-(0)>Inputs!$B$19,1,0) -> 1 | Y8: =IF(D8-(0)>Inputs!$B$19,1,0) -> 1 | Z8: =IF(E8-(0)>Inputs!$B$19,1,0) -> 1 | AA8: =IF((X8*C8+Y8*D8+Z8*E8)>0,MIN(C8-(0),S8*X8*C8/(X8*C8+Y8*D8+Z8*E8)),0) -> 7007228.9 | AB8: =IF((X8*C8+Y8*D8+Z8*E8)>0,MIN(D8-(0),S8*Y8*D8/(X8*C8+Y8*D8+Z8*E8)),0) -> 993285.35 | AC8: =IF((X8*C8+Y8*D8+Z8*E8)>0,MIN(E8-(0),S8*Z8*E8/(X8*C8+Y8*D8+Z8*E8)),0) -> 744964.01 | AD8: =IF(C8-(AA8)>Inputs!$B$19,1,0) -> 1 | AE8: =IF(D8-(AB8)>Inputs!$B$19,1,0) -> 1 | AF8: =IF(E8-(AC8)>Inputs!$B$19,1,0) -> 1 | AG8: =IF((AD8*C8+AE8*D8+AF8*E8)>0,MIN(C8-(AA8),(S8-(AA8+AB8+AC8))*AD8*C8/(AD8*C8+AE8*D8+AF8*E8)),0) -> 0 | AH8: =IF((AD8*C8+AE8*D8+AF8*E8)>0,MIN(D8-(AB8),(S8-(AA8+AB8+AC8))*AE8*D8/(AD8*C8+AE8*D8+AF8*E8)),0) -> 0 | AI8: =IF((AD8*C8+AE8*D8+AF8*E8)>0,MIN(E8-(AC8),(S8-(AA8+AB8+AC8))*AF8*E8/(AD8*C8+AE8*D8+AF8*E8)),0) -> 0 | AJ8: =IF(C8-(AA8+AG8)>Inputs!$B$19,1,0) -> 1 | AK8: =IF(D8-(AB8+AH8)>Inputs!$B$19,1,0) -> 1 | AL8: =IF(E8-(AC8+AI8)>Inputs!$B$19,1,0) -> 1 | AM8: =IF((AJ8*C8+AK8*D8+AL8*E8)>0,MIN(C8-(AA8+AG8),(S8-(AA8+AB8+AC8+AG8+AH8+AI8))*AJ8*C8/(AJ8*C8+AK8*D8+AL8*E8)),0) -> 0 | AN8: =IF((AJ8*C8+AK8*D8+AL8*E8)>0,MIN(D8-(AB8+AH8),(S8-(AA8+AB8+AC8+AG8+AH8+AI8))*AK8*D8/(AJ8*C8+AK8*D8+AL8*E8)),0) -> 0 | AO8: =IF((AJ8*C8+AK8*D8+AL8*E8)>0,MIN(E8-(AC8+AI8),(S8-(AA8+AB8+AC8+AG8+AH8+AI8))*AL8*E8/(AJ8*C8+AK8*D8+AL8*E8)),0) -> 0 | AP8: =IF(T8=1,U8,AA8+AG8+AM8) -> 8745478.3 | AQ8: =IF(T8=1,V8,AB8+AH8+AN8) -> 0 | AR8: =IF(T8=1,W8,AC8+AI8+AO8) -> 0 | AS8: =S8-AP8-AQ8-AR8 -> 0 | AT8: =C8-AP8 -> 2.7343845e+08 | AU8: =D8-AQ8 -> 40000000 | AV8: =E8-AR8 -> 30000000 | AW8: =Pool!CB8 -> 3.7225184e+08 | AX8: =IF((AT8)>Inputs!$B$19,AW8/(AT8),1000000000) -> 1.3613734 | AY8: =IF((J8)>0.000000001,(R8-I8-MAX(-M8,0))/(J8),1000000000) -> 2.173269 | AZ8: =IF(OR(AX8<Inputs!$B$24,AY8<Inputs!$B$25),1,0) -> 0 | BA8: =IF((AT8+AU8)>Inputs!$B$19,AW8/(AT8+AU8),1000000000) -> 1.1876394 | BB8: =IF((J8+K8)>0.000000001,(R8-I8-MAX(-M8,0))/(J8+K8),1000000000) -> 1.8533048 | BC8: =IF(OR(BA8<Inputs!$B$29,BB8<Inputs!$B$30),1,0) -> 0 | BD8: =IF((AT8+AU8+AV8)>Inputs!$B$19,AW8/(AT8+AU8+AV8),1000000000) -> 1.0838968 | BE8: =IF((J8+K8+L8)>0.000000001,(R8-I8-MAX(-M8,0))/(J8+K8+L8),1000000000) -> 1.6417449 | BF8: =IF(OR(BD8<Inputs!$B$34,BE8<Inputs!$B$35),1,0) -> 0 | BG8: =MAX(AZ8,BC8,BF8) -> 0 | BH8: =MIN(R8,N8) -> 199595.12 | BI8: =R8-BH8 -> 2696624.4 | BJ8: =MIN(BI8,O8) -> 1240814.9 | BK8: =BI8-BJ8 -> 1455809.6 | BL8: =AZ8*MIN(AT8,BK8) -> 0 | BM8: =AZ8*MIN(AU8,BK8-BL8) -> 0 | BN8: =AZ8*MIN(AV8,BK8-BL8-BM8) -> 0 | BO8: =BK8-BL8-BM8-BN8 -> 1455809.6 | BP8: =MIN(BO8,P8) -> 214220.72 | BQ8: =BO8-BP8 -> 1241588.9 | BR8: =BC8*MIN((AT8-BL8),BQ8) -> 0 | BS8: =BC8*MIN((AU8-BM8),BQ8-BR8) -> 0 | BT8: =BC8*MIN((AV8-BN8),BQ8-BR8-BS8) -> 0 | BU8: =BQ8-BR8-BS8-BT8 -> 1241588.9 | BV8: =MIN(BU8,Q8) -> 187500 | BW8: =BU8-BV8 -> 1054088.9 | BX8: =BF8*MIN((AT8-BL8-BR8),BW8) -> 0 | BY8: =BF8*MIN((AU8-BM8-BS8),BW8-BX8) -> 0 | BZ8: =BF8*MIN((AV8-BN8-BT8),BW8-BX8-BY8) -> 0 | CA8: =BW8-BX8-BY8-BZ8 -> 1054088.9 | CB8: =MAX(0,AT8+AU8+AV8-BL8-BM8-BN8-BR8-BS8-BT8-BX8-BY8-BZ8-AW8) -> 0 | CC8: =1*MIN((AT8-BL8-BR8-BX8),MIN(CA8,CB8)) -> 0 | CD8: =1*MIN((AU8-BM8-BS8-BY8),MIN(CA8,CB8)-CC8) -> 0 | CE8: =1*MIN((AV8-BN8-BT8-BZ8),MIN(CA8,CB8)-CC8-CD8) -> 0 | CF8: =CA8-CC8-CD8-CE8 -> 1054088.9 | CG8: =IF(C8+D8+E8>Inputs!$B$19,MIN(CF8,MAX(0,Inputs!$B$15-DO7)),0) -> 0 | CH8: =CF8-CG8 -> 1054088.9 | CI8: =DO7+CG8 -> 3000000 | CJ8: =MIN(MAX(N8-BH8,0),CI8) -> 0 | CK8: =MIN(MAX(O8-BJ8,0),CI8-CJ8) -> 0 | CL8: =MIN(MAX(P8-BP8,0),CI8-CJ8-CK8) -> 0 | CM8: =CJ8+CK8+CL8 -> 0 | CN8: =CI8-CM8 -> 3000000 | CO8: =BH8+CJ8 -> 199595.12 | CP8: =BJ8+CK8 -> 1240814.9 | CQ8: =BP8+CL8 -> 214220.72 | CR8: =BV8 -> 187500 | CS8: =AT8-BL8-BR8-BX8-CC8 -> 2.7343845e+08 | CT8: =AU8-BM8-BS8-BY8-CD8 -> 40000000 | CU8: =AV8-BN8-BT8-BZ8-CE8 -> 30000000 | CV8: =MAX(0,CS8+CT8+CU8-AW8) -> 0 | CW8: =MIN(CU8,CV8) -> 0 | CX8: =MIN(CT8,CV8-CW8) -> 0 | CY8: =MIN(CS8,CV8-CW8-CX8) -> 0 | CZ8: =IF(CS8-CY8<Inputs!$B$19,0,CS8-CY8) -> 2.7343845e+08 | DA8: =IF(CT8-CX8<Inputs!$B$19,0,CT8-CX8) -> 40000000 | DB8: =IF(CU8-CW8<Inputs!$B$19,0,CU8-CW8) -> 30000000 | DC8: =N8-CO8 -> 0 | DD8: =O8-CP8 -> 0 | DE8: =P8-CQ8 -> 0 | DF8: =Q8-CR8 -> 0 | DG8: =IF(CZ8+DA8+DB8<=Inputs!$B$19,1,0) -> 0 | DH8: =DG8*CN8 -> 0 | DI8: =DG8*(AS8+DH8) -> 0 | DJ8: =DG8*MIN(DC8,DI8) -> 0 | DK8: =DG8*MIN(DD8,DI8-DJ8) -> 0 | DL8: =DG8*MIN(DE8,DI8-DJ8-DK8) -> 0 | DM8: =DG8*MIN(DF8,DI8-DJ8-DK8-DL8) -> 0 | DN8: =DJ8+DK8+DL8+DM8 -> 0 | DO8: =CN8-DH8 -> 3000000 | DP8: =DC8-DJ8 -> 0 | DQ8: =DD8-DK8 -> 0 | DR8: =DE8-DL8 -> 0 | DS8: =DF8-DM8 -> 0 | DT8: =CO8+DJ8 -> 199595.12 | DU8: =CP8+DK8 -> 1240814.9 | DV8: =AP8+BL8+BR8+BX8+CC8 -> 8745478.3 | DW8: =CQ8+DL8 -> 214220.72 | DX8: =AQ8+BM8+BS8+BY8+CD8 -> 0 | DY8: =CR8+DM8 -> 187500 | DZ8: =AR8+BN8+BT8+BZ8+CE8 -> 0 | EA8: =DI8-DN8 -> 0 | EB8: =CH8+EA8 -> 1054088.9 | EC8: =R8-I8-MAX(-M8,0)-J8-K8-L8 -> 1054088.9 | ED8: =R8+S8+CM8+DH8-CG8-DT8-DU8-DW8-DY8-DV8-DX8-DZ8-EB8 -> 0 | EE8: =IF(AND(EB8>0.000001,DP8+DQ8+DR8+DS8>0.000001),1,0) -> 0
A9: =ROW()-5 -> 4 | B9: =Inputs!$B$11+(Inputs!$B$12-Inputs!$B$11)*(1-EXP(-A9/Inputs!$B$13))+Inputs!$B$8 -> 0.041388058 | C9: =CZ8 -> 2.7343845e+08 | D9: =DA8 -> 40000000 | E9: =DB8 -> 30000000 | F9: =IF(Inputs!$B$22=1,B9+Inputs!$B$23,Inputs!$B$23)/12 -> 0.0043656715 | G9: =IF(Inputs!$B$27=1,B9+Inputs!$B$28,Inputs!$B$28)/12 -> 0.0053240048 | H9: =IF(Inputs!$B$32=1,B9+Inputs!$B$33,Inputs!$B$33)/12 -> 0.00625 | I9: =Pool!BT9*Inputs!$B$14/12 -> 194497.76 | J9: =C9*F9 -> 1193742.4 | K9: =D9*G9 -> 212960.19 | L9: =E9*H9 -> 187500 | M9: =Inputs!$B$17*(C9*Inputs!$B$22+D9*Inputs!$B$27+E9*Inputs!$B$32)*(B9-Inputs!$B$18)/12 -> 0 | N9: =DP8+I9+MAX(-M9,0) -> 194497.76 | O9: =DQ8+J9 -> 1193742.4 | P9: =DR8+K9 -> 212960.19 | Q9: =DS8+L9 -> 187500 | R9: =Pool!BV9+MAX(M9,0) -> 2824199 | S9: =Pool!BW9+Pool!BX9+Pool!BZ9 -> 8638781.6 | T9: =MAX(T8,BG8) -> 1 | U9: =MIN(C9,S9) -> 8638781.6 | V9: =MIN(D9,S9-U9) -> 0 | W9: =MIN(E9,S9-U9-V9) -> 0 | X9: =IF(C9-(0)>Inputs!$B$19,1,0) -> 1 | Y9: =IF(D9-(0)>Inputs!$B$19,1,0) -> 1 | Z9: =IF(E9-(0)>Inputs!$B$19,1,0) -> 1 | AA9: =IF((X9*C9+Y9*D9+Z9*E9)>0,MIN(C9-(0),S9*X9*C9/(X9*C9+Y9*D9+Z9*E9)),0) -> 6878015.7 | AB9: =IF((X9*C9+Y9*D9+Z9*E9)>0,MIN(D9-(0),S9*Y9*D9/(X9*C9+Y9*D9+Z9*E9)),0) -> 1006152 | AC9: =IF((X9*C9+Y9*D9+Z9*E9)>0,MIN(E9-(0),S9*Z9*E9/(X9*C9+Y9*D9+Z9*E9)),0) -> 754613.97 | AD9: =IF(C9-(AA9)>Inputs!$B$19,1,0) -> 1 | AE9: =IF(D9-(AB9)>Inputs!$B$19,1,0) -> 1 | AF9: =IF(E9-(AC9)>Inputs!$B$19,1,0) -> 1 | AG9: =IF((AD9*C9+AE9*D9+AF9*E9)>0,MIN(C9-(AA9),(S9-(AA9+AB9+AC9))*AD9*C9/(AD9*C9+AE9*D9+AF9*E9)),0) -> 0 | AH9: =IF((AD9*C9+AE9*D9+AF9*E9)>0,MIN(D9-(AB9),(S9-(AA9+AB9+AC9))*AE9*D9/(AD9*C9+AE9*D9+AF9*E9)),0) -> 0 | AI9: =IF((AD9*C9+AE9*D9+AF9*E9)>0,MIN(E9-(AC9),(S9-(AA9+AB9+AC9))*AF9*E9/(AD9*C9+AE9*D9+AF9*E9)),0) -> 0 | AJ9: =IF(C9-(AA9+AG9)>Inputs!$B$19,1,0) -> 1 | AK9: =IF(D9-(AB9+AH9)>Inputs!$B$19,1,0) -> 1 | AL9: =IF(E9-(AC9+AI9)>Inputs!$B$19,1,0) -> 1 | AM9: =IF((AJ9*C9+AK9*D9+AL9*E9)>0,MIN(C9-(AA9+AG9),(S9-(AA9+AB9+AC9+AG9+AH9+AI9))*AJ9*C9/(AJ9*C9+AK9*D9+AL9*E9)),0) -> 0 | AN9: =IF((AJ9*C9+AK9*D9+AL9*E9)>0,MIN(D9-(AB9+AH9),(S9-(AA9+AB9+AC9+AG9+AH9+AI9))*AK9*D9/(AJ9*C9+AK9*D9+AL9*E9)),0) -> 0 | AO9: =IF((AJ9*C9+AK9*D9+AL9*E9)>0,MIN(E9-(AC9+AI9),(S9-(AA9+AB9+AC9+AG9+AH9+AI9))*AL9*E9/(AJ9*C9+AK9*D9+AL9*E9)),0) -> 0 | AP9: =IF(T9=1,U9,AA9+AG9+AM9) -> 8638781.6 | AQ9: =IF(T9=1,V9,AB9+AH9+AN9) -> 0 | AR9: =IF(T9=1,W9,AC9+AI9+AO9) -> 0 | AS9: =S9-AP9-AQ9-AR9 -> 0 | AT9: =C9-AP9 -> 2.6479966e+08 | AU9: =D9-AQ9 -> 40000000 | AV9: =E9-AR9 -> 30000000 | AW9: =Pool!CB9 -> 3.6323739e+08 | AX9: =IF((AT9)>Inputs!$B$19,AW9/(AT9),1000000000) -> 1.3717441 | AY9: =IF((J9)>0.000000001,(R9-I9-MAX(-M9,0))/(J9),1000000000) -> 2.2029051 | AZ9: =IF(OR(AX9<Inputs!$B$24,AY9<Inputs!$B$25),1,0) -> 0 | BA9: =IF((AT9+AU9)>Inputs!$B$19,AW9/(AT9+AU9),1000000000) -> 1.191725 | BB9: =IF((J9+K9)>0.000000001,(R9-I9-MAX(-M9,0))/(J9+K9),1000000000) -> 1.8694081 | BC9: =IF(OR(BA9<Inputs!$B$29,BB9<Inputs!$B$30),1,0) -> 0 | BD9: =IF((AT9+AU9+AV9)>Inputs!$B$19,AW9/(AT9+AU9+AV9),1000000000) -> 1.0849395 | BE9: =IF((J9+K9+L9)>0.000000001,(R9-I9-MAX(-M9,0))/(J9+K9+L9),1000000000) -> 1.6495402 | BF9: =IF(OR(BD9<Inputs!$B$34,BE9<Inputs!$B$35),1,0) -> 0 | BG9: =MAX(AZ9,BC9,BF9) -> 0 | BH9: =MIN(R9,N9) -> 194497.76 | BI9: =R9-BH9 -> 2629701.3 | BJ9: =MIN(BI9,O9) -> 1193742.4 | BK9: =BI9-BJ9 -> 1435958.8 | BL9: =AZ9*MIN(AT9,BK9) -> 0 | BM9: =AZ9*MIN(AU9,BK9-BL9) -> 0 | BN9: =AZ9*MIN(AV9,BK9-BL9-BM9) -> 0 | BO9: =BK9-BL9-BM9-BN9 -> 1435958.8 | BP9: =MIN(BO9,P9) -> 212960.19 | BQ9: =BO9-BP9 -> 1222998.6 | BR9: =BC9*MIN((AT9-BL9),BQ9) -> 0 | BS9: =BC9*MIN((AU9-BM9),BQ9-BR9) -> 0 | BT9: =BC9*MIN((AV9-BN9),BQ9-BR9-BS9) -> 0 | BU9: =BQ9-BR9-BS9-BT9 -> 1222998.6 | BV9: =MIN(BU9,Q9) -> 187500 | BW9: =BU9-BV9 -> 1035498.6 | BX9: =BF9*MIN((AT9-BL9-BR9),BW9) -> 0 | BY9: =BF9*MIN((AU9-BM9-BS9),BW9-BX9) -> 0 | BZ9: =BF9*MIN((AV9-BN9-BT9),BW9-BX9-BY9) -> 0 | CA9: =BW9-BX9-BY9-BZ9 -> 1035498.6 | CB9: =MAX(0,AT9+AU9+AV9-BL9-BM9-BN9-BR9-BS9-BT9-BX9-BY9-BZ9-AW9) -> 0 | CC9: =1*MIN((AT9-BL9-BR9-BX9),MIN(CA9,CB9)) -> 0 | CD9: =1*MIN((AU9-BM9-BS9-BY9),MIN(CA9,CB9)-CC9) -> 0 | CE9: =1*MIN((AV9-BN9-BT9-BZ9),MIN(CA9,CB9)-CC9-CD9) -> 0 | CF9: =CA9-CC9-CD9-CE9 -> 1035498.6 | CG9: =IF(C9+D9+E9>Inputs!$B$19,MIN(CF9,MAX(0,Inputs!$B$15-DO8)),0) -> 0 | CH9: =CF9-CG9 -> 1035498.6 | CI9: =DO8+CG9 -> 3000000 | CJ9: =MIN(MAX(N9-BH9,0),CI9) -> 0 | CK9: =MIN(MAX(O9-BJ9,0),CI9-CJ9) -> 0 | CL9: =MIN(MAX(P9-BP9,0),CI9-CJ9-CK9) -> 0 | CM9: =CJ9+CK9+CL9 -> 0 | CN9: =CI9-CM9 -> 3000000 | CO9: =BH9+CJ9 -> 194497.76 | CP9: =BJ9+CK9 -> 1193742.4 | CQ9: =BP9+CL9 -> 212960.19 | CR9: =BV9 -> 187500 | CS9: =AT9-BL9-BR9-BX9-CC9 -> 2.6479966e+08 | CT9: =AU9-BM9-BS9-BY9-CD9 -> 40000000 | CU9: =AV9-BN9-BT9-BZ9-CE9 -> 30000000 | CV9: =MAX(0,CS9+CT9+CU9-AW9) -> 0 | CW9: =MIN(CU9,CV9) -> 0 | CX9: =MIN(CT9,CV9-CW9) -> 0 | CY9: =MIN(CS9,CV9-CW9-CX9) -> 0 | CZ9: =IF(CS9-CY9<Inputs!$B$19,0,CS9-CY9) -> 2.6479966e+08 | DA9: =IF(CT9-CX9<Inputs!$B$19,0,CT9-CX9) -> 40000000 | DB9: =IF(CU9-CW9<Inputs!$B$19,0,CU9-CW9) -> 30000000 | DC9: =N9-CO9 -> 0 | DD9: =O9-CP9 -> 0 | DE9: =P9-CQ9 -> 0 | DF9: =Q9-CR9 -> 0 | DG9: =IF(CZ9+DA9+DB9<=Inputs!$B$19,1,0) -> 0 | DH9: =DG9*CN9 -> 0 | DI9: =DG9*(AS9+DH9) -> 0 | DJ9: =DG9*MIN(DC9,DI9) -> 0 | DK9: =DG9*MIN(DD9,DI9-DJ9) -> 0 | DL9: =DG9*MIN(DE9,DI9-DJ9-DK9) -> 0 | DM9: =DG9*MIN(DF9,DI9-DJ9-DK9-DL9) -> 0 | DN9: =DJ9+DK9+DL9+DM9 -> 0 | DO9: =CN9-DH9 -> 3000000 | DP9: =DC9-DJ9 -> 0 | DQ9: =DD9-DK9 -> 0 | DR9: =DE9-DL9 -> 0 | DS9: =DF9-DM9 -> 0 | DT9: =CO9+DJ9 -> 194497.76 | DU9: =CP9+DK9 -> 1193742.4 | DV9: =AP9+BL9+BR9+BX9+CC9 -> 8638781.6 | DW9: =CQ9+DL9 -> 212960.19 | DX9: =AQ9+BM9+BS9+BY9+CD9 -> 0 | DY9: =CR9+DM9 -> 187500 | DZ9: =AR9+BN9+BT9+BZ9+CE9 -> 0 | EA9: =DI9-DN9 -> 0 | EB9: =CH9+EA9 -> 1035498.6 | EC9: =R9-I9-MAX(-M9,0)-J9-K9-L9 -> 1035498.6 | ED9: =R9+S9+CM9+DH9-CG9-DT9-DU9-DW9-DY9-DV9-DX9-DZ9-EB9 -> 0 | EE9: =IF(AND(EB9>0.000001,DP9+DQ9+DR9+DS9>0.000001),1,0) -> 0
A10: =ROW()-5 -> 5 | B10: =Inputs!$B$11+(Inputs!$B$12-Inputs!$B$11)*(1-EXP(-A10/Inputs!$B$13))+Inputs!$B$8 -> 0.041025332 | C10: =CZ9 -> 2.6479966e+08 | D10: =DA9 -> 40000000 | E10: =DB9 -> 30000000 | F10: =IF(Inputs!$B$22=1,B10+Inputs!$B$23,Inputs!$B$23)/12 -> 0.0043354443 | G10: =IF(Inputs!$B$27=1,B10+Inputs!$B$28,Inputs!$B$28)/12 -> 0.0052937776 | H10: =IF(Inputs!$B$32=1,B10+Inputs!$B$33,Inputs!$B$33)/12 -> 0.00625 | I10: =Pool!BT10*Inputs!$B$14/12 -> 189469.34 | J10: =C10*F10 -> 1148024.2 | K10: =D10*G10 -> 211751.11 | L10: =E10*H10 -> 187500 | M10: =Inputs!$B$17*(C10*Inputs!$B$22+D10*Inputs!$B$27+E10*Inputs!$B$32)*(B10-Inputs!$B$18)/12 -> 0 | N10: =DP9+I10+MAX(-M10,0) -> 189469.34 | O10: =DQ9+J10 -> 1148024.2 | P10: =DR9+K10 -> 211751.11 | Q10: =DS9+L10 -> 187500 | R10: =Pool!BV10+MAX(M10,0) -> 2753143.8 | S10: =Pool!BW10+Pool!BX10+Pool!BZ10 -> 8533324.6 | T10: =MAX(T9,BG9) -> 1 | U10: =MIN(C10,S10) -> 8533324.6 | V10: =MIN(D10,S10-U10) -> 0 | W10: =MIN(E10,S10-U10-V10) -> 0 | X10: =IF(C10-(0)>Inputs!$B$19,1,0) -> 1 | Y10: =IF(D10-(0)>Inputs!$B$19,1,0) -> 1 | Z10: =IF(E10-(0)>Inputs!$B$19,1,0) -> 1 | AA10: =IF((X10*C10+Y10*D10+Z10*E10)>0,MIN(C10-(0),S10*X10*C10/(X10*C10+Y10*D10+Z10*E10)),0) -> 6749174.9 | AB10: =IF((X10*C10+Y10*D10+Z10*E10)>0,MIN(D10-(0),S10*Y10*D10/(X10*C10+Y10*D10+Z10*E10)),0) -> 1019514.1 | AC10: =IF((X10*C10+Y10*D10+Z10*E10)>0,MIN(E10-(0),S10*Z10*E10/(X10*C10+Y10*D10+Z10*E10)),0) -> 764635.59 | AD10: =IF(C10-(AA10)>Inputs!$B$19,1,0) -> 1 | AE10: =IF(D10-(AB10)>Inputs!$B$19,1,0) -> 1 | AF10: =IF(E10-(AC10)>Inputs!$B$19,1,0) -> 1 | AG10: =IF((AD10*C10+AE10*D10+AF10*E10)>0,MIN(C10-(AA10),(S10-(AA10+AB10+AC10))*AD10*C10/(AD10*C10+AE10*D10+AF10*E10)),0) -> 0 | AH10: =IF((AD10*C10+AE10*D10+AF10*E10)>0,MIN(D10-(AB10),(S10-(AA10+AB10+AC10))*AE10*D10/(AD10*C10+AE10*D10+AF10*E10)),0) -> 0 | AI10: =IF((AD10*C10+AE10*D10+AF10*E10)>0,MIN(E10-(AC10),(S10-(AA10+AB10+AC10))*AF10*E10/(AD10*C10+AE10*D10+AF10*E10)),0) -> 0 | AJ10: =IF(C10-(AA10+AG10)>Inputs!$B$19,1,0) -> 1 | AK10: =IF(D10-(AB10+AH10)>Inputs!$B$19,1,0) -> 1 | AL10: =IF(E10-(AC10+AI10)>Inputs!$B$19,1,0) -> 1 | AM10: =IF((AJ10*C10+AK10*D10+AL10*E10)>0,MIN(C10-(AA10+AG10),(S10-(AA10+AB10+AC10+AG10+AH10+AI10))*AJ10*C10/(AJ10*C10+AK10*D10+AL10*E10)),0) -> 0 | AN10: =IF((AJ10*C10+AK10*D10+AL10*E10)>0,MIN(D10-(AB10+AH10),(S10-(AA10+AB10+AC10+AG10+AH10+AI10))*AK10*D10/(AJ10*C10+AK10*D10+AL10*E10)),0) -> 0 | AO10: =IF((AJ10*C10+AK10*D10+AL10*E10)>0,MIN(E10-(AC10+AI10),(S10-(AA10+AB10+AC10+AG10+AH10+AI10))*AL10*E10/(AJ10*C10+AK10*D10+AL10*E10)),0) -> 0 | AP10: =IF(T10=1,U10,AA10+AG10+AM10) -> 8533324.6 | AQ10: =IF(T10=1,V10,AB10+AH10+AN10) -> 0 | AR10: =IF(T10=1,W10,AC10+AI10+AO10) -> 0 | AS10: =S10-AP10-AQ10-AR10 -> 0 | AT10: =C10-AP10 -> 2.5626634e+08 | AU10: =D10-AQ10 -> 40000000 | AV10: =E10-AR10 -> 30000000 | AW10: =Pool!CB10 -> 3.5433811e+08 | AX10: =IF((AT10)>Inputs!$B$19,AW10/(AT10),1000000000) -> 1.3826947 | AY10: =IF((J10)>0.000000001,(R10-I10-MAX(-M10,0))/(J10),1000000000) -> 2.2331188 | AZ10: =IF(OR(AX10<Inputs!$B$24,AY10<Inputs!$B$25),1,0) -> 0 | BA10: =IF((AT10+AU10)>Inputs!$B$19,AW10/(AT10+AU10),1000000000) -> 1.196012 | BB10: =IF((J10+K10)>0.000000001,(R10-I10-MAX(-M10,0))/(J10+K10),1000000000) -> 1.8853662 | BC10: =IF(OR(BA10<Inputs!$B$29,BB10<Inputs!$B$30),1,0) -> 0 | BD10: =IF((AT10+AU10+AV10)>Inputs!$B$19,AW10/(AT10+AU10+AV10),1000000000) -> 1.0860394 | BE10: =IF((J10+K10+L10)>0.000000001,(R10-I10-MAX(-M10,0))/(J10+K10+L10),1000000000) -> 1.6568961 | BF10: =IF(OR(BD10<Inputs!$B$34,BE10<Inputs!$B$35),1,0) -> 0 | BG10: =MAX(AZ10,BC10,BF10) -> 0 | BH10: =MIN(R10,N10) -> 189469.34 | BI10: =R10-BH10 -> 2563674.4 | BJ10: =MIN(BI10,O10) -> 1148024.2 | BK10: =BI10-BJ10 -> 1415650.2 | BL10: =AZ10*MIN(AT10,BK10) -> 0 | BM10: =AZ10*MIN(AU10,BK10-BL10) -> 0 | BN10: =AZ10*MIN(AV10,BK10-BL10-BM10) -> 0 | BO10: =BK10-BL10-BM10-BN10 -> 1415650.2 | BP10: =MIN(BO10,P10) -> 211751.11 | BQ10: =BO10-BP10 -> 1203899.1 | BR10: =BC10*MIN((AT10-BL10),BQ10) -> 0 | BS10: =BC10*MIN((AU10-BM10),BQ10-BR10) -> 0 | BT10: =BC10*MIN((AV10-BN10),BQ10-BR10-BS10) -> 0 | BU10: =BQ10-BR10-BS10-BT10 -> 1203899.1 | BV10: =MIN(BU10,Q10) -> 187500 | BW10: =BU10-BV10 -> 1016399.1 | BX10: =BF10*MIN((AT10-BL10-BR10),BW10) -> 0 | BY10: =BF10*MIN((AU10-BM10-BS10),BW10-BX10) -> 0 | BZ10: =BF10*MIN((AV10-BN10-BT10),BW10-BX10-BY10) -> 0 | CA10: =BW10-BX10-BY10-BZ10 -> 1016399.1 | CB10: =MAX(0,AT10+AU10+AV10-BL10-BM10-BN10-BR10-BS10-BT10-BX10-BY10-BZ10-AW10) -> 0 | CC10: =1*MIN((AT10-BL10-BR10-BX10),MIN(CA10,CB10)) -> 0 | CD10: =1*MIN((AU10-BM10-BS10-BY10),MIN(CA10,CB10)-CC10) -> 0 | CE10: =1*MIN((AV10-BN10-BT10-BZ10),MIN(CA10,CB10)-CC10-CD10) -> 0 | CF10: =CA10-CC10-CD10-CE10 -> 1016399.1 | CG10: =IF(C10+D10+E10>Inputs!$B$19,MIN(CF10,MAX(0,Inputs!$B$15-DO9)),0) -> 0 | CH10: =CF10-CG10 -> 1016399.1 | CI10: =DO9+CG10 -> 3000000 | CJ10: =MIN(MAX(N10-BH10,0),CI10) -> 0 | CK10: =MIN(MAX(O10-BJ10,0),CI10-CJ10) -> 0 | CL10: =MIN(MAX(P10-BP10,0),CI10-CJ10-CK10) -> 0 | CM10: =CJ10+CK10+CL10 -> 0 | CN10: =CI10-CM10 -> 3000000 | CO10: =BH10+CJ10 -> 189469.34 | CP10: =BJ10+CK10 -> 1148024.2 | CQ10: =BP10+CL10 -> 211751.11 | CR10: =BV10 -> 187500 | CS10: =AT10-BL10-BR10-BX10-CC10 -> 2.5626634e+08 | CT10: =AU10-BM10-BS10-BY10-CD10 -> 40000000 | CU10: =AV10-BN10-BT10-BZ10-CE10 -> 30000000 | CV10: =MAX(0,CS10+CT10+CU10-AW10) -> 0 | CW10: =MIN(CU10,CV10) -> 0 | CX10: =MIN(CT10,CV10-CW10) -> 0 | CY10: =MIN(CS10,CV10-CW10-CX10) -> 0 | CZ10: =IF(CS10-CY10<Inputs!$B$19,0,CS10-CY10) -> 2.5626634e+08 | DA10: =IF(CT10-CX10<Inputs!$B$19,0,CT10-CX10) -> 40000000 | DB10: =IF(CU10-CW10<Inputs!$B$19,0,CU10-CW10) -> 30000000 | DC10: =N10-CO10 -> 0 | DD10: =O10-CP10 -> 0 | DE10: =P10-CQ10 -> 0 | DF10: =Q10-CR10 -> 0 | DG10: =IF(CZ10+DA10+DB10<=Inputs!$B$19,1,0) -> 0 | DH10: =DG10*CN10 -> 0 | DI10: =DG10*(AS10+DH10) -> 0 | DJ10: =DG10*MIN(DC10,DI10) -> 0 | DK10: =DG10*MIN(DD10,DI10-DJ10) -> 0 | DL10: =DG10*MIN(DE10,DI10-DJ10-DK10) -> 0 | DM10: =DG10*MIN(DF10,DI10-DJ10-DK10-DL10) -> 0 | DN10: =DJ10+DK10+DL10+DM10 -> 0 | DO10: =CN10-DH10 -> 3000000 | DP10: =DC10-DJ10 -> 0 | DQ10: =DD10-DK10 -> 0 | DR10: =DE10-DL10 -> 0 | DS10: =DF10-DM10 -> 0 | DT10: =CO10+DJ10 -> 189469.34 | DU10: =CP10+DK10 -> 1148024.2 | DV10: =AP10+BL10+BR10+BX10+CC10 -> 8533324.6 | DW10: =CQ10+DL10 -> 211751.11 | DX10: =AQ10+BM10+BS10+BY10+CD10 -> 0 | DY10: =CR10+DM10 -> 187500 | DZ10: =AR10+BN10+BT10+BZ10+CE10 -> 0 | EA10: =DI10-DN10 -> 0 | EB10: =CH10+EA10 -> 1016399.1 | EC10: =R10-I10-MAX(-M10,0)-J10-K10-L10 -> 1016399.1 | ED10: =R10+S10+CM10+DH10-CG10-DT10-DU10-DW10-DY10-DV10-DX10-DZ10-EB10 -> 0 | EE10: =IF(AND(EB10>0.000001,DP10+DQ10+DR10+DS10>0.000001),1,0) -> 0
A11: =ROW()-5 -> 6 | B11: =Inputs!$B$11+(Inputs!$B$12-Inputs!$B$11)*(1-EXP(-A11/Inputs!$B$13))+Inputs!$B$8 -> 0.040677408 | C11: =CZ10 -> 2.5626634e+08 | D11: =DA10 -> 40000000 | E11: =DB10 -> 30000000 | F11: =IF(Inputs!$B$22=1,B11+Inputs!$B$23,Inputs!$B$23)/12 -> 0.0043064507 | G11: =IF(Inputs!$B$27=1,B11+Inputs!$B$28,Inputs!$B$28)/12 -> 0.005264784 | H11: =IF(Inputs!$B$32=1,B11+Inputs!$B$33,Inputs!$B$33)/12 -> 0.00625 | I11: =Pool!BT11*Inputs!$B$14/12 -> 184509.03 | J11: =C11*F11 -> 1103598.4 | K11: =D11*G11 -> 210591.36 | L11: =E11*H11 -> 187500 | M11: =Inputs!$B$17*(C11*Inputs!$B$22+D11*Inputs!$B$27+E11*Inputs!$B$32)*(B11-Inputs!$B$18)/12 -> 0 | N11: =DP10+I11+MAX(-M11,0) -> 184509.03 | O11: =DQ10+J11 -> 1103598.4 | P11: =DR10+K11 -> 210591.36 | Q11: =DS10+L11 -> 187500 | R11: =Pool!BV11+MAX(M11,0) -> 2683042.3 | S11: =Pool!BW11+Pool!BX11+Pool!BZ11 -> 8429093 | T11: =MAX(T10,BG10) -> 1 | U11: =MIN(C11,S11) -> 8429093 | V11: =MIN(D11,S11-U11) -> 0 | W11: =MIN(E11,S11-U11-V11) -> 0 | X11: =IF(C11-(0)>Inputs!$B$19,1,0) -> 1 | Y11: =IF(D11-(0)>Inputs!$B$19,1,0) -> 1 | Z11: =IF(E11-(0)>Inputs!$B$19,1,0) -> 1 | AA11: =IF((X11*C11+Y11*D11+Z11*E11)>0,MIN(C11-(0),S11*X11*C11/(X11*C11+Y11*D11+Z11*E11)),0) -> 6620642.6 | AB11: =IF((X11*C11+Y11*D11+Z11*E11)>0,MIN(D11-(0),S11*Y11*D11/(X11*C11+Y11*D11+Z11*E11)),0) -> 1033400.3 | AC11: =IF((X11*C11+Y11*D11+Z11*E11)>0,MIN(E11-(0),S11*Z11*E11/(X11*C11+Y11*D11+Z11*E11)),0) -> 775050.2 | AD11: =IF(C11-(AA11)>Inputs!$B$19,1,0) -> 1 | AE11: =IF(D11-(AB11)>Inputs!$B$19,1,0) -> 1 | AF11: =IF(E11-(AC11)>Inputs!$B$19,1,0) -> 1 | AG11: =IF((AD11*C11+AE11*D11+AF11*E11)>0,MIN(C11-(AA11),(S11-(AA11+AB11+AC11))*AD11*C11/(AD11*C11+AE11*D11+AF11*E11)),0) -> 0 | AH11: =IF((AD11*C11+AE11*D11+AF11*E11)>0,MIN(D11-(AB11),(S11-(AA11+AB11+AC11))*AE11*D11/(AD11*C11+AE11*D11+AF11*E11)),0) -> 0 | AI11: =IF((AD11*C11+AE11*D11+AF11*E11)>0,MIN(E11-(AC11),(S11-(AA11+AB11+AC11))*AF11*E11/(AD11*C11+AE11*D11+AF11*E11)),0) -> 0 | AJ11: =IF(C11-(AA11+AG11)>Inputs!$B$19,1,0) -> 1 | AK11: =IF(D11-(AB11+AH11)>Inputs!$B$19,1,0) -> 1 | AL11: =IF(E11-(AC11+AI11)>Inputs!$B$19,1,0) -> 1 | AM11: =IF((AJ11*C11+AK11*D11+AL11*E11)>0,MIN(C11-(AA11+AG11),(S11-(AA11+AB11+AC11+AG11+AH11+AI11))*AJ11*C11/(AJ11*C11+AK11*D11+AL11*E11)),0) -> 0 | AN11: =IF((AJ11*C11+AK11*D11+AL11*E11)>0,MIN(D11-(AB11+AH11),(S11-(AA11+AB11+AC11+AG11+AH11+AI11))*AK11*D11/(AJ11*C11+AK11*D11+AL11*E11)),0) -> 0 | AO11: =IF((AJ11*C11+AK11*D11+AL11*E11)>0,MIN(E11-(AC11+AI11),(S11-(AA11+AB11+AC11+AG11+AH11+AI11))*AL11*E11/(AJ11*C11+AK11*D11+AL11*E11)),0) -> 0 | AP11: =IF(T11=1,U11,AA11+AG11+AM11) -> 8429093 | AQ11: =IF(T11=1,V11,AB11+AH11+AN11) -> 0 | AR11: =IF(T11=1,W11,AC11+AI11+AO11) -> 0 | AS11: =S11-AP11-AQ11-AR11 -> 0 | AT11: =C11-AP11 -> 2.4783725e+08 | AU11: =D11-AQ11 -> 40000000 | AV11: =E11-AR11 -> 30000000 | AW11: =Pool!CB11 -> 3.4555264e+08 | AX11: =IF((AT11)>Inputs!$B$19,AW11/(AT11),1000000000) -> 1.3942724 | AY11: =IF((J11)>0.000000001,(R11-I11-MAX(-M11,0))/(J11),1000000000) -> 2.2639879 | AZ11: =IF(OR(AX11<Inputs!$B$24,AY11<Inputs!$B$25),1,0) -> 0 | BA11: =IF((AT11+AU11)>Inputs!$B$19,AW11/(AT11+AU11),1000000000) -> 1.200514 | BB11: =IF((J11+K11)>0.000000001,(R11-I11-MAX(-M11,0))/(J11+K11),1000000000) -> 1.9011968 | BC11: =IF(OR(BA11<Inputs!$B$29,BB11<Inputs!$B$30),1,0) -> 0 | BD11: =IF((AT11+AU11+AV11)>Inputs!$B$19,AW11/(AT11+AU11+AV11),1000000000) -> 1.0872 | BE11: =IF((J11+K11+L11)>0.000000001,(R11-I11-MAX(-M11,0))/(J11+K11+L11),1000000000) -> 1.6638146 | BF11: =IF(OR(BD11<Inputs!$B$34,BE11<Inputs!$B$35),1,0) -> 0 | BG11: =MAX(AZ11,BC11,BF11) -> 0 | BH11: =MIN(R11,N11) -> 184509.03 | BI11: =R11-BH11 -> 2498533.3 | BJ11: =MIN(BI11,O11) -> 1103598.4 | BK11: =BI11-BJ11 -> 1394934.9 | BL11: =AZ11*MIN(AT11,BK11) -> 0 | BM11: =AZ11*MIN(AU11,BK11-BL11) -> 0 | BN11: =AZ11*MIN(AV11,BK11-BL11-BM11) -> 0 | BO11: =BK11-BL11-BM11-BN11 -> 1394934.9 | BP11: =MIN(BO11,P11) -> 210591.36 | BQ11: =BO11-BP11 -> 1184343.6 | BR11: =BC11*MIN((AT11-BL11),BQ11) -> 0 | BS11: =BC11*MIN((AU11-BM11),BQ11-BR11) -> 0 | BT11: =BC11*MIN((AV11-BN11),BQ11-BR11-BS11) -> 0 | BU11: =BQ11-BR11-BS11-BT11 -> 1184343.6 | BV11: =MIN(BU11,Q11) -> 187500 | BW11: =BU11-BV11 -> 996843.55 | BX11: =BF11*MIN((AT11-BL11-BR11),BW11) -> 0 | BY11: =BF11*MIN((AU11-BM11-BS11),BW11-BX11) -> 0 | BZ11: =BF11*MIN((AV11-BN11-BT11),BW11-BX11-BY11) -> 0 | CA11: =BW11-BX11-BY11-BZ11 -> 996843.55 | CB11: =MAX(0,AT11+AU11+AV11-BL11-BM11-BN11-BR11-BS11-BT11-BX11-BY11-BZ11-AW11) -> 0 | CC11: =1*MIN((AT11-BL11-BR11-BX11),MIN(CA11,CB11)) -> 0 | CD11: =1*MIN((AU11-BM11-BS11-BY11),MIN(CA11,CB11)-CC11) -> 0 | CE11: =1*MIN((AV11-BN11-BT11-BZ11),MIN(CA11,CB11)-CC11-CD11) -> 0 | CF11: =CA11-CC11-CD11-CE11 -> 996843.55 | CG11: =IF(C11+D11+E11>Inputs!$B$19,MIN(CF11,MAX(0,Inputs!$B$15-DO10)),0) -> 0 | CH11: =CF11-CG11 -> 996843.55 | CI11: =DO10+CG11 -> 3000000 | CJ11: =MIN(MAX(N11-BH11,0),CI11) -> 0 | CK11: =MIN(MAX(O11-BJ11,0),CI11-CJ11) -> 0 | CL11: =MIN(MAX(P11-BP11,0),CI11-CJ11-CK11) -> 0 | CM11: =CJ11+CK11+CL11 -> 0 | CN11: =CI11-CM11 -> 3000000 | CO11: =BH11+CJ11 -> 184509.03 | CP11: =BJ11+CK11 -> 1103598.4 | CQ11: =BP11+CL11 -> 210591.36 | CR11: =BV11 -> 187500 | CS11: =AT11-BL11-BR11-BX11-CC11 -> 2.4783725e+08 | CT11: =AU11-BM11-BS11-BY11-CD11 -> 40000000 | CU11: =AV11-BN11-BT11-BZ11-CE11 -> 30000000 | CV11: =MAX(0,CS11+CT11+CU11-AW11) -> 0 | CW11: =MIN(CU11,CV11) -> 0 | CX11: =MIN(CT11,CV11-CW11) -> 0 | CY11: =MIN(CS11,CV11-CW11-CX11) -> 0 | CZ11: =IF(CS11-CY11<Inputs!$B$19,0,CS11-CY11) -> 2.4783725e+08 | DA11: =IF(CT11-CX11<Inputs!$B$19,0,CT11-CX11) -> 40000000 | DB11: =IF(CU11-CW11<Inputs!$B$19,0,CU11-CW11) -> 30000000 | DC11: =N11-CO11 -> 0 | DD11: =O11-CP11 -> 0 | DE11: =P11-CQ11 -> 0 | DF11: =Q11-CR11 -> 0 | DG11: =IF(CZ11+DA11+DB11<=Inputs!$B$19,1,0) -> 0 | DH11: =DG11*CN11 -> 0 | DI11: =DG11*(AS11+DH11) -> 0 | DJ11: =DG11*MIN(DC11,DI11) -> 0 | DK11: =DG11*MIN(DD11,DI11-DJ11) -> 0 | DL11: =DG11*MIN(DE11,DI11-DJ11-DK11) -> 0 | DM11: =DG11*MIN(DF11,DI11-DJ11-DK11-DL11) -> 0 | DN11: =DJ11+DK11+DL11+DM11 -> 0 | DO11: =CN11-DH11 -> 3000000 | DP11: =DC11-DJ11 -> 0 | DQ11: =DD11-DK11 -> 0 | DR11: =DE11-DL11 -> 0 | DS11: =DF11-DM11 -> 0 | DT11: =CO11+DJ11 -> 184509.03 | DU11: =CP11+DK11 -> 1103598.4 | DV11: =AP11+BL11+BR11+BX11+CC11 -> 8429093 | DW11: =CQ11+DL11 -> 210591.36 | DX11: =AQ11+BM11+BS11+BY11+CD11 -> 0 | DY11: =CR11+DM11 -> 187500 | DZ11: =AR11+BN11+BT11+BZ11+CE11 -> 0 | EA11: =DI11-DN11 -> 0 | EB11: =CH11+EA11 -> 996843.55 | EC11: =R11-I11-MAX(-M11,0)-J11-K11-L11 -> 996843.55 | ED11: =R11+S11+CM11+DH11-CG11-DT11-DU11-DW11-DY11-DV11-DX11-DZ11-EB11 -> 0 | EE11: =IF(AND(EB11>0.000001,DP11+DQ11+DR11+DS11>0.000001),1,0) -> 0
A12: =ROW()-5 -> 7 | B12: =Inputs!$B$11+(Inputs!$B$12-Inputs!$B$11)*(1-EXP(-A12/Inputs!$B$13))+Inputs!$B$8 -> 0.040343684 | C12: =CZ11 -> 2.4783725e+08 | D12: =DA11 -> 40000000 | E12: =DB11 -> 30000000 | F12: =IF(Inputs!$B$22=1,B12+Inputs!$B$23,Inputs!$B$23)/12 -> 0.0042786403 | G12: =IF(Inputs!$B$27=1,B12+Inputs!$B$28,Inputs!$B$28)/12 -> 0.0052369736 | H12: =IF(Inputs!$B$32=1,B12+Inputs!$B$33,Inputs!$B$33)/12 -> 0.00625 | I12: =Pool!BT12*Inputs!$B$14/12 -> 179616.01 | J12: =C12*F12 -> 1060406.4 | K12: =D12*G12 -> 209478.95 | L12: =E12*H12 -> 187500 | M12: =Inputs!$B$17*(C12*Inputs!$B$22+D12*Inputs!$B$27+E12*Inputs!$B$32)*(B12-Inputs!$B$18)/12 -> 0 | N12: =DP11+I12+MAX(-M12,0) -> 179616.01 | O12: =DQ11+J12 -> 1060406.4 | P12: =DR11+K12 -> 209478.95 | Q12: =DS11+L12 -> 187500 | R12: =Pool!BV12+MAX(M12,0) -> 2613883.2 | S12: =Pool!BW12+Pool!BX12+Pool!BZ12 -> 8934484.6 | T12: =MAX(T11,BG11) -> 1 | U12: =MIN(C12,S12) -> 8934484.6 | V12: =MIN(D12,S12-U12) -> 0 | W12: =MIN(E12,S12-U12-V12) -> 0 | X12: =IF(C12-(0)>Inputs!$B$19,1,0) -> 1 | Y12: =IF(D12-(0)>Inputs!$B$19,1,0) -> 1 | Z12: =IF(E12-(0)>Inputs!$B$19,1,0) -> 1 | AA12: =IF((X12*C12+Y12*D12+Z12*E12)>0,MIN(C12-(0),S12*X12*C12/(X12*C12+Y12*D12+Z12*E12)),0) -> 6966767.1 | AB12: =IF((X12*C12+Y12*D12+Z12*E12)>0,MIN(D12-(0),S12*Y12*D12/(X12*C12+Y12*D12+Z12*E12)),0) -> 1124410 | AC12: =IF((X12*C12+Y12*D12+Z12*E12)>0,MIN(E12-(0),S12*Z12*E12/(X12*C12+Y12*D12+Z12*E12)),0) -> 843307.52 | AD12: =IF(C12-(AA12)>Inputs!$B$19,1,0) -> 1 | AE12: =IF(D12-(AB12)>Inputs!$B$19,1,0) -> 1 | AF12: =IF(E12-(AC12)>Inputs!$B$19,1,0) -> 1 | AG12: =IF((AD12*C12+AE12*D12+AF12*E12)>0,MIN(C12-(AA12),(S12-(AA12+AB12+AC12))*AD12*C12/(AD12*C12+AE12*D12+AF12*E12)),0) -> 0 | AH12: =IF((AD12*C12+AE12*D12+AF12*E12)>0,MIN(D12-(AB12),(S12-(AA12+AB12+AC12))*AE12*D12/(AD12*C12+AE12*D12+AF12*E12)),0) -> 0 | AI12: =IF((AD12*C12+AE12*D12+AF12*E12)>0,MIN(E12-(AC12),(S12-(AA12+AB12+AC12))*AF12*E12/(AD12*C12+AE12*D12+AF12*E12)),0) -> 0 | AJ12: =IF(C12-(AA12+AG12)>Inputs!$B$19,1,0) -> 1 | AK12: =IF(D12-(AB12+AH12)>Inputs!$B$19,1,0) -> 1 | AL12: =IF(E12-(AC12+AI12)>Inputs!$B$19,1,0) -> 1 | AM12: =IF((AJ12*C12+AK12*D12+AL12*E12)>0,MIN(C12-(AA12+AG12),(S12-(AA12+AB12+AC12+AG12+AH12+AI12))*AJ12*C12/(AJ12*C12+AK12*D12+AL12*E12)),0) -> 0 | AN12: =IF((AJ12*C12+AK12*D12+AL12*E12)>0,MIN(D12-(AB12+AH12),(S12-(AA12+AB12+AC12+AG12+AH12+AI12))*AK12*D12/(AJ12*C12+AK12*D12+AL12*E12)),0) -> 0 | AO12: =IF((AJ12*C12+AK12*D12+AL12*E12)>0,MIN(E12-(AC12+AI12),(S12-(AA12+AB12+AC12+AG12+AH12+AI12))*AL12*E12/(AJ12*C12+AK12*D12+AL12*E12)),0) -> 0 | AP12: =IF(T12=1,U12,AA12+AG12+AM12) -> 8934484.6 | AQ12: =IF(T12=1,V12,AB12+AH12+AN12) -> 0 | AR12: =IF(T12=1,W12,AC12+AI12+AO12) -> 0 | AS12: =S12-AP12-AQ12-AR12 -> 0 | AT12: =C12-AP12 -> 2.3890276e+08 | AU12: =D12-AQ12 -> 40000000 | AV12: =E12-AR12 -> 30000000 | AW12: =Pool!CB12 -> 3.3627124e+08 | AX12: =IF((AT12)>Inputs!$B$19,AW12/(AT12),1000000000) -> 1.4075653 | AY12: =IF((J12)>0.000000001,(R12-I12-MAX(-M12,0))/(J12),1000000000) -> 2.2955983 | AZ12: =IF(OR(AX12<Inputs!$B$24,AY12<Inputs!$B$25),1,0) -> 0 | BA12: =IF((AT12+AU12)>Inputs!$B$19,AW12/(AT12+AU12),1000000000) -> 1.2056935 | BB12: =IF((J12+K12)>0.000000001,(R12-I12-MAX(-M12,0))/(J12+K12),1000000000) -> 1.9169188 | BC12: =IF(OR(BA12<Inputs!$B$29,BB12<Inputs!$B$30),1,0) -> 0 | BD12: =IF((AT12+AU12+AV12)>Inputs!$B$19,AW12/(AT12+AU12+AV12),1000000000) -> 1.088599 | BE12: =IF((J12+K12+L12)>0.000000001,(R12-I12-MAX(-M12,0))/(J12+K12+L12),1000000000) -> 1.6702975 | BF12: =IF(OR(BD12<Inputs!$B$34,BE12<Inputs!$B$35),1,0) -> 0 | BG12: =MAX(AZ12,BC12,BF12) -> 0 | BH12: =MIN(R12,N12) -> 179616.01 | BI12: =R12-BH12 -> 2434267.2 | BJ12: =MIN(BI12,O12) -> 1060406.4 | BK12: =BI12-BJ12 -> 1373860.8 | BL12: =AZ12*MIN(AT12,BK12) -> 0 | BM12: =AZ12*MIN(AU12,BK12-BL12) -> 0 | BN12: =AZ12*MIN(AV12,BK12-BL12-BM12) -> 0 | BO12: =BK12-BL12-BM12-BN12 -> 1373860.8 | BP12: =MIN(BO12,P12) -> 209478.95 | BQ12: =BO12-BP12 -> 1164381.8 | BR12: =BC12*MIN((AT12-BL12),BQ12) -> 0 | BS12: =BC12*MIN((AU12-BM12),BQ12-BR12) -> 0 | BT12: =BC12*MIN((AV12-BN12),BQ12-BR12-BS12) -> 0 | BU12: =BQ12-BR12-BS12-BT12 -> 1164381.8 | BV12: =MIN(BU12,Q12) -> 187500 | BW12: =BU12-BV12 -> 976881.82 | BX12: =BF12*MIN((AT12-BL12-BR12),BW12) -> 0 | BY12: =BF12*MIN((AU12-BM12-BS12),BW12-BX12) -> 0 | BZ12: =BF12*MIN((AV12-BN12-BT12),BW12-BX12-BY12) -> 0 | CA12: =BW12-BX12-BY12-BZ12 -> 976881.82 | CB12: =MAX(0,AT12+AU12+AV12-BL12-BM12-BN12-BR12-BS12-BT12-BX12-BY12-BZ12-AW12) -> 0 | CC12: =1*MIN((AT12-BL12-BR12-BX12),MIN(CA12,CB12)) -> 0 | CD12: =1*MIN((AU12-BM12-BS12-BY12),MIN(CA12,CB12)-CC12) -> 0 | CE12: =1*MIN((AV12-BN12-BT12-BZ12),MIN(CA12,CB12)-CC12-CD12) -> 0 | CF12: =CA12-CC12-CD12-CE12 -> 976881.82 | CG12: =IF(C12+D12+E12>Inputs!$B$19,MIN(CF12,MAX(0,Inputs!$B$15-DO11)),0) -> 0 | CH12: =CF12-CG12 -> 976881.82 | CI12: =DO11+CG12 -> 3000000 | CJ12: =MIN(MAX(N12-BH12,0),CI12) -> 0 | CK12: =MIN(MAX(O12-BJ12,0),CI12-CJ12) -> 0 | CL12: =MIN(MAX(P12-BP12,0),CI12-CJ12-CK12) -> 0 | CM12: =CJ12+CK12+CL12 -> 0 | CN12: =CI12-CM12 -> 3000000 | CO12: =BH12+CJ12 -> 179616.01 | CP12: =BJ12+CK12 -> 1060406.4 | CQ12: =BP12+CL12 -> 209478.95 | CR12: =BV12 -> 187500 | CS12: =AT12-BL12-BR12-BX12-CC12 -> 2.3890276e+08 | CT12: =AU12-BM12-BS12-BY12-CD12 -> 40000000 | CU12: =AV12-BN12-BT12-BZ12-CE12 -> 30000000 | CV12: =MAX(0,CS12+CT12+CU12-AW12) -> 0 | CW12: =MIN(CU12,CV12) -> 0 | CX12: =MIN(CT12,CV12-CW12) -> 0 | CY12: =MIN(CS12,CV12-CW12-CX12) -> 0 | CZ12: =IF(CS12-CY12<Inputs!$B$19,0,CS12-CY12) -> 2.3890276e+08 | DA12: =IF(CT12-CX12<Inputs!$B$19,0,CT12-CX12) -> 40000000 | DB12: =IF(CU12-CW12<Inputs!$B$19,0,CU12-CW12) -> 30000000 | DC12: =N12-CO12 -> 0 | DD12: =O12-CP12 -> 0 | DE12: =P12-CQ12 -> 0 | DF12: =Q12-CR12 -> 0 | DG12: =IF(CZ12+DA12+DB12<=Inputs!$B$19,1,0) -> 0 | DH12: =DG12*CN12 -> 0 | DI12: =DG12*(AS12+DH12) -> 0 | DJ12: =DG12*MIN(DC12,DI12) -> 0 | DK12: =DG12*MIN(DD12,DI12-DJ12) -> 0 | DL12: =DG12*MIN(DE12,DI12-DJ12-DK12) -> 0 | DM12: =DG12*MIN(DF12,DI12-DJ12-DK12-DL12) -> 0 | DN12: =DJ12+DK12+DL12+DM12 -> 0 | DO12: =CN12-DH12 -> 3000000 | DP12: =DC12-DJ12 -> 0 | DQ12: =DD12-DK12 -> 0 | DR12: =DE12-DL12 -> 0 | DS12: =DF12-DM12 -> 0 | DT12: =CO12+DJ12 -> 179616.01 | DU12: =CP12+DK12 -> 1060406.4 | DV12: =AP12+BL12+BR12+BX12+CC12 -> 8934484.6 | DW12: =CQ12+DL12 -> 209478.95 | DX12: =AQ12+BM12+BS12+BY12+CD12 -> 0 | DY12: =CR12+DM12 -> 187500 | DZ12: =AR12+BN12+BT12+BZ12+CE12 -> 0 | EA12: =DI12-DN12 -> 0 | EB12: =CH12+EA12 -> 976881.82 | EC12: =R12-I12-MAX(-M12,0)-J12-K12-L12 -> 976881.82 | ED12: =R12+S12+CM12+DH12-CG12-DT12-DU12-DW12-DY12-DV12-DX12-DZ12-EB12 -> 0 | EE12: =IF(AND(EB12>0.000001,DP12+DQ12+DR12+DS12>0.000001),1,0) -> 0
A13: =ROW()-5 -> 8 | B13: =Inputs!$B$11+(Inputs!$B$12-Inputs!$B$11)*(1-EXP(-A13/Inputs!$B$13))+Inputs!$B$8 -> 0.040023579 | C13: =CZ12 -> 2.3890276e+08 | D13: =DA12 -> 40000000 | E13: =DB12 -> 30000000 | F13: =IF(Inputs!$B$22=1,B13+Inputs!$B$23,Inputs!$B$23)/12 -> 0.0042519649 | G13: =IF(Inputs!$B$27=1,B13+Inputs!$B$28,Inputs!$B$28)/12 -> 0.0052102982 | H13: =IF(Inputs!$B$32=1,B13+Inputs!$B$33,Inputs!$B$33)/12 -> 0.00625 | I13: =Pool!BT13*Inputs!$B$14/12 -> 174789.49 | J13: =C13*F13 -> 1015806.2 | K13: =D13*G13 -> 208411.93 | L13: =E13*H13 -> 187500 | M13: =Inputs!$B$17*(C13*Inputs!$B$22+D13*Inputs!$B$27+E13*Inputs!$B$32)*(B13-Inputs!$B$18)/12 -> 0 | N13: =DP12+I13+MAX(-M13,0) -> 174789.49 | O13: =DQ12+J13 -> 1015806.2 | P13: =DR12+K13 -> 208411.93 | Q13: =DS12+L13 -> 187500 | R13: =Pool!BV13+MAX(M13,0) -> 2545655.3 | S13: =Pool!BW13+Pool!BX13+Pool!BZ13 -> 8817487.4 | T13: =MAX(T12,BG12) -> 1 | U13: =MIN(C13,S13) -> 8817487.4 | V13: =MIN(D13,S13-U13) -> 0 | W13: =MIN(E13,S13-U13-V13) -> 0 | X13: =IF(C13-(0)>Inputs!$B$19,1,0) -> 1 | Y13: =IF(D13-(0)>Inputs!$B$19,1,0) -> 1 | Z13: =IF(E13-(0)>Inputs!$B$19,1,0) -> 1 | AA13: =IF((X13*C13+Y13*D13+Z13*E13)>0,MIN(C13-(0),S13*X13*C13/(X13*C13+Y13*D13+Z13*E13)),0) -> 6819369.5 | AB13: =IF((X13*C13+Y13*D13+Z13*E13)>0,MIN(D13-(0),S13*Y13*D13/(X13*C13+Y13*D13+Z13*E13)),0) -> 1141781.6 | AC13: =IF((X13*C13+Y13*D13+Z13*E13)>0,MIN(E13-(0),S13*Z13*E13/(X13*C13+Y13*D13+Z13*E13)),0) -> 856336.21 | AD13: =IF(C13-(AA13)>Inputs!$B$19,1,0) -> 1 | AE13: =IF(D13-(AB13)>Inputs!$B$19,1,0) -> 1 | AF13: =IF(E13-(AC13)>Inputs!$B$19,1,0) -> 1 | AG13: =IF((AD13*C13+AE13*D13+AF13*E13)>0,MIN(C13-(AA13),(S13-(AA13+AB13+AC13))*AD13*C13/(AD13*C13+AE13*D13+AF13*E13)),0) -> 0 | AH13: =IF((AD13*C13+AE13*D13+AF13*E13)>0,MIN(D13-(AB13),(S13-(AA13+AB13+AC13))*AE13*D13/(AD13*C13+AE13*D13+AF13*E13)),0) -> 0 | AI13: =IF((AD13*C13+AE13*D13+AF13*E13)>0,MIN(E13-(AC13),(S13-(AA13+AB13+AC13))*AF13*E13/(AD13*C13+AE13*D13+AF13*E13)),0) -> 0 | AJ13: =IF(C13-(AA13+AG13)>Inputs!$B$19,1,0) -> 1 | AK13: =IF(D13-(AB13+AH13)>Inputs!$B$19,1,0) -> 1 | AL13: =IF(E13-(AC13+AI13)>Inputs!$B$19,1,0) -> 1 | AM13: =IF((AJ13*C13+AK13*D13+AL13*E13)>0,MIN(C13-(AA13+AG13),(S13-(AA13+AB13+AC13+AG13+AH13+AI13))*AJ13*C13/(AJ13*C13+AK13*D13+AL13*E13)),0) -> 0 | AN13: =IF((AJ13*C13+AK13*D13+AL13*E13)>0,MIN(D13-(AB13+AH13),(S13-(AA13+AB13+AC13+AG13+AH13+AI13))*AK13*D13/(AJ13*C13+AK13*D13+AL13*E13)),0) -> 0 | AO13: =IF((AJ13*C13+AK13*D13+AL13*E13)>0,MIN(E13-(AC13+AI13),(S13-(AA13+AB13+AC13+AG13+AH13+AI13))*AL13*E13/(AJ13*C13+AK13*D13+AL13*E13)),0) -> 0 | AP13: =IF(T13=1,U13,AA13+AG13+AM13) -> 8817487.4 | AQ13: =IF(T13=1,V13,AB13+AH13+AN13) -> 0 | AR13: =IF(T13=1,W13,AC13+AI13+AO13) -> 0 | AS13: =S13-AP13-AQ13-AR13 -> 0 | AT13: =C13-AP13 -> 2.3008527e+08 | AU13: =D13-AQ13 -> 40000000 | AV13: =E13-AR13 -> 30000000 | AW13: =Pool!CB13 -> 3.2711615e+08 | AX13: =IF((AT13)>Inputs!$B$19,AW13/(AT13),1000000000) -> 1.421717 | AY13: =IF((J13)>0.000000001,(R13-I13-MAX(-M13,0))/(J13),1000000000) -> 2.3339746 | AZ13: =IF(OR(AX13<Inputs!$B$24,AY13<Inputs!$B$25),1,0) -> 0 | BA13: =IF((AT13+AU13)>Inputs!$B$19,AW13/(AT13+AU13),1000000000) -> 1.2111588 | BB13: =IF((J13+K13)>0.000000001,(R13-I13-MAX(-M13,0))/(J13+K13),1000000000) -> 1.9366368 | BC13: =IF(OR(BA13<Inputs!$B$29,BB13<Inputs!$B$30),1,0) -> 0 | BD13: =IF((AT13+AU13+AV13)>Inputs!$B$19,AW13/(AT13+AU13+AV13),1000000000) -> 1.0900773 | BE13: =IF((J13+K13+L13)>0.000000001,(R13-I13-MAX(-M13,0))/(J13+K13+L13),1000000000) -> 1.6794187 | BF13: =IF(OR(BD13<Inputs!$B$34,BE13<Inputs!$B$35),1,0) -> 0 | BG13: =MAX(AZ13,BC13,BF13) -> 0 | BH13: =MIN(R13,N13) -> 174789.49 | BI13: =R13-BH13 -> 2370865.8 | BJ13: =MIN(BI13,O13) -> 1015806.2 | BK13: =BI13-BJ13 -> 1355059.6 | BL13: =AZ13*MIN(AT13,BK13) -> 0 | BM13: =AZ13*MIN(AU13,BK13-BL13) -> 0 | BN13: =AZ13*MIN(AV13,BK13-BL13-BM13) -> 0 | BO13: =BK13-BL13-BM13-BN13 -> 1355059.6 | BP13: =MIN(BO13,P13) -> 208411.93 | BQ13: =BO13-BP13 -> 1146647.7 | BR13: =BC13*MIN((AT13-BL13),BQ13) -> 0 | BS13: =BC13*MIN((AU13-BM13),BQ13-BR13) -> 0 | BT13: =BC13*MIN((AV13-BN13),BQ13-BR13-BS13) -> 0 | BU13: =BQ13-BR13-BS13-BT13 -> 1146647.7 | BV13: =MIN(BU13,Q13) -> 187500 | BW13: =BU13-BV13 -> 959147.72 | BX13: =BF13*MIN((AT13-BL13-BR13),BW13) -> 0 | BY13: =BF13*MIN((AU13-BM13-BS13),BW13-BX13) -> 0 | BZ13: =BF13*MIN((AV13-BN13-BT13),BW13-BX13-BY13) -> 0 | CA13: =BW13-BX13-BY13-BZ13 -> 959147.72 | CB13: =MAX(0,AT13+AU13+AV13-BL13-BM13-BN13-BR13-BS13-BT13-BX13-BY13-BZ13-AW13) -> 0 | CC13: =1*MIN((AT13-BL13-BR13-BX13),MIN(CA13,CB13)) -> 0 | CD13: =1*MIN((AU13-BM13-BS13-BY13),MIN(CA13,CB13)-CC13) -> 0 | CE13: =1*MIN((AV13-BN13-BT13-BZ13),MIN(CA13,CB13)-CC13-CD13) -> 0 | CF13: =CA13-CC13-CD13-CE13 -> 959147.72 | CG13: =IF(C13+D13+E13>Inputs!$B$19,MIN(CF13,MAX(0,Inputs!$B$15-DO12)),0) -> 0 | CH13: =CF13-CG13 -> 959147.72 | CI13: =DO12+CG13 -> 3000000 | CJ13: =MIN(MAX(N13-BH13,0),CI13) -> 0 | CK13: =MIN(MAX(O13-BJ13,0),CI13-CJ13) -> 0 | CL13: =MIN(MAX(P13-BP13,0),CI13-CJ13-CK13) -> 0 | CM13: =CJ13+CK13+CL13 -> 0 | CN13: =CI13-CM13 -> 3000000 | CO13: =BH13+CJ13 -> 174789.49 | CP13: =BJ13+CK13 -> 1015806.2 | CQ13: =BP13+CL13 -> 208411.93 | CR13: =BV13 -> 187500 | CS13: =AT13-BL13-BR13-BX13-CC13 -> 2.3008527e+08 | CT13: =AU13-BM13-BS13-BY13-CD13 -> 40000000 | CU13: =AV13-BN13-BT13-BZ13-CE13 -> 30000000 | CV13: =MAX(0,CS13+CT13+CU13-AW13) -> 0 | CW13: =MIN(CU13,CV13) -> 0 | CX13: =MIN(CT13,CV13-CW13) -> 0 | CY13: =MIN(CS13,CV13-CW13-CX13) -> 0 | CZ13: =IF(CS13-CY13<Inputs!$B$19,0,CS13-CY13) -> 2.3008527e+08 | DA13: =IF(CT13-CX13<Inputs!$B$19,0,CT13-CX13) -> 40000000 | DB13: =IF(CU13-CW13<Inputs!$B$19,0,CU13-CW13) -> 30000000 | DC13: =N13-CO13 -> 0 | DD13: =O13-CP13 -> 0 | DE13: =P13-CQ13 -> 0 | DF13: =Q13-CR13 -> 0 | DG13: =IF(CZ13+DA13+DB13<=Inputs!$B$19,1,0) -> 0 | DH13: =DG13*CN13 -> 0 | DI13: =DG13*(AS13+DH13) -> 0 | DJ13: =DG13*MIN(DC13,DI13) -> 0 | DK13: =DG13*MIN(DD13,DI13-DJ13) -> 0 | DL13: =DG13*MIN(DE13,DI13-DJ13-DK13) -> 0 | DM13: =DG13*MIN(DF13,DI13-DJ13-DK13-DL13) -> 0 | DN13: =DJ13+DK13+DL13+DM13 -> 0 | DO13: =CN13-DH13 -> 3000000 | DP13: =DC13-DJ13 -> 0 | DQ13: =DD13-DK13 -> 0 | DR13: =DE13-DL13 -> 0 | DS13: =DF13-DM13 -> 0 | DT13: =CO13+DJ13 -> 174789.49 | DU13: =CP13+DK13 -> 1015806.2 | DV13: =AP13+BL13+BR13+BX13+CC13 -> 8817487.4 | DW13: =CQ13+DL13 -> 208411.93 | DX13: =AQ13+BM13+BS13+BY13+CD13 -> 0 | DY13: =CR13+DM13 -> 187500 | DZ13: =AR13+BN13+BT13+BZ13+CE13 -> 0 | EA13: =DI13-DN13 -> 0 | EB13: =CH13+EA13 -> 959147.72 | EC13: =R13-I13-MAX(-M13,0)-J13-K13-L13 -> 959147.72 | ED13: =R13+S13+CM13+DH13-CG13-DT13-DU13-DW13-DY13-DV13-DX13-DZ13-EB13 -> 0 | EE13: =IF(AND(EB13>0.000001,DP13+DQ13+DR13+DS13>0.000001),1,0) -> 0
A14: =ROW()-5 -> 9 | B14: =Inputs!$B$11+(Inputs!$B$12-Inputs!$B$11)*(1-EXP(-A14/Inputs!$B$13))+Inputs!$B$8 -> 0.039716537 | C14: =CZ13 -> 2.3008527e+08 | D14: =DA13 -> 40000000 | E14: =DB13 -> 30000000 | F14: =IF(Inputs!$B$22=1,B14+Inputs!$B$23,Inputs!$B$23)/12 -> 0.0042263781 | G14: =IF(Inputs!$B$27=1,B14+Inputs!$B$28,Inputs!$B$28)/12 -> 0.0051847115 | H14: =IF(Inputs!$B$32=1,B14+Inputs!$B$33,Inputs!$B$33)/12 -> 0.00625 | I14: =Pool!BT14*Inputs!$B$14/12 -> 170028.66 | J14: =C14*F14 -> 972427.37 | K14: =D14*G14 -> 207388.46 | L14: =E14*H14 -> 187500 | M14: =Inputs!$B$17*(C14*Inputs!$B$22+D14*Inputs!$B$27+E14*Inputs!$B$32)*(B14-Inputs!$B$18)/12 -> 0 | N14: =DP13+I14+MAX(-M14,0) -> 170028.66 | O14: =DQ13+J14 -> 972427.37 | P14: =DR13+K14 -> 207388.46 | Q14: =DS13+L14 -> 187500 | R14: =Pool!BV14+MAX(M14,0) -> 2478347.4 | S14: =Pool!BW14+Pool!BX14+Pool!BZ14 -> 8701878.7 | T14: =MAX(T13,BG13) -> 1 | U14: =MIN(C14,S14) -> 8701878.7 | V14: =MIN(D14,S14-U14) -> 0 | W14: =MIN(E14,S14-U14-V14) -> 0 | X14: =IF(C14-(0)>Inputs!$B$19,1,0) -> 1 | Y14: =IF(D14-(0)>Inputs!$B$19,1,0) -> 1 | Z14: =IF(E14-(0)>Inputs!$B$19,1,0) -> 1 | AA14: =IF((X14*C14+Y14*D14+Z14*E14)>0,MIN(C14-(0),S14*X14*C14/(X14*C14+Y14*D14+Z14*E14)),0) -> 6672017.4 | AB14: =IF((X14*C14+Y14*D14+Z14*E14)>0,MIN(D14-(0),S14*Y14*D14/(X14*C14+Y14*D14+Z14*E14)),0) -> 1159920.8 | AC14: =IF((X14*C14+Y14*D14+Z14*E14)>0,MIN(E14-(0),S14*Z14*E14/(X14*C14+Y14*D14+Z14*E14)),0) -> 869940.6 | AD14: =IF(C14-(AA14)>Inputs!$B$19,1,0) -> 1 | AE14: =IF(D14-(AB14)>Inputs!$B$19,1,0) -> 1 | AF14: =IF(E14-(AC14)>Inputs!$B$19,1,0) -> 1 | AG14: =IF((AD14*C14+AE14*D14+AF14*E14)>0,MIN(C14-(AA14),(S14-(AA14+AB14+AC14))*AD14*C14/(AD14*C14+AE14*D14+AF14*E14)),0) -> 0 | AH14: =IF((AD14*C14+AE14*D14+AF14*E14)>0,MIN(D14-(AB14),(S14-(AA14+AB14+AC14))*AE14*D14/(AD14*C14+AE14*D14+AF14*E14)),0) -> 0 | AI14: =IF((AD14*C14+AE14*D14+AF14*E14)>0,MIN(E14-(AC14),(S14-(AA14+AB14+AC14))*AF14*E14/(AD14*C14+AE14*D14+AF14*E14)),0) -> 0 | AJ14: =IF(C14-(AA14+AG14)>Inputs!$B$19,1,0) -> 1 | AK14: =IF(D14-(AB14+AH14)>Inputs!$B$19,1,0) -> 1 | AL14: =IF(E14-(AC14+AI14)>Inputs!$B$19,1,0) -> 1 | AM14: =IF((AJ14*C14+AK14*D14+AL14*E14)>0,MIN(C14-(AA14+AG14),(S14-(AA14+AB14+AC14+AG14+AH14+AI14))*AJ14*C14/(AJ14*C14+AK14*D14+AL14*E14)),0) -> 0 | AN14: =IF((AJ14*C14+AK14*D14+AL14*E14)>0,MIN(D14-(AB14+AH14),(S14-(AA14+AB14+AC14+AG14+AH14+AI14))*AK14*D14/(AJ14*C14+AK14*D14+AL14*E14)),0) -> 0 | AO14: =IF((AJ14*C14+AK14*D14+AL14*E14)>0,MIN(E14-(AC14+AI14),(S14-(AA14+AB14+AC14+AG14+AH14+AI14))*AL14*E14/(AJ14*C14+AK14*D14+AL14*E14)),0) -> 0 | AP14: =IF(T14=1,U14,AA14+AG14+AM14) -> 8701878.7 | AQ14: =IF(T14=1,V14,AB14+AH14+AN14) -> 0 | AR14: =IF(T14=1,W14,AC14+AI14+AO14) -> 0 | AS14: =S14-AP14-AQ14-AR14 -> 0 | AT14: =C14-AP14 -> 2.213834e+08 | AU14: =D14-AQ14 -> 40000000 | AV14: =E14-AR14 -> 30000000 | AW14: =Pool!CB14 -> 3.1808587e+08 | AX14: =IF((AT14)>Inputs!$B$19,AW14/(AT14),1000000000) -> 1.43681 | AY14: =IF((J14)>0.000000001,(R14-I14-MAX(-M14,0))/(J14),1000000000) -> 2.3737698 | AZ14: =IF(OR(AX14<Inputs!$B$24,AY14<Inputs!$B$25),1,0) -> 0 | BA14: =IF((AT14+AU14)>Inputs!$B$19,AW14/(AT14+AU14),1000000000) -> 1.2169322 | BB14: =IF((J14+K14)>0.000000001,(R14-I14-MAX(-M14,0))/(J14+K14),1000000000) -> 1.9565077 | BC14: =IF(OR(BA14<Inputs!$B$29,BB14<Inputs!$B$30),1,0) -> 0 | BD14: =IF((AT14+AU14+AV14)>Inputs!$B$19,AW14/(AT14+AU14+AV14),1000000000) -> 1.0916403 | BE14: =IF((J14+K14+L14)>0.000000001,(R14-I14-MAX(-M14,0))/(J14+K14+L14),1000000000) -> 1.6882118 | BF14: =IF(OR(BD14<Inputs!$B$34,BE14<Inputs!$B$35),1,0) -> 0 | BG14: =MAX(AZ14,BC14,BF14) -> 0 | BH14: =MIN(R14,N14) -> 170028.66 | BI14: =R14-BH14 -> 2308318.7 | BJ14: =MIN(BI14,O14) -> 972427.37 | BK14: =BI14-BJ14 -> 1335891.4 | BL14: =AZ14*MIN(AT14,BK14) -> 0 | BM14: =AZ14*MIN(AU14,BK14-BL14) -> 0 | BN14: =AZ14*MIN(AV14,BK14-BL14-BM14) -> 0 | BO14: =BK14-BL14-BM14-BN14 -> 1335891.4 | BP14: =MIN(BO14,P14) -> 207388.46 | BQ14: =BO14-BP14 -> 1128502.9 | BR14: =BC14*MIN((AT14-BL14),BQ14) -> 0 | BS14: =BC14*MIN((AU14-BM14),BQ14-BR14) -> 0 | BT14: =BC14*MIN((AV14-BN14),BQ14-BR14-BS14) -> 0 | BU14: =BQ14-BR14-BS14-BT14 -> 1128502.9 | BV14: =MIN(BU14,Q14) -> 187500 | BW14: =BU14-BV14 -> 941002.92 | BX14: =BF14*MIN((AT14-BL14-BR14),BW14) -> 0 | BY14: =BF14*MIN((AU14-BM14-BS14),BW14-BX14) -> 0 | BZ14: =BF14*MIN((AV14-BN14-BT14),BW14-BX14-BY14) -> 0 | CA14: =BW14-BX14-BY14-BZ14 -> 941002.92 | CB14: =MAX(0,AT14+AU14+AV14-BL14-BM14-BN14-BR14-BS14-BT14-BX14-BY14-BZ14-AW14) -> 0 | CC14: =1*MIN((AT14-BL14-BR14-BX14),MIN(CA14,CB14)) -> 0 | CD14: =1*MIN((AU14-BM14-BS14-BY14),MIN(CA14,CB14)-CC14) -> 0 | CE14: =1*MIN((AV14-BN14-BT14-BZ14),MIN(CA14,CB14)-CC14-CD14) -> 0 | CF14: =CA14-CC14-CD14-CE14 -> 941002.92 | CG14: =IF(C14+D14+E14>Inputs!$B$19,MIN(CF14,MAX(0,Inputs!$B$15-DO13)),0) -> 0 | CH14: =CF14-CG14 -> 941002.92 | CI14: =DO13+CG14 -> 3000000 | CJ14: =MIN(MAX(N14-BH14,0),CI14) -> 0 | CK14: =MIN(MAX(O14-BJ14,0),CI14-CJ14) -> 0 | CL14: =MIN(MAX(P14-BP14,0),CI14-CJ14-CK14) -> 0 | CM14: =CJ14+CK14+CL14 -> 0 | CN14: =CI14-CM14 -> 3000000 | CO14: =BH14+CJ14 -> 170028.66 | CP14: =BJ14+CK14 -> 972427.37 | CQ14: =BP14+CL14 -> 207388.46 | CR14: =BV14 -> 187500 | CS14: =AT14-BL14-BR14-BX14-CC14 -> 2.213834e+08 | CT14: =AU14-BM14-BS14-BY14-CD14 -> 40000000 | CU14: =AV14-BN14-BT14-BZ14-CE14 -> 30000000 | CV14: =MAX(0,CS14+CT14+CU14-AW14) -> 0 | CW14: =MIN(CU14,CV14) -> 0 | CX14: =MIN(CT14,CV14-CW14) -> 0 | CY14: =MIN(CS14,CV14-CW14-CX14) -> 0 | CZ14: =IF(CS14-CY14<Inputs!$B$19,0,CS14-CY14) -> 2.213834e+08 | DA14: =IF(CT14-CX14<Inputs!$B$19,0,CT14-CX14) -> 40000000 | DB14: =IF(CU14-CW14<Inputs!$B$19,0,CU14-CW14) -> 30000000 | DC14: =N14-CO14 -> 0 | DD14: =O14-CP14 -> 0 | DE14: =P14-CQ14 -> 0 | DF14: =Q14-CR14 -> 0 | DG14: =IF(CZ14+DA14+DB14<=Inputs!$B$19,1,0) -> 0 | DH14: =DG14*CN14 -> 0 | DI14: =DG14*(AS14+DH14) -> 0 | DJ14: =DG14*MIN(DC14,DI14) -> 0 | DK14: =DG14*MIN(DD14,DI14-DJ14) -> 0 | DL14: =DG14*MIN(DE14,DI14-DJ14-DK14) -> 0 | DM14: =DG14*MIN(DF14,DI14-DJ14-DK14-DL14) -> 0 | DN14: =DJ14+DK14+DL14+DM14 -> 0 | DO14: =CN14-DH14 -> 3000000 | DP14: =DC14-DJ14 -> 0 | DQ14: =DD14-DK14 -> 0 | DR14: =DE14-DL14 -> 0 | DS14: =DF14-DM14 -> 0 | DT14: =CO14+DJ14 -> 170028.66 | DU14: =CP14+DK14 -> 972427.37 | DV14: =AP14+BL14+BR14+BX14+CC14 -> 8701878.7 | DW14: =CQ14+DL14 -> 207388.46 | DX14: =AQ14+BM14+BS14+BY14+CD14 -> 0 | DY14: =CR14+DM14 -> 187500 | DZ14: =AR14+BN14+BT14+BZ14+CE14 -> 0 | EA14: =DI14-DN14 -> 0 | EB14: =CH14+EA14 -> 941002.92 | EC14: =R14-I14-MAX(-M14,0)-J14-K14-L14 -> 941002.92 | ED14: =R14+S14+CM14+DH14-CG14-DT14-DU14-DW14-DY14-DV14-DX14-DZ14-EB14 -> 0 | EE14: =IF(AND(EB14>0.000001,DP14+DQ14+DR14+DS14>0.000001),1,0) -> 0
A15: =ROW()-5 -> 10 | B15: =Inputs!$B$11+(Inputs!$B$12-Inputs!$B$11)*(1-EXP(-A15/Inputs!$B$13))+Inputs!$B$8 -> 0.039422027 | C15: =CZ14 -> 2.213834e+08 | D15: =DA14 -> 40000000 | E15: =DB14 -> 30000000 | F15: =IF(Inputs!$B$22=1,B15+Inputs!$B$23,Inputs!$B$23)/12 -> 0.0042018356 | G15: =IF(Inputs!$B$27=1,B15+Inputs!$B$28,Inputs!$B$28)/12 -> 0.0051601689 | H15: =IF(Inputs!$B$32=1,B15+Inputs!$B$33,Inputs!$B$33)/12 -> 0.00625 | I15: =Pool!BT15*Inputs!$B$14/12 -> 165332.73 | J15: =C15*F15 -> 930216.62 | K15: =D15*G15 -> 206406.76 | L15: =E15*H15 -> 187500 | M15: =Inputs!$B$17*(C15*Inputs!$B$22+D15*Inputs!$B$27+E15*Inputs!$B$32)*(B15-Inputs!$B$18)/12 -> 0 | N15: =DP14+I15+MAX(-M15,0) -> 165332.73 | O15: =DQ14+J15 -> 930216.62 | P15: =DR14+K15 -> 206406.76 | Q15: =DS14+L15 -> 187500 | R15: =Pool!BV15+MAX(M15,0) -> 2411948.6 | S15: =Pool!BW15+Pool!BX15+Pool!BZ15 -> 8587642.7 | T15: =MAX(T14,BG14) -> 1 | U15: =MIN(C15,S15) -> 8587642.7 | V15: =MIN(D15,S15-U15) -> 0 | W15: =MIN(E15,S15-U15-V15) -> 0 | X15: =IF(C15-(0)>Inputs!$B$19,1,0) -> 1 | Y15: =IF(D15-(0)>Inputs!$B$19,1,0) -> 1 | Z15: =IF(E15-(0)>Inputs!$B$19,1,0) -> 1 | AA15: =IF((X15*C15+Y15*D15+Z15*E15)>0,MIN(C15-(0),S15*X15*C15/(X15*C15+Y15*D15+Z15*E15)),0) -> 6524604.8 | AB15: =IF((X15*C15+Y15*D15+Z15*E15)>0,MIN(D15-(0),S15*Y15*D15/(X15*C15+Y15*D15+Z15*E15)),0) -> 1178878.8 | AC15: =IF((X15*C15+Y15*D15+Z15*E15)>0,MIN(E15-(0),S15*Z15*E15/(X15*C15+Y15*D15+Z15*E15)),0) -> 884159.11 | AD15: =IF(C15-(AA15)>Inputs!$B$19,1,0) -> 1 | AE15: =IF(D15-(AB15)>Inputs!$B$19,1,0) -> 1 | AF15: =IF(E15-(AC15)>Inputs!$B$19,1,0) -> 1 | AG15: =IF((AD15*C15+AE15*D15+AF15*E15)>0,MIN(C15-(AA15),(S15-(AA15+AB15+AC15))*AD15*C15/(AD15*C15+AE15*D15+AF15*E15)),0) -> 0 | AH15: =IF((AD15*C15+AE15*D15+AF15*E15)>0,MIN(D15-(AB15),(S15-(AA15+AB15+AC15))*AE15*D15/(AD15*C15+AE15*D15+AF15*E15)),0) -> 0 | AI15: =IF((AD15*C15+AE15*D15+AF15*E15)>0,MIN(E15-(AC15),(S15-(AA15+AB15+AC15))*AF15*E15/(AD15*C15+AE15*D15+AF15*E15)),0) -> 0 | AJ15: =IF(C15-(AA15+AG15)>Inputs!$B$19,1,0) -> 1 | AK15: =IF(D15-(AB15+AH15)>Inputs!$B$19,1,0) -> 1 | AL15: =IF(E15-(AC15+AI15)>Inputs!$B$19,1,0) -> 1 | AM15: =IF((AJ15*C15+AK15*D15+AL15*E15)>0,MIN(C15-(AA15+AG15),(S15-(AA15+AB15+AC15+AG15+AH15+AI15))*AJ15*C15/(AJ15*C15+AK15*D15+AL15*E15)),0) -> 0 | AN15: =IF((AJ15*C15+AK15*D15+AL15*E15)>0,MIN(D15-(AB15+AH15),(S15-(AA15+AB15+AC15+AG15+AH15+AI15))*AK15*D15/(AJ15*C15+AK15*D15+AL15*E15)),0) -> 0 | AO15: =IF((AJ15*C15+AK15*D15+AL15*E15)>0,MIN(E15-(AC15+AI15),(S15-(AA15+AB15+AC15+AG15+AH15+AI15))*AL15*E15/(AJ15*C15+AK15*D15+AL15*E15)),0) -> 0 | AP15: =IF(T15=1,U15,AA15+AG15+AM15) -> 8587642.7 | AQ15: =IF(T15=1,V15,AB15+AH15+AN15) -> 0 | AR15: =IF(T15=1,W15,AC15+AI15+AO15) -> 0 | AS15: =S15-AP15-AQ15-AR15 -> 0 | AT15: =C15-AP15 -> 2.1279575e+08 | AU15: =D15-AQ15 -> 40000000 | AV15: =E15-AR15 -> 30000000 | AW15: =Pool!CB15 -> 3.0917889e+08 | AX15: =IF((AT15)>Inputs!$B$19,AW15/(AT15),1000000000) -> 1.4529373 | AY15: =IF((J15)>0.000000001,(R15-I15-MAX(-M15,0))/(J15),1000000000) -> 2.4151534 | AZ15: =IF(OR(AX15<Inputs!$B$24,AY15<Inputs!$B$25),1,0) -> 0 | BA15: =IF((AT15+AU15)>Inputs!$B$19,AW15/(AT15+AU15),1000000000) -> 1.2230383 | BB15: =IF((J15+K15)>0.000000001,(R15-I15-MAX(-M15,0))/(J15+K15),1000000000) -> 1.9765701 | BC15: =IF(OR(BA15<Inputs!$B$29,BB15<Inputs!$B$30),1,0) -> 0 | BD15: =IF((AT15+AU15+AV15)>Inputs!$B$19,AW15/(AT15+AU15+AV15),1000000000) -> 1.093294 | BE15: =IF((J15+K15+L15)>0.000000001,(R15-I15-MAX(-M15,0))/(J15+K15+L15),1000000000) -> 1.6966816 | BF15: =IF(OR(BD15<Inputs!$B$34,BE15<Inputs!$B$35),1,0) -> 0 | BG15: =MAX(AZ15,BC15,BF15) -> 0 | BH15: =MIN(R15,N15) -> 165332.73 | BI15: =R15-BH15 -> 2246615.8 | BJ15: =MIN(BI15,O15) -> 930216.62 | BK15: =BI15-BJ15 -> 1316399.2 | BL15: =AZ15*MIN(AT15,BK15) -> 0 | BM15: =AZ15*MIN(AU15,BK15-BL15) -> 0 | BN15: =AZ15*MIN(AV15,BK15-BL15-BM15) -> 0 | BO15: =BK15-BL15-BM15-BN15 -> 1316399.2 | BP15: =MIN(BO15,P15) -> 206406.76 | BQ15: =BO15-BP15 -> 1109992.5 | BR15: =BC15*MIN((AT15-BL15),BQ15) -> 0 | BS15: =BC15*MIN((AU15-BM15),BQ15-BR15) -> 0 | BT15: =BC15*MIN((AV15-BN15),BQ15-BR15-BS15) -> 0 | BU15: =BQ15-BR15-BS15-BT15 -> 1109992.5 | BV15: =MIN(BU15,Q15) -> 187500 | BW15: =BU15-BV15 -> 922492.45 | BX15: =BF15*MIN((AT15-BL15-BR15),BW15) -> 0 | BY15: =BF15*MIN((AU15-BM15-BS15),BW15-BX15) -> 0 | BZ15: =BF15*MIN((AV15-BN15-BT15),BW15-BX15-BY15) -> 0 | CA15: =BW15-BX15-BY15-BZ15 -> 922492.45 | CB15: =MAX(0,AT15+AU15+AV15-BL15-BM15-BN15-BR15-BS15-BT15-BX15-BY15-BZ15-AW15) -> 0 | CC15: =1*MIN((AT15-BL15-BR15-BX15),MIN(CA15,CB15)) -> 0 | CD15: =1*MIN((AU15-BM15-BS15-BY15),MIN(CA15,CB15)-CC15) -> 0 | CE15: =1*MIN((AV15-BN15-BT15-BZ15),MIN(CA15,CB15)-CC15-CD15) -> 0 | CF15: =CA15-CC15-CD15-CE15 -> 922492.45 | CG15: =IF(C15+D15+E15>Inputs!$B$19,MIN(CF15,MAX(0,Inputs!$B$15-DO14)),0) -> 0 | CH15: =CF15-CG15 -> 922492.45 | CI15: =DO14+CG15 -> 3000000 | CJ15: =MIN(MAX(N15-BH15,0),CI15) -> 0 | CK15: =MIN(MAX(O15-BJ15,0),CI15-CJ15) -> 0 | CL15: =MIN(MAX(P15-BP15,0),CI15-CJ15-CK15) -> 0 | CM15: =CJ15+CK15+CL15 -> 0 | CN15: =CI15-CM15 -> 3000000 | CO15: =BH15+CJ15 -> 165332.73 | CP15: =BJ15+CK15 -> 930216.62 | CQ15: =BP15+CL15 -> 206406.76 | CR15: =BV15 -> 187500 | CS15: =AT15-BL15-BR15-BX15-CC15 -> 2.1279575e+08 | CT15: =AU15-BM15-BS15-BY15-CD15 -> 40000000 | CU15: =AV15-BN15-BT15-BZ15-CE15 -> 30000000 | CV15: =MAX(0,CS15+CT15+CU15-AW15) -> 0 | CW15: =MIN(CU15,CV15) -> 0 | CX15: =MIN(CT15,CV15-CW15) -> 0 | CY15: =MIN(CS15,CV15-CW15-CX15) -> 0 | CZ15: =IF(CS15-CY15<Inputs!$B$19,0,CS15-CY15) -> 2.1279575e+08 | DA15: =IF(CT15-CX15<Inputs!$B$19,0,CT15-CX15) -> 40000000 | DB15: =IF(CU15-CW15<Inputs!$B$19,0,CU15-CW15) -> 30000000 | DC15: =N15-CO15 -> 0 | DD15: =O15-CP15 -> 0 | DE15: =P15-CQ15 -> 0 | DF15: =Q15-CR15 -> 0 | DG15: =IF(CZ15+DA15+DB15<=Inputs!$B$19,1,0) -> 0 | DH15: =DG15*CN15 -> 0 | DI15: =DG15*(AS15+DH15) -> 0 | DJ15: =DG15*MIN(DC15,DI15) -> 0 | DK15: =DG15*MIN(DD15,DI15-DJ15) -> 0 | DL15: =DG15*MIN(DE15,DI15-DJ15-DK15) -> 0 | DM15: =DG15*MIN(DF15,DI15-DJ15-DK15-DL15) -> 0 | DN15: =DJ15+DK15+DL15+DM15 -> 0 | DO15: =CN15-DH15 -> 3000000 | DP15: =DC15-DJ15 -> 0 | DQ15: =DD15-DK15 -> 0 | DR15: =DE15-DL15 -> 0 | DS15: =DF15-DM15 -> 0 | DT15: =CO15+DJ15 -> 165332.73 | DU15: =CP15+DK15 -> 930216.62 | DV15: =AP15+BL15+BR15+BX15+CC15 -> 8587642.7 | DW15: =CQ15+DL15 -> 206406.76 | DX15: =AQ15+BM15+BS15+BY15+CD15 -> 0 | DY15: =CR15+DM15 -> 187500 | DZ15: =AR15+BN15+BT15+BZ15+CE15 -> 0 | EA15: =DI15-DN15 -> 0 | EB15: =CH15+EA15 -> 922492.45 | EC15: =R15-I15-MAX(-M15,0)-J15-K15-L15 -> 922492.45 | ED15: =R15+S15+CM15+DH15-CG15-DT15-DU15-DW15-DY15-DV15-DX15-DZ15-EB15 -> 0 | EE15: =IF(AND(EB15>0.000001,DP15+DQ15+DR15+DS15>0.000001),1,0) -> 0
A16: =ROW()-5 -> 11 | B16: =Inputs!$B$11+(Inputs!$B$12-Inputs!$B$11)*(1-EXP(-A16/Inputs!$B$13))+Inputs!$B$8 -> 0.039139535 | C16: =CZ15 -> 2.1279575e+08 | D16: =DA15 -> 40000000 | E16: =DB15 -> 30000000 | F16: =IF(Inputs!$B$22=1,B16+Inputs!$B$23,Inputs!$B$23)/12 -> 0.0041782946 | G16: =IF(Inputs!$B$27=1,B16+Inputs!$B$28,Inputs!$B$28)/12 -> 0.0051366279 | H16: =IF(Inputs!$B$32=1,B16+Inputs!$B$33,Inputs!$B$33)/12 -> 0.00625 | I16: =Pool!BT16*Inputs!$B$14/12 -> 160700.93 | J16: =C16*F16 -> 889123.34 | K16: =D16*G16 -> 205465.12 | L16: =E16*H16 -> 187500 | M16: =Inputs!$B$17*(C16*Inputs!$B$22+D16*Inputs!$B$27+E16*Inputs!$B$32)*(B16-Inputs!$B$18)/12 -> 0 | N16: =DP15+I16+MAX(-M16,0) -> 160700.93 | O16: =DQ15+J16 -> 889123.34 | P16: =DR15+K16 -> 205465.12 | Q16: =DS15+L16 -> 187500 | R16: =Pool!BV16+MAX(M16,0) -> 2346447.9 | S16: =Pool!BW16+Pool!BX16+Pool!BZ16 -> 8474763.6 | T16: =MAX(T15,BG15) -> 1 | U16: =MIN(C16,S16) -> 8474763.6 | V16: =MIN(D16,S16-U16) -> 0 | W16: =MIN(E16,S16-U16-V16) -> 0 | X16: =IF(C16-(0)>Inputs!$B$19,1,0) -> 1 | Y16: =IF(D16-(0)>Inputs!$B$19,1,0) -> 1 | Z16: =IF(E16-(0)>Inputs!$B$19,1,0) -> 1 | AA16: =IF((X16*C16+Y16*D16+Z16*E16)>0,MIN(C16-(0),S16*X16*C16/(X16*C16+Y16*D16+Z16*E16)),0) -> 6377018.3 | AB16: =IF((X16*C16+Y16*D16+Z16*E16)>0,MIN(D16-(0),S16*Y16*D16/(X16*C16+Y16*D16+Z16*E16)),0) -> 1198711.6 | AC16: =IF((X16*C16+Y16*D16+Z16*E16)>0,MIN(E16-(0),S16*Z16*E16/(X16*C16+Y16*D16+Z16*E16)),0) -> 899033.69 | AD16: =IF(C16-(AA16)>Inputs!$B$19,1,0) -> 1 | AE16: =IF(D16-(AB16)>Inputs!$B$19,1,0) -> 1 | AF16: =IF(E16-(AC16)>Inputs!$B$19,1,0) -> 1 | AG16: =IF((AD16*C16+AE16*D16+AF16*E16)>0,MIN(C16-(AA16),(S16-(AA16+AB16+AC16))*AD16*C16/(AD16*C16+AE16*D16+AF16*E16)),0) -> 0 | AH16: =IF((AD16*C16+AE16*D16+AF16*E16)>0,MIN(D16-(AB16),(S16-(AA16+AB16+AC16))*AE16*D16/(AD16*C16+AE16*D16+AF16*E16)),0) -> 0 | AI16: =IF((AD16*C16+AE16*D16+AF16*E16)>0,MIN(E16-(AC16),(S16-(AA16+AB16+AC16))*AF16*E16/(AD16*C16+AE16*D16+AF16*E16)),0) -> 0 | AJ16: =IF(C16-(AA16+AG16)>Inputs!$B$19,1,0) -> 1 | AK16: =IF(D16-(AB16+AH16)>Inputs!$B$19,1,0) -> 1 | AL16: =IF(E16-(AC16+AI16)>Inputs!$B$19,1,0) -> 1 | AM16: =IF((AJ16*C16+AK16*D16+AL16*E16)>0,MIN(C16-(AA16+AG16),(S16-(AA16+AB16+AC16+AG16+AH16+AI16))*AJ16*C16/(AJ16*C16+AK16*D16+AL16*E16)),0) -> 0 | AN16: =IF((AJ16*C16+AK16*D16+AL16*E16)>0,MIN(D16-(AB16+AH16),(S16-(AA16+AB16+AC16+AG16+AH16+AI16))*AK16*D16/(AJ16*C16+AK16*D16+AL16*E16)),0) -> 0 | AO16: =IF((AJ16*C16+AK16*D16+AL16*E16)>0,MIN(E16-(AC16+AI16),(S16-(AA16+AB16+AC16+AG16+AH16+AI16))*AL16*E16/(AJ16*C16+AK16*D16+AL16*E16)),0) -> 0 | AP16: =IF(T16=1,U16,AA16+AG16+AM16) -> 8474763.6 | AQ16: =IF(T16=1,V16,AB16+AH16+AN16) -> 0 | AR16: =IF(T16=1,W16,AC16+AI16+AO16) -> 0 | AS16: =S16-AP16-AQ16-AR16 -> 0 | AT16: =C16-AP16 -> 2.0432099e+08 | AU16: =D16-AQ16 -> 40000000 | AV16: =E16-AR16 -> 30000000 | AW16: =Pool!CB16 -> 3.0039374e+08 | AX16: =IF((AT16)>Inputs!$B$19,AW16/(AT16),1000000000) -> 1.470205 | AY16: =IF((J16)>0.000000001,(R16-I16-MAX(-M16,0))/(J16),1000000000) -> 2.4583169 | AZ16: =IF(OR(AX16<Inputs!$B$24,AY16<Inputs!$B$25),1,0) -> 0 | BA16: =IF((AT16+AU16)>Inputs!$B$19,AW16/(AT16+AU16),1000000000) -> 1.2295044 | BB16: =IF((J16+K16)>0.000000001,(R16-I16-MAX(-M16,0))/(J16+K16),1000000000) -> 1.9968665 | BC16: =IF(OR(BA16<Inputs!$B$29,BB16<Inputs!$B$30),1,0) -> 0 | BD16: =IF((AT16+AU16+AV16)>Inputs!$B$19,AW16/(AT16+AU16+AV16),1000000000) -> 1.0950447 | BE16: =IF((J16+K16+L16)>0.000000001,(R16-I16-MAX(-M16,0))/(J16+K16+L16),1000000000) -> 1.7048332 | BF16: =IF(OR(BD16<Inputs!$B$34,BE16<Inputs!$B$35),1,0) -> 0 | BG16: =MAX(AZ16,BC16,BF16) -> 0 | BH16: =MIN(R16,N16) -> 160700.93 | BI16: =R16-BH16 -> 2185747 | BJ16: =MIN(BI16,O16) -> 889123.34 | BK16: =BI16-BJ16 -> 1296623.6 | BL16: =AZ16*MIN(AT16,BK16) -> 0 | BM16: =AZ16*MIN(AU16,BK16-BL16) -> 0 | BN16: =AZ16*MIN(AV16,BK16-BL16-BM16) -> 0 | BO16: =BK16-BL16-BM16-BN16 -> 1296623.6 | BP16: =MIN(BO16,P16) -> 205465.12 | BQ16: =BO16-BP16 -> 1091158.5 | BR16: =BC16*MIN((AT16-BL16),BQ16) -> 0 | BS16: =BC16*MIN((AU16-BM16),BQ16-BR16) -> 0 | BT16: =BC16*MIN((AV16-BN16),BQ16-BR16-BS16) -> 0 | BU16: =BQ16-BR16-BS16-BT16 -> 1091158.5 | BV16: =MIN(BU16,Q16) -> 187500 | BW16: =BU16-BV16 -> 903658.51 | BX16: =BF16*MIN((AT16-BL16-BR16),BW16) -> 0 | BY16: =BF16*MIN((AU16-BM16-BS16),BW16-BX16) -> 0 | BZ16: =BF16*MIN((AV16-BN16-BT16),BW16-BX16-BY16) -> 0 | CA16: =BW16-BX16-BY16-BZ16 -> 903658.51 | CB16: =MAX(0,AT16+AU16+AV16-BL16-BM16-BN16-BR16-BS16-BT16-BX16-BY16-BZ16-AW16) -> 0 | CC16: =1*MIN((AT16-BL16-BR16-BX16),MIN(CA16,CB16)) -> 0 | CD16: =1*MIN((AU16-BM16-BS16-BY16),MIN(CA16,CB16)-CC16) -> 0 | CE16: =1*MIN((AV16-BN16-BT16-BZ16),MIN(CA16,CB16)-CC16-CD16) -> 0 | CF16: =CA16-CC16-CD16-CE16 -> 903658.51 | CG16: =IF(C16+D16+E16>Inputs!$B$19,MIN(CF16,MAX(0,Inputs!$B$15-DO15)),0) -> 0 | CH16: =CF16-CG16 -> 903658.51 | CI16: =DO15+CG16 -> 3000000 | CJ16: =MIN(MAX(N16-BH16,0),CI16) -> 0 | CK16: =MIN(MAX(O16-BJ16,0),CI16-CJ16) -> 0 | CL16: =MIN(MAX(P16-BP16,0),CI16-CJ16-CK16) -> 0 | CM16: =CJ16+CK16+CL16 -> 0 | CN16: =CI16-CM16 -> 3000000 | CO16: =BH16+CJ16 -> 160700.93 | CP16: =BJ16+CK16 -> 889123.34 | CQ16: =BP16+CL16 -> 205465.12 | CR16: =BV16 -> 187500 | CS16: =AT16-BL16-BR16-BX16-CC16 -> 2.0432099e+08 | CT16: =AU16-BM16-BS16-BY16-CD16 -> 40000000 | CU16: =AV16-BN16-BT16-BZ16-CE16 -> 30000000 | CV16: =MAX(0,CS16+CT16+CU16-AW16) -> 0 | CW16: =MIN(CU16,CV16) -> 0 | CX16: =MIN(CT16,CV16-CW16) -> 0 | CY16: =MIN(CS16,CV16-CW16-CX16) -> 0 | CZ16: =IF(CS16-CY16<Inputs!$B$19,0,CS16-CY16) -> 2.0432099e+08 | DA16: =IF(CT16-CX16<Inputs!$B$19,0,CT16-CX16) -> 40000000 | DB16: =IF(CU16-CW16<Inputs!$B$19,0,CU16-CW16) -> 30000000 | DC16: =N16-CO16 -> 0 | DD16: =O16-CP16 -> 0 | DE16: =P16-CQ16 -> 0 | DF16: =Q16-CR16 -> 0 | DG16: =IF(CZ16+DA16+DB16<=Inputs!$B$19,1,0) -> 0 | DH16: =DG16*CN16 -> 0 | DI16: =DG16*(AS16+DH16) -> 0 | DJ16: =DG16*MIN(DC16,DI16) -> 0 | DK16: =DG16*MIN(DD16,DI16-DJ16) -> 0 | DL16: =DG16*MIN(DE16,DI16-DJ16-DK16) -> 0 | DM16: =DG16*MIN(DF16,DI16-DJ16-DK16-DL16) -> 0 | DN16: =DJ16+DK16+DL16+DM16 -> 0 | DO16: =CN16-DH16 -> 3000000 | DP16: =DC16-DJ16 -> 0 | DQ16: =DD16-DK16 -> 0 | DR16: =DE16-DL16 -> 0 | DS16: =DF16-DM16 -> 0 | DT16: =CO16+DJ16 -> 160700.93 | DU16: =CP16+DK16 -> 889123.34 | DV16: =AP16+BL16+BR16+BX16+CC16 -> 8474763.6 | DW16: =CQ16+DL16 -> 205465.12 | DX16: =AQ16+BM16+BS16+BY16+CD16 -> 0 | DY16: =CR16+DM16 -> 187500 | DZ16: =AR16+BN16+BT16+BZ16+CE16 -> 0 | EA16: =DI16-DN16 -> 0 | EB16: =CH16+EA16 -> 903658.51 | EC16: =R16-I16-MAX(-M16,0)-J16-K16-L16 -> 903658.51 | ED16: =R16+S16+CM16+DH16-CG16-DT16-DU16-DW16-DY16-DV16-DX16-DZ16-EB16 -> 0 | EE16: =IF(AND(EB16>0.000001,DP16+DQ16+DR16+DS16>0.000001),1,0) -> 0
A17: =ROW()-5 -> 12 | B17: =Inputs!$B$11+(Inputs!$B$12-Inputs!$B$11)*(1-EXP(-A17/Inputs!$B$13))+Inputs!$B$8 -> 0.038868572 | C17: =CZ16 -> 2.0432099e+08 | D17: =DA16 -> 40000000 | E17: =DB16 -> 30000000 | F17: =IF(Inputs!$B$22=1,B17+Inputs!$B$23,Inputs!$B$23)/12 -> 0.0041557143 | G17: =IF(Inputs!$B$27=1,B17+Inputs!$B$28,Inputs!$B$28)/12 -> 0.0051140477 | H17: =IF(Inputs!$B$32=1,B17+Inputs!$B$33,Inputs!$B$33)/12 -> 0.00625 | I17: =Pool!BT17*Inputs!$B$14/12 -> 156132.48 | J17: =C17*F17 -> 849099.66 | K17: =D17*G17 -> 204561.91 | L17: =E17*H17 -> 187500 | M17: =Inputs!$B$17*(C17*Inputs!$B$22+D17*Inputs!$B$27+E17*Inputs!$B$32)*(B17-Inputs!$B$18)/12 -> 0 | N17: =DP16+I17+MAX(-M17,0) -> 156132.48 | O17: =DQ16+J17 -> 849099.66 | P17: =DR16+K17 -> 204561.91 | Q17: =DS16+L17 -> 187500 | R17: =Pool!BV17+MAX(M17,0) -> 2281834.7 | S17: =Pool!BW17+Pool!BX17+Pool!BZ17 -> 8363225.8 | T17: =MAX(T16,BG16) -> 1 | U17: =MIN(C17,S17) -> 8363225.8 | V17: =MIN(D17,S17-U17) -> 0 | W17: =MIN(E17,S17-U17-V17) -> 0 | X17: =IF(C17-(0)>Inputs!$B$19,1,0) -> 1 | Y17: =IF(D17-(0)>Inputs!$B$19,1,0) -> 1 | Z17: =IF(E17-(0)>Inputs!$B$19,1,0) -> 1 | AA17: =IF((X17*C17+Y17*D17+Z17*E17)>0,MIN(C17-(0),S17*X17*C17/(X17*C17+Y17*D17+Z17*E17)),0) -> 6229135.3 | AB17: =IF((X17*C17+Y17*D17+Z17*E17)>0,MIN(D17-(0),S17*Y17*D17/(X17*C17+Y17*D17+Z17*E17)),0) -> 1219480.3 | AC17: =IF((X17*C17+Y17*D17+Z17*E17)>0,MIN(E17-(0),S17*Z17*E17/(X17*C17+Y17*D17+Z17*E17)),0) -> 914610.19 | AD17: =IF(C17-(AA17)>Inputs!$B$19,1,0) -> 1 | AE17: =IF(D17-(AB17)>Inputs!$B$19,1,0) -> 1 | AF17: =IF(E17-(AC17)>Inputs!$B$19,1,0) -> 1 | AG17: =IF((AD17*C17+AE17*D17+AF17*E17)>0,MIN(C17-(AA17),(S17-(AA17+AB17+AC17))*AD17*C17/(AD17*C17+AE17*D17+AF17*E17)),0) -> 0 | AH17: =IF((AD17*C17+AE17*D17+AF17*E17)>0,MIN(D17-(AB17),(S17-(AA17+AB17+AC17))*AE17*D17/(AD17*C17+AE17*D17+AF17*E17)),0) -> 0 | AI17: =IF((AD17*C17+AE17*D17+AF17*E17)>0,MIN(E17-(AC17),(S17-(AA17+AB17+AC17))*AF17*E17/(AD17*C17+AE17*D17+AF17*E17)),0) -> 0 | AJ17: =IF(C17-(AA17+AG17)>Inputs!$B$19,1,0) -> 1 | AK17: =IF(D17-(AB17+AH17)>Inputs!$B$19,1,0) -> 1 | AL17: =IF(E17-(AC17+AI17)>Inputs!$B$19,1,0) -> 1 | AM17: =IF((AJ17*C17+AK17*D17+AL17*E17)>0,MIN(C17-(AA17+AG17),(S17-(AA17+AB17+AC17+AG17+AH17+AI17))*AJ17*C17/(AJ17*C17+AK17*D17+AL17*E17)),0) -> 0 | AN17: =IF((AJ17*C17+AK17*D17+AL17*E17)>0,MIN(D17-(AB17+AH17),(S17-(AA17+AB17+AC17+AG17+AH17+AI17))*AK17*D17/(AJ17*C17+AK17*D17+AL17*E17)),0) -> 0 | AO17: =IF((AJ17*C17+AK17*D17+AL17*E17)>0,MIN(E17-(AC17+AI17),(S17-(AA17+AB17+AC17+AG17+AH17+AI17))*AL17*E17/(AJ17*C17+AK17*D17+AL17*E17)),0) -> 0 | AP17: =IF(T17=1,U17,AA17+AG17+AM17) -> 8363225.8 | AQ17: =IF(T17=1,V17,AB17+AH17+AN17) -> 0 | AR17: =IF(T17=1,W17,AC17+AI17+AO17) -> 0 | AS17: =S17-AP17-AQ17-AR17 -> 0 | AT17: =C17-AP17 -> 1.9595776e+08 | AU17: =D17-AQ17 -> 40000000 | AV17: =E17-AR17 -> 30000000 | AW17: =Pool!CB17 -> 2.9172895e+08 | AX17: =IF((AT17)>Inputs!$B$19,AW17/(AT17),1000000000) -> 1.4887338 | AY17: =IF((J17)>0.000000001,(R17-I17-MAX(-M17,0))/(J17),1000000000) -> 2.5034778 | AZ17: =IF(OR(AX17<Inputs!$B$24,AY17<Inputs!$B$25),1,0) -> 0 | BA17: =IF((AT17+AU17)>Inputs!$B$19,AW17/(AT17+AU17),1000000000) -> 1.2363609 | BB17: =IF((J17+K17)>0.000000001,(R17-I17-MAX(-M17,0))/(J17+K17),1000000000) -> 2.017443 | BC17: =IF(OR(BA17<Inputs!$B$29,BB17<Inputs!$B$30),1,0) -> 0 | BD17: =IF((AT17+AU17+AV17)>Inputs!$B$19,AW17/(AT17+AU17+AV17),1000000000) -> 1.0968995 | BE17: =IF((J17+K17+L17)>0.000000001,(R17-I17-MAX(-M17,0))/(J17+K17+L17),1000000000) -> 1.7126716 | BF17: =IF(OR(BD17<Inputs!$B$34,BE17<Inputs!$B$35),1,0) -> 0 | BG17: =MAX(AZ17,BC17,BF17) -> 0 | BH17: =MIN(R17,N17) -> 156132.48 | BI17: =R17-BH17 -> 2125702.2 | BJ17: =MIN(BI17,O17) -> 849099.66 | BK17: =BI17-BJ17 -> 1276602.5 | BL17: =AZ17*MIN(AT17,BK17) -> 0 | BM17: =AZ17*MIN(AU17,BK17-BL17) -> 0 | BN17: =AZ17*MIN(AV17,BK17-BL17-BM17) -> 0 | BO17: =BK17-BL17-BM17-BN17 -> 1276602.5 | BP17: =MIN(BO17,P17) -> 204561.91 | BQ17: =BO17-BP17 -> 1072040.6 | BR17: =BC17*MIN((AT17-BL17),BQ17) -> 0 | BS17: =BC17*MIN((AU17-BM17),BQ17-BR17) -> 0 | BT17: =BC17*MIN((AV17-BN17),BQ17-BR17-BS17) -> 0 | BU17: =BQ17-BR17-BS17-BT17 -> 1072040.6 | BV17: =MIN(BU17,Q17) -> 187500 | BW17: =BU17-BV17 -> 884540.62 | BX17: =BF17*MIN((AT17-BL17-BR17),BW17) -> 0 | BY17: =BF17*MIN((AU17-BM17-BS17),BW17-BX17) -> 0 | BZ17: =BF17*MIN((AV17-BN17-BT17),BW17-BX17-BY17) -> 0 | CA17: =BW17-BX17-BY17-BZ17 -> 884540.62 | CB17: =MAX(0,AT17+AU17+AV17-BL17-BM17-BN17-BR17-BS17-BT17-BX17-BY17-BZ17-AW17) -> 0 | CC17: =1*MIN((AT17-BL17-BR17-BX17),MIN(CA17,CB17)) -> 0 | CD17: =1*MIN((AU17-BM17-BS17-BY17),MIN(CA17,CB17)-CC17) -> 0 | CE17: =1*MIN((AV17-BN17-BT17-BZ17),MIN(CA17,CB17)-CC17-CD17) -> 0 | CF17: =CA17-CC17-CD17-CE17 -> 884540.62 | CG17: =IF(C17+D17+E17>Inputs!$B$19,MIN(CF17,MAX(0,Inputs!$B$15-DO16)),0) -> 0 | CH17: =CF17-CG17 -> 884540.62 | CI17: =DO16+CG17 -> 3000000 | CJ17: =MIN(MAX(N17-BH17,0),CI17) -> 0 | CK17: =MIN(MAX(O17-BJ17,0),CI17-CJ17) -> 0 | CL17: =MIN(MAX(P17-BP17,0),CI17-CJ17-CK17) -> 0 | CM17: =CJ17+CK17+CL17 -> 0 | CN17: =CI17-CM17 -> 3000000 | CO17: =BH17+CJ17 -> 156132.48 | CP17: =BJ17+CK17 -> 849099.66 | CQ17: =BP17+CL17 -> 204561.91 | CR17: =BV17 -> 187500 | CS17: =AT17-BL17-BR17-BX17-CC17 -> 1.9595776e+08 | CT17: =AU17-BM17-BS17-BY17-CD17 -> 40000000 | CU17: =AV17-BN17-BT17-BZ17-CE17 -> 30000000 | CV17: =MAX(0,CS17+CT17+CU17-AW17) -> 0 | CW17: =MIN(CU17,CV17) -> 0 | CX17: =MIN(CT17,CV17-CW17) -> 0 | CY17: =MIN(CS17,CV17-CW17-CX17) -> 0 | CZ17: =IF(CS17-CY17<Inputs!$B$19,0,CS17-CY17) -> 1.9595776e+08 | DA17: =IF(CT17-CX17<Inputs!$B$19,0,CT17-CX17) -> 40000000 | DB17: =IF(CU17-CW17<Inputs!$B$19,0,CU17-CW17) -> 30000000 | DC17: =N17-CO17 -> 0 | DD17: =O17-CP17 -> 0 | DE17: =P17-CQ17 -> 0 | DF17: =Q17-CR17 -> 0 | DG17: =IF(CZ17+DA17+DB17<=Inputs!$B$19,1,0) -> 0 | DH17: =DG17*CN17 -> 0 | DI17: =DG17*(AS17+DH17) -> 0 | DJ17: =DG17*MIN(DC17,DI17) -> 0 | DK17: =DG17*MIN(DD17,DI17-DJ17) -> 0 | DL17: =DG17*MIN(DE17,DI17-DJ17-DK17) -> 0 | DM17: =DG17*MIN(DF17,DI17-DJ17-DK17-DL17) -> 0 | DN17: =DJ17+DK17+DL17+DM17 -> 0 | DO17: =CN17-DH17 -> 3000000 | DP17: =DC17-DJ17 -> 0 | DQ17: =DD17-DK17 -> 0 | DR17: =DE17-DL17 -> 0 | DS17: =DF17-DM17 -> 0 | DT17: =CO17+DJ17 -> 156132.48 | DU17: =CP17+DK17 -> 849099.66 | DV17: =AP17+BL17+BR17+BX17+CC17 -> 8363225.8 | DW17: =CQ17+DL17 -> 204561.91 | DX17: =AQ17+BM17+BS17+BY17+CD17 -> 0 | DY17: =CR17+DM17 -> 187500 | DZ17: =AR17+BN17+BT17+BZ17+CE17 -> 0 | EA17: =DI17-DN17 -> 0 | EB17: =CH17+EA17 -> 884540.62 | EC17: =R17-I17-MAX(-M17,0)-J17-K17-L17 -> 884540.62 | ED17: =R17+S17+CM17+DH17-CG17-DT17-DU17-DW17-DY17-DV17-DX17-DZ17-EB17 -> 0 | EE17: =IF(AND(EB17>0.000001,DP17+DQ17+DR17+DS17>0.000001),1,0) -> 0
... A125: =ROW()-5 -> 120 | B125: =Inputs!$B$11+(Inputs!$B$12-Inputs!$B$11)*(1-EXP(-A125/Inputs!$B$13))+Inputs!$B$8 -> 0.032570748 | C125: =CZ124 -> 0 | D125: =DA124 -> 0 | E125: =DB124 -> 0 | F125: =IF(Inputs!$B$22=1,B125+Inputs!$B$23,Inputs!$B$23)/12 -> 0.0036308957 | G125: =IF(Inputs!$B$27=1,B125+Inputs!$B$28,Inputs!$B$28)/12 -> 0.004589229 | H125: =IF(Inputs!$B$32=1,B125+Inputs!$B$33,Inputs!$B$33)/12 -> 0.00625 | I125: =Pool!BT125*Inputs!$B$14/12 -> 0 | J125: =C125*F125 -> 0 | K125: =D125*G125 -> 0 | L125: =E125*H125 -> 0 | M125: =Inputs!$B$17*(C125*Inputs!$B$22+D125*Inputs!$B$27+E125*Inputs!$B$32)*(B125-Inputs!$B$18)/12 -> 0 | N125: =DP124+I125+MAX(-M125,0) -> 0 | O125: =DQ124+J125 -> 0 | P125: =DR124+K125 -> 0 | Q125: =DS124+L125 -> 0 | R125: =Pool!BV125+MAX(M125,0) -> 0 | S125: =Pool!BW125+Pool!BX125+Pool!BZ125 -> 0 | T125: =MAX(T124,BG124) -> 1 | U125: =MIN(C125,S125) -> 0 | V125: =MIN(D125,S125-U125) -> 0 | W125: =MIN(E125,S125-U125-V125) -> 0 | X125: =IF(C125-(0)>Inputs!$B$19,1,0) -> 0 | Y125: =IF(D125-(0)>Inputs!$B$19,1,0) -> 0 | Z125: =IF(E125-(0)>Inputs!$B$19,1,0) -> 0 | AA125: =IF((X125*C125+Y125*D125+Z125*E125)>0,MIN(C125-(0),S125*X125*C125/(X125*C125+Y125*D125+Z125*E125)),0) -> 0 | AB125: =IF((X125*C125+Y125*D125+Z125*E125)>0,MIN(D125-(0),S125*Y125*D125/(X125*C125+Y125*D125+Z125*E125)),0) -> 0 | AC125: =IF((X125*C125+Y125*D125+Z125*E125)>0,MIN(E125-(0),S125*Z125*E125/(X125*C125+Y125*D125+Z125*E125)),0) -> 0 | AD125: =IF(C125-(AA125)>Inputs!$B$19,1,0) -> 0 | AE125: =IF(D125-(AB125)>Inputs!$B$19,1,0) -> 0 | AF125: =IF(E125-(AC125)>Inputs!$B$19,1,0) -> 0 | AG125: =IF((AD125*C125+AE125*D125+AF125*E125)>0,MIN(C125-(AA125),(S125-(AA125+AB125+AC125))*AD125*C125/(AD125*C125+AE125*D125+AF125*E125)),0) -> 0 | AH125: =IF((AD125*C125+AE125*D125+AF125*E125)>0,MIN(D125-(AB125),(S125-(AA125+AB125+AC125))*AE125*D125/(AD125*C125+AE125*D125+AF125*E125)),0) -> 0 | AI125: =IF((AD125*C125+AE125*D125+AF125*E125)>0,MIN(E125-(AC125),(S125-(AA125+AB125+AC125))*AF125*E125/(AD125*C125+AE125*D125+AF125*E125)),0) -> 0 | AJ125: =IF(C125-(AA125+AG125)>Inputs!$B$19,1,0) -> 0 | AK125: =IF(D125-(AB125+AH125)>Inputs!$B$19,1,0) -> 0 | AL125: =IF(E125-(AC125+AI125)>Inputs!$B$19,1,0) -> 0 | AM125: =IF((AJ125*C125+AK125*D125+AL125*E125)>0,MIN(C125-(AA125+AG125),(S125-(AA125+AB125+AC125+AG125+AH125+AI125))*AJ125*C125/(AJ125*C125+AK125*D125+AL125*E125)),0) -> 0 | AN125: =IF((AJ125*C125+AK125*D125+AL125*E125)>0,MIN(D125-(AB125+AH125),(S125-(AA125+AB125+AC125+AG125+AH125+AI125))*AK125*D125/(AJ125*C125+AK125*D125+AL125*E125)),0) -> 0 | AO125: =IF((AJ125*C125+AK125*D125+AL125*E125)>0,MIN(E125-(AC125+AI125),(S125-(AA125+AB125+AC125+AG125+AH125+AI125))*AL125*E125/(AJ125*C125+AK125*D125+AL125*E125)),0) -> 0 | AP125: =IF(T125=1,U125,AA125+AG125+AM125) -> 0 | AQ125: =IF(T125=1,V125,AB125+AH125+AN125) -> 0 | AR125: =IF(T125=1,W125,AC125+AI125+AO125) -> 0 | AS125: =S125-AP125-AQ125-AR125 -> 0 | AT125: =C125-AP125 -> 0 | AU125: =D125-AQ125 -> 0 | AV125: =E125-AR125 -> 0 | AW125: =Pool!CB125 -> -1.0697931e-10 | AX125: =IF((AT125)>Inputs!$B$19,AW125/(AT125),1000000000) -> 1000000000 | AY125: =IF((J125)>0.000000001,(R125-I125-MAX(-M125,0))/(J125),1000000000) -> 1000000000 | AZ125: =IF(OR(AX125<Inputs!$B$24,AY125<Inputs!$B$25),1,0) -> 0 | BA125: =IF((AT125+AU125)>Inputs!$B$19,AW125/(AT125+AU125),1000000000) -> 1000000000 | BB125: =IF((J125+K125)>0.000000001,(R125-I125-MAX(-M125,0))/(J125+K125),1000000000) -> 1000000000 | BC125: =IF(OR(BA125<Inputs!$B$29,BB125<Inputs!$B$30),1,0) -> 0 | BD125: =IF((AT125+AU125+AV125)>Inputs!$B$19,AW125/(AT125+AU125+AV125),1000000000) -> 1000000000 | BE125: =IF((J125+K125+L125)>0.000000001,(R125-I125-MAX(-M125,0))/(J125+K125+L125),1000000000) -> 1000000000 | BF125: =IF(OR(BD125<Inputs!$B$34,BE125<Inputs!$B$35),1,0) -> 0 | BG125: =MAX(AZ125,BC125,BF125) -> 0 | BH125: =MIN(R125,N125) -> 0 | BI125: =R125-BH125 -> 0 | BJ125: =MIN(BI125,O125) -> 0 | BK125: =BI125-BJ125 -> 0 | BL125: =AZ125*MIN(AT125,BK125) -> 0 | BM125: =AZ125*MIN(AU125,BK125-BL125) -> 0 | BN125: =AZ125*MIN(AV125,BK125-BL125-BM125) -> 0 | BO125: =BK125-BL125-BM125-BN125 -> 0 | BP125: =MIN(BO125,P125) -> 0 | BQ125: =BO125-BP125 -> 0 | BR125: =BC125*MIN((AT125-BL125),BQ125) -> 0 | BS125: =BC125*MIN((AU125-BM125),BQ125-BR125) -> 0 | BT125: =BC125*MIN((AV125-BN125),BQ125-BR125-BS125) -> 0 | BU125: =BQ125-BR125-BS125-BT125 -> 0 | BV125: =MIN(BU125,Q125) -> 0 | BW125: =BU125-BV125 -> 0 | BX125: =BF125*MIN((AT125-BL125-BR125),BW125) -> 0 | BY125: =BF125*MIN((AU125-BM125-BS125),BW125-BX125) -> 0 | BZ125: =BF125*MIN((AV125-BN125-BT125),BW125-BX125-BY125) -> 0 | CA125: =BW125-BX125-BY125-BZ125 -> 0 | CB125: =MAX(0,AT125+AU125+AV125-BL125-BM125-BN125-BR125-BS125-BT125-BX125-BY125-BZ125-AW125) -> 1.0697931e-10 | CC125: =1*MIN((AT125-BL125-BR125-BX125),MIN(CA125,CB125)) -> 0 | CD125: =1*MIN((AU125-BM125-BS125-BY125),MIN(CA125,CB125)-CC125) -> 0 | CE125: =1*MIN((AV125-BN125-BT125-BZ125),MIN(CA125,CB125)-CC125-CD125) -> 0 | CF125: =CA125-CC125-CD125-CE125 -> 0 | CG125: =IF(C125+D125+E125>Inputs!$B$19,MIN(CF125,MAX(0,Inputs!$B$15-DO124)),0) -> 0 | CH125: =CF125-CG125 -> 0 | CI125: =DO124+CG125 -> 0 | CJ125: =MIN(MAX(N125-BH125,0),CI125) -> 0 | CK125: =MIN(MAX(O125-BJ125,0),CI125-CJ125) -> 0 | CL125: =MIN(MAX(P125-BP125,0),CI125-CJ125-CK125) -> 0 | CM125: =CJ125+CK125+CL125 -> 0 | CN125: =CI125-CM125 -> 0 | CO125: =BH125+CJ125 -> 0 | CP125: =BJ125+CK125 -> 0 | CQ125: =BP125+CL125 -> 0 | CR125: =BV125 -> 0 | CS125: =AT125-BL125-BR125-BX125-CC125 -> 0 | CT125: =AU125-BM125-BS125-BY125-CD125 -> 0 | CU125: =AV125-BN125-BT125-BZ125-CE125 -> 0 | CV125: =MAX(0,CS125+CT125+CU125-AW125) -> 1.0697931e-10 | CW125: =MIN(CU125,CV125) -> 0 | CX125: =MIN(CT125,CV125-CW125) -> 0 | CY125: =MIN(CS125,CV125-CW125-CX125) -> 0 | CZ125: =IF(CS125-CY125<Inputs!$B$19,0,CS125-CY125) -> 0 | DA125: =IF(CT125-CX125<Inputs!$B$19,0,CT125-CX125) -> 0 | DB125: =IF(CU125-CW125<Inputs!$B$19,0,CU125-CW125) -> 0 | DC125: =N125-CO125 -> 0 | DD125: =O125-CP125 -> 0 | DE125: =P125-CQ125 -> 0 | DF125: =Q125-CR125 -> 0 | DG125: =IF(CZ125+DA125+DB125<=Inputs!$B$19,1,0) -> 1 | DH125: =DG125*CN125 -> 0 | DI125: =DG125*(AS125+DH125) -> 0 | DJ125: =DG125*MIN(DC125,DI125) -> 0 | DK125: =DG125*MIN(DD125,DI125-DJ125) -> 0 | DL125: =DG125*MIN(DE125,DI125-DJ125-DK125) -> 0 | DM125: =DG125*MIN(DF125,DI125-DJ125-DK125-DL125) -> 0 | DN125: =DJ125+DK125+DL125+DM125 -> 0 | DO125: =CN125-DH125 -> 0 | DP125: =DC125-DJ125 -> 0 | DQ125: =DD125-DK125 -> 0 | DR125: =DE125-DL125 -> 0 | DS125: =DF125-DM125 -> 0 | DT125: =CO125+DJ125 -> 0 | DU125: =CP125+DK125 -> 0 | DV125: =AP125+BL125+BR125+BX125+CC125 -> 0 | DW125: =CQ125+DL125 -> 0 | DX125: =AQ125+BM125+BS125+BY125+CD125 -> 0 | DY125: =CR125+DM125 -> 0 | DZ125: =AR125+BN125+BT125+BZ125+CE125 -> 0 | EA125: =DI125-DN125 -> 0 | EB125: =CH125+EA125 -> 0 | EC125: =R125-I125-MAX(-M125,0)-J125-K125-L125 -> 0 | ED125: =R125+S125+CM125+DH125-CG125-DT125-DU125-DW125-DY125-DV125-DX125-DZ125-EB125 -> 0 | EE125: =IF(AND(EB125>0.000001,DP125+DQ125+DR125+DS125>0.000001),1,0) -> 0

Sheet CashFlows
A4: Period | B4: cf_A | C4: cf_B | D4: cf_C | E4: cf_R
B5: =-Inputs!$B$21 -> -300000000 | C5: =-Inputs!$B$26 -> -40000000 | D5: =-Inputs!$B$31 -> -30000000 | E5: =-Inputs!$B$37 -> -33000000
A6: =ROW()-5 -> 1 | B6: =Waterfall!DU6+Waterfall!DV6 -> 10301935 | C6: =Waterfall!DW6+Waterfall!DX6 -> 216904.96 | D6: =Waterfall!DY6+Waterfall!DZ6 -> 187500 | E6: =Waterfall!EB6 -> 1089511
A7: =ROW()-5 -> 2 | B7: =Waterfall!DU7+Waterfall!DV7 -> 10142736 | C7: =Waterfall!DW7+Waterfall!DX7 -> 215534.89 | D7: =Waterfall!DY7+Waterfall!DZ7 -> 187500 | E7: =Waterfall!EB7 -> 1072113.1
A8: =ROW()-5 -> 3 | B8: =Waterfall!DU8+Waterfall!DV8 -> 9986293.1 | C8: =Waterfall!DW8+Waterfall!DX8 -> 214220.72 | D8: =Waterfall!DY8+Waterfall!DZ8 -> 187500 | E8: =Waterfall!EB8 -> 1054088.9
A9: =ROW()-5 -> 4 | B9: =Waterfall!DU9+Waterfall!DV9 -> 9832524.1 | C9: =Waterfall!DW9+Waterfall!DX9 -> 212960.19 | D9: =Waterfall!DY9+Waterfall!DZ9 -> 187500 | E9: =Waterfall!EB9 -> 1035498.6
A10: =ROW()-5 -> 5 | B10: =Waterfall!DU10+Waterfall!DV10 -> 9681348.8 | C10: =Waterfall!DW10+Waterfall!DX10 -> 211751.11 | D10: =Waterfall!DY10+Waterfall!DZ10 -> 187500 | E10: =Waterfall!EB10 -> 1016399.1
A11: =ROW()-5 -> 6 | B11: =Waterfall!DU11+Waterfall!DV11 -> 9532691.4 | C11: =Waterfall!DW11+Waterfall!DX11 -> 210591.36 | D11: =Waterfall!DY11+Waterfall!DZ11 -> 187500 | E11: =Waterfall!EB11 -> 996843.55
A12: =ROW()-5 -> 7 | B12: =Waterfall!DU12+Waterfall!DV12 -> 9994891 | C12: =Waterfall!DW12+Waterfall!DX12 -> 209478.95 | D12: =Waterfall!DY12+Waterfall!DZ12 -> 187500 | E12: =Waterfall!EB12 -> 976881.82
A13: =ROW()-5 -> 8 | B13: =Waterfall!DU13+Waterfall!DV13 -> 9833293.5 | C13: =Waterfall!DW13+Waterfall!DX13 -> 208411.93 | D13: =Waterfall!DY13+Waterfall!DZ13 -> 187500 | E13: =Waterfall!EB13 -> 959147.72
A14: =ROW()-5 -> 9 | B14: =Waterfall!DU14+Waterfall!DV14 -> 9674306.1 | C14: =Waterfall!DW14+Waterfall!DX14 -> 207388.46 | D14: =Waterfall!DY14+Waterfall!DZ14 -> 187500 | E14: =Waterfall!EB14 -> 941002.92
A15: =ROW()-5 -> 10 | B15: =Waterfall!DU15+Waterfall!DV15 -> 9517859.4 | C15: =Waterfall!DW15+Waterfall!DX15 -> 206406.76 | D15: =Waterfall!DY15+Waterfall!DZ15 -> 187500 | E15: =Waterfall!EB15 -> 922492.45
A16: =ROW()-5 -> 11 | B16: =Waterfall!DU16+Waterfall!DV16 -> 9363887 | C16: =Waterfall!DW16+Waterfall!DX16 -> 205465.12 | D16: =Waterfall!DY16+Waterfall!DZ16 -> 187500 | E16: =Waterfall!EB16 -> 903658.51
A17: =ROW()-5 -> 12 | B17: =Waterfall!DU17+Waterfall!DV17 -> 9212325.4 | C17: =Waterfall!DW17+Waterfall!DX17 -> 204561.91 | D17: =Waterfall!DY17+Waterfall!DZ17 -> 187500 | E17: =Waterfall!EB17 -> 884540.62
... A125: =ROW()-5 -> 120 | B125: =Waterfall!DU125+Waterfall!DV125 -> 0 | C125: =Waterfall!DW125+Waterfall!DX125 -> 0 | D125: =Waterfall!DY125+Waterfall!DZ125 -> 0 | E125: =Waterfall!EB125 -> 0

Sheet Scenario_Summary
A1: Tranche summary for the selected scenario (Python-only: break-even CDR, discount margin, retention)
A3: Class | B3: Par | C3: WAL (yrs) | D3: Yield at par | E3: First principal month | F3: Last principal month | G3: Interest paid | H3: Cash received | I3: Write-down | J3: Unpaid interest end | K3: Unpaid interest peak | L3: Any shortfall
A4: A | B4: =Inputs!$B$21 -> 300000000 | C4: =IF(SUM(Waterfall!$DV$6:$DV$125)>0,SUMPRODUCT(Waterfall!$A$6:$A$125,Waterfall!$DV$6:$DV$125)/12/SUM(Waterfall!$DV$6:$DV$125),"n/a") -> 1.59225 | D4: =IF(SUM(CashFlows!$B$6:$B$125)>0,IFERROR(IRR(CashFlows!$B$5:$B$125,0.005),IFERROR(IRR(CashFlows!$B$5:$B$125,-0.03),IFERROR(IRR(CashFlows!$B$5:$B$125,-0.1),IFERROR(IRR(CashFlows!$B$5:$B$125,-0.3),IRR(CashFlows!$B$5:$B$125,-0.6)))))*12,"n/a") -> 0.049997788 | E4: =IFERROR(minifs(Waterfall!$A$6:$A$125,Waterfall!$DV$6:$DV$125,">1"),"n/a") -> #VALUE! | F4: =IFERROR(maxifs(Waterfall!$A$6:$A$125,Waterfall!$DV$6:$DV$125,">1"),"n/a") -> #VALUE! | G4: =SUM(Waterfall!$DU$6:$DU$125) -> 23841743 | H4: =SUM(CashFlows!$B$6:$B$125) -> 3.2384174e+08 | I4: =SUM(Waterfall!$CY$6:$CY$125) -> 0 | J4: =Waterfall!DQ125 -> 0 | K4: =MAX(Waterfall!$DQ$6:$DQ$125) -> 0 | L4: =IF(OR(I4>Inputs!$B$20,J4>Inputs!$B$20,K4>Inputs!$B$20),1,0) -> 0
A5: B | B5: =Inputs!$B$26 -> 40000000 | C5: =IF(SUM(Waterfall!$DX$6:$DX$125)>0,SUMPRODUCT(Waterfall!$A$6:$A$125,Waterfall!$DX$6:$DX$125)/12/SUM(Waterfall!$DX$6:$DX$125),"n/a") -> 3.8275015 | D5: =IF(SUM(CashFlows!$C$6:$C$125)>0,IFERROR(IRR(CashFlows!$C$5:$C$125,0.005),IFERROR(IRR(CashFlows!$C$5:$C$125,-0.03),IFERROR(IRR(CashFlows!$C$5:$C$125,-0.1),IFERROR(IRR(CashFlows!$C$5:$C$125,-0.3),IRR(CashFlows!$C$5:$C$125,-0.6)))))*12,"n/a") -> 0.05973537 | E5: =IFERROR(minifs(Waterfall!$A$6:$A$125,Waterfall!$DX$6:$DX$125,">1"),"n/a") -> #VALUE! | F5: =IFERROR(maxifs(Waterfall!$A$6:$A$125,Waterfall!$DX$6:$DX$125,">1"),"n/a") -> #VALUE! | G5: =SUM(Waterfall!$DW$6:$DW$125) -> 9121028.4 | H5: =SUM(CashFlows!$C$6:$C$125) -> 49121028 | I5: =SUM(Waterfall!$CX$6:$CX$125) -> 0 | J5: =Waterfall!DR125 -> 0 | K5: =MAX(Waterfall!$DR$6:$DR$125) -> 0 | L5: =IF(OR(I5>Inputs!$B$20,J5>Inputs!$B$20,K5>Inputs!$B$20),1,0) -> 0
A6: C | B6: =Inputs!$B$31 -> 30000000 | C6: =IF(SUM(Waterfall!$DZ$6:$DZ$125)>0,SUMPRODUCT(Waterfall!$A$6:$A$125,Waterfall!$DZ$6:$DZ$125)/12/SUM(Waterfall!$DZ$6:$DZ$125),"n/a") -> 4.7131884 | D6: =IF(SUM(CashFlows!$D$6:$D$125)>0,IFERROR(IRR(CashFlows!$D$5:$D$125,0.005),IFERROR(IRR(CashFlows!$D$5:$D$125,-0.03),IFERROR(IRR(CashFlows!$D$5:$D$125,-0.1),IFERROR(IRR(CashFlows!$D$5:$D$125,-0.3),IRR(CashFlows!$D$5:$D$125,-0.6)))))*12,"n/a") -> 0.075 | E6: =IFERROR(minifs(Waterfall!$A$6:$A$125,Waterfall!$DZ$6:$DZ$125,">1"),"n/a") -> #VALUE! | F6: =IFERROR(maxifs(Waterfall!$A$6:$A$125,Waterfall!$DZ$6:$DZ$125,">1"),"n/a") -> #VALUE! | G6: =SUM(Waterfall!$DY$6:$DY$125) -> 10604674 | H6: =SUM(CashFlows!$D$6:$D$125) -> 40604674 | I6: =SUM(Waterfall!$CW$6:$CW$125) -> 0 | J6: =Waterfall!DS125 -> 0 | K6: =MAX(Waterfall!$DS$6:$DS$125) -> 0 | L6: =IF(OR(I6>Inputs!$B$20,J6>Inputs!$B$20,K6>Inputs!$B$20),1,0) -> 0
A7: R | B7: =Inputs!$B$37 -> 33000000 | C7: =IF(SUM(Waterfall!$EA$6:$EA$125)>0,SUMPRODUCT(Waterfall!$A$6:$A$125,Waterfall!$EA$6:$EA$125)/12/SUM(Waterfall!$EA$6:$EA$125),"n/a") -> 5.8843146 | D7: =IF(SUM(CashFlows!$E$6:$E$125)>0,IFERROR(IRR(CashFlows!$E$5:$E$125,0.005),IFERROR(IRR(CashFlows!$E$5:$E$125,-0.03),IFERROR(IRR(CashFlows!$E$5:$E$125,-0.1),IFERROR(IRR(CashFlows!$E$5:$E$125,-0.3),IRR(CashFlows!$E$5:$E$125,-0.6)))))*12,"n/a") -> 0.18161657 | E7: =IFERROR(minifs(Waterfall!$A$6:$A$125,Waterfall!$EA$6:$EA$125,">1"),"n/a") -> #VALUE! | F7: =IFERROR(maxifs(Waterfall!$A$6:$A$125,Waterfall!$EA$6:$EA$125,">1"),"n/a") -> #VALUE! | G7: 0 | H7: =SUM(CashFlows!$E$6:$E$125) -> 57063658 | I7: =MAX(B7-H7,0) -> 0 | J7: 0 | K7: 0 | L7: =IF(OR(I7>Inputs!$B$20,J7>Inputs!$B$20,K7>Inputs!$B$20),1,0) -> 0
A10: Junior-most class with a write-down | B10: =IF(I7>Inputs!$B$20,"R",IF(I6>Inputs!$B$20,"C",IF(I5>Inputs!$B$20,"B",IF(I4>Inputs!$B$20,"A","none")))) -> none
A11: Most senior class with a write-down | B11: =IF(I4>Inputs!$B$20,"A",IF(I5>Inputs!$B$20,"B",IF(I6>Inputs!$B$20,"C",IF(I7>Inputs!$B$20,"R","none")))) -> none
A12: Cumulative net loss, % of original pool | B12: =Pool!CD125/Inputs!$B$36 -> 0.027284733
A14: Integrity checks
A15: Max abs cash conservation gap | B15: =MAX(MAX(Waterfall!$ED$6:$ED$125),-MIN(Waterfall!$ED$6:$ED$125)) -> 1.3969839e-09
A16: Periods with residual paid while arrears remain | B16: =SUM(Waterfall!$EE$6:$EE$125) -> 0
A17: Months with any test breach | B17: =SUM(Waterfall!$BG$6:$BG$125) -> 0
A18: Max abs pool roll-forward difference (ending pool balance at horizon) | B18: =ABS(Pool!BY125) -> 0
A19: All checks pass (1 = yes) | B19: =IF(AND(B15<0.001,B16=0),1,0) -> 1
